{
"type": "FeatureCollection",
"name": "BRIST_179",
"crs": { "type": "name", "properties": { "name": "urn:ogc:def:crs:OGC:1.3:CRS84" } },
"features": [
{ "type": "Feature", "properties": { "osm_id": 6074755978, "name": null, "amenity": "bench", "man_made": null, "leisure": null, "playground": null, "memorial": null }, "geometry": { "type": "Point", "coordinates": [ -2.5780235, 51.4415479 ] } },
{ "type": "Feature", "properties": { "osm_id": 10305059021, "name": null, "amenity": "bench", "man_made": null, "leisure": null, "playground": null, "memorial": null }, "geometry": { "type": "Point", "coordinates": [ -2.5780331, 51.4415783 ] } }
]
}
