{
"type": "FeatureCollection",
"name": "BRIST_79",
"crs": { "type": "name", "properties": { "name": "urn:ogc:def:crs:OGC:1.3:CRS84" } },
"features": [
{ "type": "Feature", "properties": { "osm_id": 12383387238, "name": null, "amenity": "bench", "man_made": null, "leisure": null, "playground": null, "memorial": null }, "geometry": { "type": "Point", "coordinates": [ -2.6190688, 51.4360229 ] } },
{ "type": "Feature", "properties": { "osm_id": 12383393741, "name": null, "amenity": "bench", "man_made": null, "leisure": null, "playground": null, "memorial": null }, "geometry": { "type": "Point", "coordinates": [ -2.6185875, 51.4362941 ] } },
{ "type": "Feature", "properties": { "osm_id": 12383387998, "name": null, "amenity": null, "man_made": null, "leisure": "picnic_table", "playground": null, "memorial": null }, "geometry": { "type": "Point", "coordinates": [ -2.6188185, 51.4363863 ] } }
]
}
