{
"type": "FeatureCollection",
"name": "BRIST_149",
"crs": { "type": "name", "properties": { "name": "urn:ogc:def:crs:OGC:1.3:CRS84" } },
"features": [
{ "type": "Feature", "properties": { "osm_id": 8842326904, "name": null, "amenity": "bench", "man_made": null, "leisure": null, "playground": null, "memorial": null }, "geometry": { "type": "Point", "coordinates": [ -2.5634507, 51.4552264 ] } },
{ "type": "Feature", "properties": { "osm_id": 8842326606, "name": null, "amenity": "bench", "man_made": null, "leisure": null, "playground": null, "memorial": null }, "geometry": { "type": "Point", "coordinates": [ -2.5637767, 51.4552293 ] } },
{ "type": "Feature", "properties": { "osm_id": 8842326528, "name": null, "amenity": "bench", "man_made": null, "leisure": null, "playground": null, "memorial": null }, "geometry": { "type": "Point", "coordinates": [ -2.5635011, 51.4552439 ] } },
{ "type": "Feature", "properties": { "osm_id": 12787833028, "name": null, "amenity": "bench", "man_made": null, "leisure": null, "playground": null, "memorial": null }, "geometry": { "type": "Point", "coordinates": [ -2.5630337, 51.4553524 ] } },
{ "type": "Feature", "properties": { "osm_id": 12787841193, "name": null, "amenity": "bench", "man_made": null, "leisure": null, "playground": null, "memorial": null }, "geometry": { "type": "Point", "coordinates": [ -2.5634189, 51.4554003 ] } },
{ "type": "Feature", "properties": { "osm_id": 12787823929, "name": null, "amenity": "bench", "man_made": null, "leisure": null, "playground": null, "memorial": null }, "geometry": { "type": "Point", "coordinates": [ -2.5626718, 51.4554006 ] } },
{ "type": "Feature", "properties": { "osm_id": 8842326530, "name": null, "amenity": "bench", "man_made": null, "leisure": null, "playground": null, "memorial": null }, "geometry": { "type": "Point", "coordinates": [ -2.5623032, 51.4554834 ] } },
{ "type": "Feature", "properties": { "osm_id": 12787840473, "name": null, "amenity": "bench", "man_made": null, "leisure": null, "playground": null, "memorial": null }, "geometry": { "type": "Point", "coordinates": [ -2.5625226, 51.455848 ] } },
{ "type": "Feature", "properties": { "osm_id": 12787833027, "name": null, "amenity": null, "man_made": null, "leisure": "picnic_table", "playground": null, "memorial": null }, "geometry": { "type": "Point", "coordinates": [ -2.5636296, 51.4552252 ] } }
]
}
