{
"type": "FeatureCollection",
"name": "BRIST_227",
"crs": { "type": "name", "properties": { "name": "urn:ogc:def:crs:OGC:1.3:CRS84" } },
"features": [
{ "type": "Feature", "properties": { "osm_id": 1852014114, "name": null, "amenity": "bench", "man_made": null, "leisure": null, "playground": null, "memorial": null }, "geometry": { "type": "Point", "coordinates": [ -2.6001465, 51.4687206 ] } },
{ "type": "Feature", "properties": { "osm_id": 1852014122, "name": null, "amenity": "bench", "man_made": null, "leisure": null, "playground": null, "memorial": null }, "geometry": { "type": "Point", "coordinates": [ -2.6003406, 51.4689808 ] } },
{ "type": "Feature", "properties": { "osm_id": 10241611980, "name": null, "amenity": "bench", "man_made": null, "leisure": null, "playground": null, "memorial": null }, "geometry": { "type": "Point", "coordinates": [ -2.6004512, 51.46905 ] } },
{ "type": "Feature", "properties": { "osm_id": 1852014125, "name": null, "amenity": "bench", "man_made": null, "leisure": null, "playground": null, "memorial": null }, "geometry": { "type": "Point", "coordinates": [ -2.6005102, 51.4691389 ] } },
{ "type": "Feature", "properties": { "osm_id": 1852014129, "name": null, "amenity": "bench", "man_made": null, "leisure": null, "playground": null, "memorial": null }, "geometry": { "type": "Point", "coordinates": [ -2.6006949, 51.469348 ] } },
{ "type": "Feature", "properties": { "osm_id": 1852014133, "name": null, "amenity": "bench", "man_made": null, "leisure": null, "playground": null, "memorial": null }, "geometry": { "type": "Point", "coordinates": [ -2.6009019, 51.4695746 ] } },
{ "type": "Feature", "properties": { "osm_id": 1852014137, "name": null, "amenity": "bench", "man_made": null, "leisure": null, "playground": null, "memorial": null }, "geometry": { "type": "Point", "coordinates": [ -2.601025, 51.4697245 ] } }
]
}
