{
"type": "FeatureCollection",
"name": "SOUGL_37_toilets",
"crs": { "type": "name", "properties": { "name": "urn:ogc:def:crs:OGC:1.3:CRS84" } },
"features": [
{ "type": "Feature", "properties": { "name": "Unknown", "payment_info": "Free", "accessible": "False", "radar": "Unknown", "women": "Unknown", "men": "Unknown", "baby_change": "Unknown", "Mon": "Unknown", "Tue": "Unknown", "Wed": "Unknown", "Thu": "Unknown", "Fri": "Unknown", "Sat": "Unknown", "Sun": "Unknown", "index_right": 136, "park_offical_id": "SOUGL_37" }, "geometry": { "type": "Point", "coordinates": [ -2.4154113, 51.5346428 ] } },
{ "type": "Feature", "properties": { "name": "Morrisons Yate", "payment_info": "Free", "accessible": "False", "radar": "False", "women": "True", "men": "True", "baby_change": "Unknown", "Mon": "07:00-22:00", "Tue": "07:00-22:00", "Wed": "07:00-22:00", "Thu": "07:00-22:00", "Fri": "07:00-22:00", "Sat": "07:00-22:00", "Sun": "10:00-16:00", "index_right": 136, "park_offical_id": "SOUGL_37" }, "geometry": { "type": "Point", "coordinates": [ -2.417727113, 51.541681045 ] } },
{ "type": "Feature", "properties": { "name": "Yate Shopping Centre West Walk", "payment_info": "Free", "accessible": "True", "radar": "Unknown", "women": "True", "men": "True", "baby_change": "True", "Mon": "08:00-18:00", "Tue": "08:00-18:00", "Wed": "08:00-18:00", "Thu": "08:00-18:00", "Fri": "08:00-18:00", "Sat": "08:00-18:00", "Sun": "10:00-16:00", "index_right": 136, "park_offical_id": "SOUGL_37" }, "geometry": { "type": "Point", "coordinates": [ -2.414248288, 51.540314788 ] } }
]
}
