{
"type": "FeatureCollection",
"name": "SOUGL_48_toilets",
"crs": { "type": "name", "properties": { "name": "urn:ogc:def:crs:OGC:1.3:CRS84" } },
"features": [
{ "type": "Feature", "properties": { "name": "The Hub", "payment_info": "Free", "accessible": "True", "radar": "Unknown", "women": "True", "men": "True", "baby_change": "True", "Mon": "09:00-17:00", "Tue": "09:00-17:00", "Wed": "09:00-17:00", "Thu": "09:00-17:00", "Fri": "09:00-17:00", "Sat": "Closed", "Sun": "Closed", "index_right": 160, "park_offical_id": "SOUGL_48" }, "geometry": { "type": "Point", "coordinates": [ -2.576640334, 51.531213637 ] } }
]
}
