{
"type": "FeatureCollection",
"name": "SOUGL_11_toilets",
"crs": { "type": "name", "properties": { "name": "urn:ogc:def:crs:OGC:1.3:CRS84" } },
"features": [
{ "type": "Feature", "properties": { "name": "Unknown", "payment_info": "Free", "accessible": "False", "radar": "Unknown", "women": "Unknown", "men": "Unknown", "baby_change": "Unknown", "Mon": "Unknown", "Tue": "Unknown", "Wed": "Unknown", "Thu": "Unknown", "Fri": "Unknown", "Sat": "Unknown", "Sun": "Unknown", "index_right": 13, "park_offical_id": "SOUGL_11" }, "geometry": { "type": "Point", "coordinates": [ -2.502291799, 51.462114146 ] } },
{ "type": "Feature", "properties": { "name": "Moravian Road Public Toilets", "payment_info": "Free", "accessible": "True", "radar": "False", "women": "True", "men": "True", "baby_change": "False", "Mon": "Unknown", "Tue": "Unknown", "Wed": "Unknown", "Thu": "Unknown", "Fri": "Unknown", "Sat": "Unknown", "Sun": "Unknown", "index_right": 13, "park_offical_id": "SOUGL_11" }, "geometry": { "type": "Point", "coordinates": [ -2.508058548, 51.462052315 ] } }
]
}
