{
"type": "FeatureCollection",
"name": "35f569df8d52_visibility",
"crs": { "type": "name", "properties": { "name": "urn:ogc:def:crs:OGC:1.3:CRS84" } },
"features": [
{ "type": "Feature", "properties": { "visible_points": 0, "total_points": 53, "visibility_pct": 0.0 }, "geometry": { "type": "Point", "coordinates": [ -3.382822172612309, 50.94040050486462 ] } },
{ "type": "Feature", "properties": { "visible_points": 2, "total_points": 54, "visibility_pct": 3.7037037037037033 }, "geometry": { "type": "Point", "coordinates": [ -3.3829239519351, 50.940507214986113 ] } },
{ "type": "Feature", "properties": { "visible_points": 1, "total_points": 56, "visibility_pct": 1.7857142857142856 }, "geometry": { "type": "Point", "coordinates": [ -3.382726794156121, 50.940509550046748 ] } },
{ "type": "Feature", "properties": { "visible_points": 0, "total_points": 56, "visibility_pct": 0.0 }, "geometry": { "type": "Point", "coordinates": [ -3.382529636351055, 50.940511884774729 ] } },
{ "type": "Feature", "properties": { "visible_points": 3, "total_points": 54, "visibility_pct": 5.5555555555555554 }, "geometry": { "type": "Point", "coordinates": [ -3.38302573172319, 50.940613925009615 ] } },
{ "type": "Feature", "properties": { "visible_points": 0, "total_points": 56, "visibility_pct": 0.0 }, "geometry": { "type": "Point", "coordinates": [ -3.382828573504999, 50.940616260249151 ] } },
{ "type": "Feature", "properties": { "visible_points": 0, "total_points": 56, "visibility_pct": 0.0 }, "geometry": { "type": "Point", "coordinates": [ -3.382631415260715, 50.940618595156032 ] } },
{ "type": "Feature", "properties": { "visible_points": 0, "total_points": 56, "visibility_pct": 0.0 }, "geometry": { "type": "Point", "coordinates": [ -3.382434256990332, 50.940620929730301 ] } },
{ "type": "Feature", "properties": { "visible_points": 6, "total_points": 53, "visibility_pct": 11.320754716981133 }, "geometry": { "type": "Point", "coordinates": [ -3.383127511976589, 50.940720634935111 ] } },
{ "type": "Feature", "properties": { "visible_points": 2, "total_points": 56, "visibility_pct": 3.5714285714285712 }, "geometry": { "type": "Point", "coordinates": [ -3.382930353319181, 50.940722970353541 ] } },
{ "type": "Feature", "properties": { "visible_points": 1, "total_points": 56, "visibility_pct": 1.7857142857142856 }, "geometry": { "type": "Point", "coordinates": [ -3.382733194635679, 50.940725305439337 ] } },
{ "type": "Feature", "properties": { "visible_points": 0, "total_points": 56, "visibility_pct": 0.0 }, "geometry": { "type": "Point", "coordinates": [ -3.382536035926079, 50.940727640192492 ] } },
{ "type": "Feature", "properties": { "visible_points": 0, "total_points": 56, "visibility_pct": 0.0 }, "geometry": { "type": "Point", "coordinates": [ -3.382338877190387, 50.940729974613021 ] } },
{ "type": "Feature", "properties": { "visible_points": 8, "total_points": 50, "visibility_pct": 16.0 }, "geometry": { "type": "Point", "coordinates": [ -3.383229292695299, 50.940827344762567 ] } },
{ "type": "Feature", "properties": { "visible_points": 5, "total_points": 56, "visibility_pct": 8.9285714285714288 }, "geometry": { "type": "Point", "coordinates": [ -3.383032133598672, 50.940829680359904 ] } },
{ "type": "Feature", "properties": { "visible_points": 5, "total_points": 56, "visibility_pct": 8.9285714285714288 }, "geometry": { "type": "Point", "coordinates": [ -3.382834974475947, 50.940832015624608 ] } },
{ "type": "Feature", "properties": { "visible_points": 0, "total_points": 56, "visibility_pct": 0.0 }, "geometry": { "type": "Point", "coordinates": [ -3.382637815327127, 50.940834350556699 ] } },
{ "type": "Feature", "properties": { "visible_points": 0, "total_points": 55, "visibility_pct": 0.0 }, "geometry": { "type": "Point", "coordinates": [ -3.382440656152213, 50.940836685156107 ] } },
{ "type": "Feature", "properties": { "visible_points": 0, "total_points": 49, "visibility_pct": 0.0 }, "geometry": { "type": "Point", "coordinates": [ -3.382243496951212, 50.940839019422924 ] } },
{ "type": "Feature", "properties": { "visible_points": 7, "total_points": 53, "visibility_pct": 13.20754716981132 }, "geometry": { "type": "Point", "coordinates": [ -3.382936754781529, 50.940938725711895 ] } },
{ "type": "Feature", "properties": { "visible_points": 5, "total_points": 53, "visibility_pct": 9.433962264150944 }, "geometry": { "type": "Point", "coordinates": [ -3.382739595193487, 50.940941060822873 ] } },
{ "type": "Feature", "properties": { "visible_points": 0, "total_points": 52, "visibility_pct": 0.0 }, "geometry": { "type": "Point", "coordinates": [ -3.382542435579346, 50.940943395601202 ] } },
{ "type": "Feature", "properties": { "visible_points": 1, "total_points": 48, "visibility_pct": 2.083333333333333 }, "geometry": { "type": "Point", "coordinates": [ -3.382345275939118, 50.940945730046927 ] } }
]
}
