{
"type": "FeatureCollection",
"name": "4c06619f09bb_visibility",
"crs": { "type": "name", "properties": { "name": "urn:ogc:def:crs:OGC:1.3:CRS84" } },
"features": [
{ "type": "Feature", "properties": { "visible_points": 2, "total_points": 55, "visibility_pct": 3.6363636363636362 }, "geometry": { "type": "Point", "coordinates": [ -3.467812405486919, 50.99530168774907 ] } },
{ "type": "Feature", "properties": { "visible_points": 0, "total_points": 55, "visibility_pct": 0.0 }, "geometry": { "type": "Point", "coordinates": [ -3.46761502284523, 50.995304168302624 ] } },
{ "type": "Feature", "properties": { "visible_points": 0, "total_points": 54, "visibility_pct": 0.0 }, "geometry": { "type": "Point", "coordinates": [ -3.467417640154118, 50.995306648519374 ] } },
{ "type": "Feature", "properties": { "visible_points": 1, "total_points": 49, "visibility_pct": 2.0408163265306123 }, "geometry": { "type": "Point", "coordinates": [ -3.467220257435205, 50.995309128402617 ] } },
{ "type": "Feature", "properties": { "visible_points": 0, "total_points": 43, "visibility_pct": 0.0 }, "geometry": { "type": "Point", "coordinates": [ -3.467022874688489, 50.995311607952345 ] } },
{ "type": "Feature", "properties": { "visible_points": 0, "total_points": 48, "visibility_pct": 0.0 }, "geometry": { "type": "Point", "coordinates": [ -3.468111883837499, 50.995405840097249 ] } },
{ "type": "Feature", "properties": { "visible_points": 0, "total_points": 54, "visibility_pct": 0.0 }, "geometry": { "type": "Point", "coordinates": [ -3.467914501109509, 50.995408321271988 ] } },
{ "type": "Feature", "properties": { "visible_points": 1, "total_points": 55, "visibility_pct": 1.8181818181818181 }, "geometry": { "type": "Point", "coordinates": [ -3.467717118128805, 50.995410802023464 ] } },
{ "type": "Feature", "properties": { "visible_points": 3, "total_points": 55, "visibility_pct": 5.4545454545454541 }, "geometry": { "type": "Point", "coordinates": [ -3.467519734997383, 50.995413282414482 ] } },
{ "type": "Feature", "properties": { "visible_points": 4, "total_points": 54, "visibility_pct": 7.4074074074074066 }, "geometry": { "type": "Point", "coordinates": [ -3.467322351838154, 50.995415762472 ] } },
{ "type": "Feature", "properties": { "visible_points": 6, "total_points": 48, "visibility_pct": 12.5 }, "geometry": { "type": "Point", "coordinates": [ -3.467124968651131, 50.99541824219601 ] } },
{ "type": "Feature", "properties": { "visible_points": 4, "total_points": 50, "visibility_pct": 8.0 }, "geometry": { "type": "Point", "coordinates": [ -3.468016597157101, 50.99551495466838 ] } },
{ "type": "Feature", "properties": { "visible_points": 3, "total_points": 54, "visibility_pct": 5.5555555555555554 }, "geometry": { "type": "Point", "coordinates": [ -3.467819213853033, 50.99551743564691 ] } },
{ "type": "Feature", "properties": { "visible_points": 3, "total_points": 55, "visibility_pct": 5.4545454545454541 }, "geometry": { "type": "Point", "coordinates": [ -3.467621830308753, 50.995519916216608 ] } },
{ "type": "Feature", "properties": { "visible_points": 0, "total_points": 55, "visibility_pct": 0.0 }, "geometry": { "type": "Point", "coordinates": [ -3.467424446709213, 50.995522396448401 ] } },
{ "type": "Feature", "properties": { "visible_points": 12, "total_points": 52, "visibility_pct": 23.076923076923077 }, "geometry": { "type": "Point", "coordinates": [ -3.46722706308187, 50.995524876346678 ] } },
{ "type": "Feature", "properties": { "visible_points": 5, "total_points": 45, "visibility_pct": 11.111111111111111 }, "geometry": { "type": "Point", "coordinates": [ -3.468118693609534, 50.995621587958645 ] } },
{ "type": "Feature", "properties": { "visible_points": 4, "total_points": 51, "visibility_pct": 7.8431372549019605 }, "geometry": { "type": "Point", "coordinates": [ -3.467921309972095, 50.995624069154445 ] } },
{ "type": "Feature", "properties": { "visible_points": 2, "total_points": 54, "visibility_pct": 3.7037037037037033 }, "geometry": { "type": "Point", "coordinates": [ -3.467723926088234, 50.995626549925717 ] } },
{ "type": "Feature", "properties": { "visible_points": 12, "total_points": 55, "visibility_pct": 21.818181818181817 }, "geometry": { "type": "Point", "coordinates": [ -3.467526542048379, 50.995629030331799 ] } },
{ "type": "Feature", "properties": { "visible_points": 6, "total_points": 45, "visibility_pct": 13.333333333333334 }, "geometry": { "type": "Point", "coordinates": [ -3.468023406512613, 50.99573070253566 ] } }
]
}
