{
"type": "FeatureCollection",
"name": "7261005c71c4_visibility",
"crs": { "type": "name", "properties": { "name": "urn:ogc:def:crs:OGC:1.3:CRS84" } },
"features": [
{ "type": "Feature", "properties": { "visible_points": 0, "total_points": 45, "visibility_pct": 0.0 }, "geometry": { "type": "Point", "coordinates": [ -3.495526953829613, 50.975476084049582 ] } },
{ "type": "Feature", "properties": { "visible_points": 0, "total_points": 50, "visibility_pct": 0.0 }, "geometry": { "type": "Point", "coordinates": [ -3.495329658180757, 50.975478610861579 ] } },
{ "type": "Feature", "properties": { "visible_points": 6, "total_points": 45, "visibility_pct": 13.333333333333334 }, "geometry": { "type": "Point", "coordinates": [ -3.495629067887792, 50.975582693363222 ] } },
{ "type": "Feature", "properties": { "visible_points": 1, "total_points": 52, "visibility_pct": 1.9230769230769231 }, "geometry": { "type": "Point", "coordinates": [ -3.495431771802243, 50.97558522035191 ] } },
{ "type": "Feature", "properties": { "visible_points": 0, "total_points": 56, "visibility_pct": 0.0 }, "geometry": { "type": "Point", "coordinates": [ -3.4952344756883, 50.975587747007403 ] } },
{ "type": "Feature", "properties": { "visible_points": 1, "total_points": 58, "visibility_pct": 1.7241379310344827 }, "geometry": { "type": "Point", "coordinates": [ -3.495037179545977, 50.975590273329757 ] } },
{ "type": "Feature", "properties": { "visible_points": 5, "total_points": 52, "visibility_pct": 9.6153846153846168 }, "geometry": { "type": "Point", "coordinates": [ -3.495533885981003, 50.975691829766554 ] } },
{ "type": "Feature", "properties": { "visible_points": 4, "total_points": 57, "visibility_pct": 7.0175438596491224 }, "geometry": { "type": "Point", "coordinates": [ -3.495336589425843, 50.975694356597998 ] } },
{ "type": "Feature", "properties": { "visible_points": 0, "total_points": 59, "visibility_pct": 0.0 }, "geometry": { "type": "Point", "coordinates": [ -3.49513929284229, 50.975696883096241 ] } },
{ "type": "Feature", "properties": { "visible_points": 0, "total_points": 59, "visibility_pct": 0.0 }, "geometry": { "type": "Point", "coordinates": [ -3.494941996230344, 50.975699409261296 ] } },
{ "type": "Feature", "properties": { "visible_points": 1, "total_points": 56, "visibility_pct": 1.7857142857142856 }, "geometry": { "type": "Point", "coordinates": [ -3.494744699590012, 50.975701935093163 ] } },
{ "type": "Feature", "properties": { "visible_points": 3, "total_points": 59, "visibility_pct": 5.0847457627118651 }, "geometry": { "type": "Point", "coordinates": [ -3.49524140660851, 50.975803492768264 ] } },
{ "type": "Feature", "properties": { "visible_points": 0, "total_points": 59, "visibility_pct": 0.0 }, "geometry": { "type": "Point", "coordinates": [ -3.495044109555039, 50.975806019108937 ] } },
{ "type": "Feature", "properties": { "visible_points": 3, "total_points": 57, "visibility_pct": 5.2631578947368416 }, "geometry": { "type": "Point", "coordinates": [ -3.494846812473177, 50.975808545116436 ] } },
{ "type": "Feature", "properties": { "visible_points": 3, "total_points": 52, "visibility_pct": 5.7692307692307692 }, "geometry": { "type": "Point", "coordinates": [ -3.494649515362931, 50.975811070790712 ] } },
{ "type": "Feature", "properties": { "visible_points": 2, "total_points": 59, "visibility_pct": 3.3898305084745761 }, "geometry": { "type": "Point", "coordinates": [ -3.495146223349642, 50.975912628862112 ] } },
{ "type": "Feature", "properties": { "visible_points": 0, "total_points": 56, "visibility_pct": 0.0 }, "geometry": { "type": "Point", "coordinates": [ -3.494948925826252, 50.975915155045215 ] } },
{ "type": "Feature", "properties": { "visible_points": 0, "total_points": 51, "visibility_pct": 0.0 }, "geometry": { "type": "Point", "coordinates": [ -3.494751628274474, 50.97591768089513 ] } },
{ "type": "Feature", "properties": { "visible_points": 0, "total_points": 49, "visibility_pct": 0.0 }, "geometry": { "type": "Point", "coordinates": [ -3.494853741655929, 50.976024290905102 ] } },
{ "type": "Feature", "properties": { "visible_points": 0, "total_points": 45, "visibility_pct": 0.0 }, "geometry": { "type": "Point", "coordinates": [ -3.49465644363423, 50.976026816597425 ] } }
]
}
