{
"type": "FeatureCollection",
"name": "dc8c115c1fc2_visibility",
"crs": { "type": "name", "properties": { "name": "urn:ogc:def:crs:OGC:1.3:CRS84" } },
"features": [
{ "type": "Feature", "properties": { "visible_points": 0, "total_points": 53, "visibility_pct": 0.0 }, "geometry": { "type": "Point", "coordinates": [ -3.286801486564261, 50.869696680141139 ] } },
{ "type": "Feature", "properties": { "visible_points": 0, "total_points": 53, "visibility_pct": 0.0 }, "geometry": { "type": "Point", "coordinates": [ -3.286604619598202, 50.869698850216672 ] } },
{ "type": "Feature", "properties": { "visible_points": 2, "total_points": 50, "visibility_pct": 4.0 }, "geometry": { "type": "Point", "coordinates": [ -3.286407752607879, 50.869701019960132 ] } },
{ "type": "Feature", "properties": { "visible_points": 0, "total_points": 58, "visibility_pct": 0.0 }, "geometry": { "type": "Point", "coordinates": [ -3.286902891452072, 50.86980347939592 ] } },
{ "type": "Feature", "properties": { "visible_points": 0, "total_points": 59, "visibility_pct": 0.0 }, "geometry": { "type": "Point", "coordinates": [ -3.286706024045732, 50.869805649644036 ] } },
{ "type": "Feature", "properties": { "visible_points": 0, "total_points": 58, "visibility_pct": 0.0 }, "geometry": { "type": "Point", "coordinates": [ -3.286509156615125, 50.86980781956008 ] } },
{ "type": "Feature", "properties": { "visible_points": 0, "total_points": 57, "visibility_pct": 0.0 }, "geometry": { "type": "Point", "coordinates": [ -3.287201164626768, 50.869908107806275 ] } },
{ "type": "Feature", "properties": { "visible_points": 0, "total_points": 61, "visibility_pct": 0.0 }, "geometry": { "type": "Point", "coordinates": [ -3.287004296804422, 50.869910278559054 ] } },
{ "type": "Feature", "properties": { "visible_points": 1, "total_points": 62, "visibility_pct": 1.6129032258064515 }, "geometry": { "type": "Point", "coordinates": [ -3.286807428957803, 50.86991244897974 ] } },
{ "type": "Feature", "properties": { "visible_points": 0, "total_points": 62, "visibility_pct": 0.0 }, "geometry": { "type": "Point", "coordinates": [ -3.286610561086911, 50.869914619068382 ] } },
{ "type": "Feature", "properties": { "visible_points": 2, "total_points": 62, "visibility_pct": 3.225806451612903 }, "geometry": { "type": "Point", "coordinates": [ -3.286413693191755, 50.869916788824945 ] } },
{ "type": "Feature", "properties": { "visible_points": 0, "total_points": 61, "visibility_pct": 0.0 }, "geometry": { "type": "Point", "coordinates": [ -3.287105702621322, 50.870017077630543 ] } },
{ "type": "Feature", "properties": { "visible_points": 0, "total_points": 62, "visibility_pct": 0.0 }, "geometry": { "type": "Point", "coordinates": [ -3.286908834334417, 50.870019248223826 ] } },
{ "type": "Feature", "properties": { "visible_points": 0, "total_points": 62, "visibility_pct": 0.0 }, "geometry": { "type": "Point", "coordinates": [ -3.286711966023244, 50.870021418485045 ] } },
{ "type": "Feature", "properties": { "visible_points": 1, "total_points": 62, "visibility_pct": 1.6129032258064515 }, "geometry": { "type": "Point", "coordinates": [ -3.286515097687798, 50.870023588414206 ] } },
{ "type": "Feature", "properties": { "visible_points": 3, "total_points": 60, "visibility_pct": 5.0 }, "geometry": { "type": "Point", "coordinates": [ -3.287010240175582, 50.87012604737626 ] } },
{ "type": "Feature", "properties": { "visible_points": 2, "total_points": 62, "visibility_pct": 3.225806451612903 }, "geometry": { "type": "Point", "coordinates": [ -3.28681337142412, 50.87012821781007 ] } },
{ "type": "Feature", "properties": { "visible_points": 3, "total_points": 62, "visibility_pct": 4.838709677419355 }, "geometry": { "type": "Point", "coordinates": [ -3.28661650264839, 50.870130387911814 ] } },
{ "type": "Feature", "properties": { "visible_points": 4, "total_points": 56, "visibility_pct": 7.1428571428571423 }, "geometry": { "type": "Point", "coordinates": [ -3.286914777289551, 50.870235017043449 ] } },
{ "type": "Feature", "properties": { "visible_points": 2, "total_points": 57, "visibility_pct": 3.5087719298245612 }, "geometry": { "type": "Point", "coordinates": [ -3.286717908073525, 50.870237187317784 ] } },
{ "type": "Feature", "properties": { "visible_points": 0, "total_points": 57, "visibility_pct": 0.0 }, "geometry": { "type": "Point", "coordinates": [ -3.286521038833237, 50.870239357260047 ] } },
{ "type": "Feature", "properties": { "visible_points": 5, "total_points": 51, "visibility_pct": 9.8039215686274517 }, "geometry": { "type": "Point", "coordinates": [ -3.28681931396322, 50.870343986632115 ] } },
{ "type": "Feature", "properties": { "visible_points": 3, "total_points": 51, "visibility_pct": 5.8823529411764701 }, "geometry": { "type": "Point", "coordinates": [ -3.286622444282631, 50.870346156746962 ] } }
]
}
