{
"type": "FeatureCollection",
"name": "fa6dd45c71cc_visibility",
"crs": { "type": "name", "properties": { "name": "urn:ogc:def:crs:OGC:1.3:CRS84" } },
"features": [
{ "type": "Feature", "properties": { "visible_points": 0, "total_points": 51, "visibility_pct": 0.0 }, "geometry": { "type": "Point", "coordinates": [ -3.439077399621443, 50.952831440455583 ] } },
{ "type": "Feature", "properties": { "visible_points": 0, "total_points": 58, "visibility_pct": 0.0 }, "geometry": { "type": "Point", "coordinates": [ -3.438880193425618, 50.952833870953313 ] } },
{ "type": "Feature", "properties": { "visible_points": 4, "total_points": 62, "visibility_pct": 6.4516129032258061 }, "geometry": { "type": "Point", "coordinates": [ -3.438682987202305, 50.952836301118012 ] } },
{ "type": "Feature", "properties": { "visible_points": 3, "total_points": 63, "visibility_pct": 4.7619047619047619 }, "geometry": { "type": "Point", "coordinates": [ -3.438485780951512, 50.952838730949615 ] } },
{ "type": "Feature", "properties": { "visible_points": 0, "total_points": 51, "visibility_pct": 0.0 }, "geometry": { "type": "Point", "coordinates": [ -3.439179335736225, 50.952938100845067 ] } },
{ "type": "Feature", "properties": { "visible_points": 0, "total_points": 58, "visibility_pct": 0.0 }, "geometry": { "type": "Point", "coordinates": [ -3.438982129094672, 50.95294053151536 ] } },
{ "type": "Feature", "properties": { "visible_points": 0, "total_points": 63, "visibility_pct": 0.0 }, "geometry": { "type": "Point", "coordinates": [ -3.438784922425634, 50.952942961852571 ] } },
{ "type": "Feature", "properties": { "visible_points": 1, "total_points": 63, "visibility_pct": 1.5873015873015872 }, "geometry": { "type": "Point", "coordinates": [ -3.438587715729112, 50.952945391856737 ] } },
{ "type": "Feature", "properties": { "visible_points": 1, "total_points": 63, "visibility_pct": 1.5873015873015872 }, "geometry": { "type": "Point", "coordinates": [ -3.438390509005111, 50.952947821527815 ] } },
{ "type": "Feature", "properties": { "visible_points": 0, "total_points": 57, "visibility_pct": 0.0 }, "geometry": { "type": "Point", "coordinates": [ -3.438193302253633, 50.952950250865847 ] } },
{ "type": "Feature", "properties": { "visible_points": 0, "total_points": 49, "visibility_pct": 0.0 }, "geometry": { "type": "Point", "coordinates": [ -3.437996095474686, 50.952952679870805 ] } },
{ "type": "Feature", "properties": { "visible_points": 0, "total_points": 56, "visibility_pct": 0.0 }, "geometry": { "type": "Point", "coordinates": [ -3.439084065236935, 50.953047191986059 ] } },
{ "type": "Feature", "properties": { "visible_points": 0, "total_points": 63, "visibility_pct": 0.0 }, "geometry": { "type": "Point", "coordinates": [ -3.438886858122165, 50.953049622495818 ] } },
{ "type": "Feature", "properties": { "visible_points": 0, "total_points": 63, "visibility_pct": 0.0 }, "geometry": { "type": "Point", "coordinates": [ -3.438689650979917, 50.953052052672518 ] } },
{ "type": "Feature", "properties": { "visible_points": 3, "total_points": 63, "visibility_pct": 4.7619047619047619 }, "geometry": { "type": "Point", "coordinates": [ -3.438492443810181, 50.953054482516158 ] } },
{ "type": "Feature", "properties": { "visible_points": 0, "total_points": 59, "visibility_pct": 0.0 }, "geometry": { "type": "Point", "coordinates": [ -3.438295236612969, 50.95305691202671 ] } },
{ "type": "Feature", "properties": { "visible_points": 0, "total_points": 53, "visibility_pct": 0.0 }, "geometry": { "type": "Point", "coordinates": [ -3.438098029388288, 50.953059341204209 ] } },
{ "type": "Feature", "properties": { "visible_points": 0, "total_points": 63, "visibility_pct": 0.0 }, "geometry": { "type": "Point", "coordinates": [ -3.438791586703923, 50.953158713396988 ] } },
{ "type": "Feature", "properties": { "visible_points": 0, "total_points": 63, "visibility_pct": 0.0 }, "geometry": { "type": "Point", "coordinates": [ -3.438594379088458, 50.953161143413155 ] } },
{ "type": "Feature", "properties": { "visible_points": 0, "total_points": 60, "visibility_pct": 0.0 }, "geometry": { "type": "Point", "coordinates": [ -3.438397171445508, 50.953163573096269 ] } },
{ "type": "Feature", "properties": { "visible_points": 0, "total_points": 54, "visibility_pct": 0.0 }, "geometry": { "type": "Point", "coordinates": [ -3.438199963775088, 50.953166002446324 ] } },
{ "type": "Feature", "properties": { "visible_points": 0, "total_points": 62, "visibility_pct": 0.0 }, "geometry": { "type": "Point", "coordinates": [ -3.438696314839936, 50.953267804218854 ] } },
{ "type": "Feature", "properties": { "visible_points": 0, "total_points": 59, "visibility_pct": 0.0 }, "geometry": { "type": "Point", "coordinates": [ -3.438499106751252, 50.953270234074509 ] } },
{ "type": "Feature", "properties": { "visible_points": 0, "total_points": 54, "visibility_pct": 0.0 }, "geometry": { "type": "Point", "coordinates": [ -3.438301898635089, 50.953272663597083 ] } }
]
}
