{
"type": "FeatureCollection",
"name": "04c04951d3d0_visibility",
"crs": { "type": "name", "properties": { "name": "urn:ogc:def:crs:OGC:1.3:CRS84" } },
"features": [
{ "type": "Feature", "properties": { "visible_points": 0, "total_points": 53, "visibility_pct": 0.0 }, "geometry": { "type": "Point", "coordinates": [ -1.873937628077993, 50.736959803483977 ] } },
{ "type": "Feature", "properties": { "visible_points": 0, "total_points": 58, "visibility_pct": 0.0 }, "geometry": { "type": "Point", "coordinates": [ -1.873741276674132, 50.736959594392864 ] } },
{ "type": "Feature", "properties": { "visible_points": 0, "total_points": 53, "visibility_pct": 0.0 }, "geometry": { "type": "Point", "coordinates": [ -1.874035516173989, 50.737067823829022 ] } },
{ "type": "Feature", "properties": { "visible_points": 8, "total_points": 59, "visibility_pct": 13.559322033898304 }, "geometry": { "type": "Point", "coordinates": [ -1.873839164320592, 50.73706761491367 ] } },
{ "type": "Feature", "properties": { "visible_points": 9, "total_points": 60, "visibility_pct": 15.0 }, "geometry": { "type": "Point", "coordinates": [ -1.873642812469577, 50.737067405667581 ] } },
{ "type": "Feature", "properties": { "visible_points": 8, "total_points": 60, "visibility_pct": 13.333333333333334 }, "geometry": { "type": "Point", "coordinates": [ -1.873446460620927, 50.737067196090777 ] } },
{ "type": "Feature", "properties": { "visible_points": 8, "total_points": 60, "visibility_pct": 13.333333333333334 }, "geometry": { "type": "Point", "coordinates": [ -1.873250108774659, 50.737066986183272 ] } },
{ "type": "Feature", "properties": { "visible_points": 0, "total_points": 58, "visibility_pct": 0.0 }, "geometry": { "type": "Point", "coordinates": [ -1.873937052414209, 50.737175635339412 ] } },
{ "type": "Feature", "properties": { "visible_points": 9, "total_points": 60, "visibility_pct": 15.0 }, "geometry": { "type": "Point", "coordinates": [ -1.873740700113649, 50.737175426269083 ] } },
{ "type": "Feature", "properties": { "visible_points": 10, "total_points": 60, "visibility_pct": 16.666666666666664 }, "geometry": { "type": "Point", "coordinates": [ -1.873544347815467, 50.737175216868032 ] } },
{ "type": "Feature", "properties": { "visible_points": 9, "total_points": 60, "visibility_pct": 15.0 }, "geometry": { "type": "Point", "coordinates": [ -1.873347995519656, 50.737175007136244 ] } },
{ "type": "Feature", "properties": { "visible_points": 10, "total_points": 57, "visibility_pct": 17.543859649122805 }, "geometry": { "type": "Point", "coordinates": [ -1.873151643226225, 50.737174797073756 ] } },
{ "type": "Feature", "properties": { "visible_points": 0, "total_points": 60, "visibility_pct": 0.0 }, "geometry": { "type": "Point", "coordinates": [ -1.873838588204884, 50.737283446775557 ] } },
{ "type": "Feature", "properties": { "visible_points": 10, "total_points": 60, "visibility_pct": 16.666666666666664 }, "geometry": { "type": "Point", "coordinates": [ -1.873642235457158, 50.737283237550237 ] } },
{ "type": "Feature", "properties": { "visible_points": 9, "total_points": 60, "visibility_pct": 15.0 }, "geometry": { "type": "Point", "coordinates": [ -1.873445882711805, 50.737283027994209 ] } },
{ "type": "Feature", "properties": { "visible_points": 11, "total_points": 58, "visibility_pct": 18.96551724137931 }, "geometry": { "type": "Point", "coordinates": [ -1.873249529968827, 50.737282818107445 ] } },
{ "type": "Feature", "properties": { "visible_points": 0, "total_points": 52, "visibility_pct": 0.0 }, "geometry": { "type": "Point", "coordinates": [ -1.873053177228237, 50.737282607889966 ] } },
{ "type": "Feature", "properties": { "visible_points": 0, "total_points": 60, "visibility_pct": 0.0 }, "geometry": { "type": "Point", "coordinates": [ -1.873740123546006, 50.737391258137421 ] } },
{ "type": "Feature", "properties": { "visible_points": 9, "total_points": 60, "visibility_pct": 15.0 }, "geometry": { "type": "Point", "coordinates": [ -1.873543770351108, 50.737391048757111 ] } },
{ "type": "Feature", "properties": { "visible_points": 10, "total_points": 57, "visibility_pct": 17.543859649122805 }, "geometry": { "type": "Point", "coordinates": [ -1.873347417158585, 50.7373908390461 ] } },
{ "type": "Feature", "properties": { "visible_points": 1, "total_points": 52, "visibility_pct": 1.9230769230769231 }, "geometry": { "type": "Point", "coordinates": [ -1.873151063968443, 50.737390629004359 ] } },
{ "type": "Feature", "properties": { "visible_points": 0, "total_points": 56, "visibility_pct": 0.0 }, "geometry": { "type": "Point", "coordinates": [ -1.873641658437569, 50.737499069425013 ] } },
{ "type": "Feature", "properties": { "visible_points": 1, "total_points": 54, "visibility_pct": 1.8518518518518516 }, "geometry": { "type": "Point", "coordinates": [ -1.873445304795498, 50.737498859889747 ] } }
]
}
