{
"type": "FeatureCollection",
"name": "8eb37385d929_visibility",
"crs": { "type": "name", "properties": { "name": "urn:ogc:def:crs:OGC:1.3:CRS84" } },
"features": [
{ "type": "Feature", "properties": { "visible_points": 0, "total_points": 53, "visibility_pct": 0.0 }, "geometry": { "type": "Point", "coordinates": [ -1.969670332689367, 50.739093263617534 ] } },
{ "type": "Feature", "properties": { "visible_points": 11, "total_points": 56, "visibility_pct": 19.642857142857142 }, "geometry": { "type": "Point", "coordinates": [ -1.969473960822578, 50.739093209462744 ] } },
{ "type": "Feature", "properties": { "visible_points": 12, "total_points": 57, "visibility_pct": 21.052631578947366 }, "geometry": { "type": "Point", "coordinates": [ -1.969277588956364, 50.739093154977276 ] } },
{ "type": "Feature", "properties": { "visible_points": 0, "total_points": 52, "visibility_pct": 0.0 }, "geometry": { "type": "Point", "coordinates": [ -1.969768451055937, 50.739201202014279 ] } },
{ "type": "Feature", "properties": { "visible_points": 12, "total_points": 56, "visibility_pct": 21.428571428571427 }, "geometry": { "type": "Point", "coordinates": [ -1.969572078742555, 50.73920114803289 ] } },
{ "type": "Feature", "properties": { "visible_points": 13, "total_points": 57, "visibility_pct": 22.807017543859647 }, "geometry": { "type": "Point", "coordinates": [ -1.969375706429749, 50.739201093720816 ] } },
{ "type": "Feature", "properties": { "visible_points": 12, "total_points": 57, "visibility_pct": 21.052631578947366 }, "geometry": { "type": "Point", "coordinates": [ -1.969179334117524, 50.739201039078026 ] } },
{ "type": "Feature", "properties": { "visible_points": 10, "total_points": 55, "visibility_pct": 18.181818181818183 }, "geometry": { "type": "Point", "coordinates": [ -1.968982961805886, 50.739200984104549 ] } },
{ "type": "Feature", "properties": { "visible_points": 0, "total_points": 56, "visibility_pct": 0.0 }, "geometry": { "type": "Point", "coordinates": [ -1.969670197108537, 50.739309086510332 ] } },
{ "type": "Feature", "properties": { "visible_points": 13, "total_points": 57, "visibility_pct": 22.807017543859647 }, "geometry": { "type": "Point", "coordinates": [ -1.969473824349137, 50.739309032371629 ] } },
{ "type": "Feature", "properties": { "visible_points": 12, "total_points": 57, "visibility_pct": 21.052631578947366 }, "geometry": { "type": "Point", "coordinates": [ -1.969277451590315, 50.739308977902255 ] } },
{ "type": "Feature", "properties": { "visible_points": 8, "total_points": 57, "visibility_pct": 14.035087719298245 }, "geometry": { "type": "Point", "coordinates": [ -1.969081078832079, 50.739308923102172 ] } },
{ "type": "Feature", "properties": { "visible_points": 9, "total_points": 51, "visibility_pct": 17.647058823529413 }, "geometry": { "type": "Point", "coordinates": [ -1.968884706074425, 50.739308867971381 ] } },
{ "type": "Feature", "properties": { "visible_points": 0, "total_points": 53, "visibility_pct": 0.0 }, "geometry": { "type": "Point", "coordinates": [ -1.969768315920524, 50.73941702489504 ] } },
{ "type": "Feature", "properties": { "visible_points": 0, "total_points": 57, "visibility_pct": 0.0 }, "geometry": { "type": "Point", "coordinates": [ -1.969571942714529, 50.73941697092976 ] } },
{ "type": "Feature", "properties": { "visible_points": 13, "total_points": 57, "visibility_pct": 22.807017543859647 }, "geometry": { "type": "Point", "coordinates": [ -1.969375569509112, 50.739416916633758 ] } },
{ "type": "Feature", "properties": { "visible_points": 12, "total_points": 57, "visibility_pct": 21.052631578947366 }, "geometry": { "type": "Point", "coordinates": [ -1.969179196304272, 50.739416862007083 ] } },
{ "type": "Feature", "properties": { "visible_points": 0, "total_points": 54, "visibility_pct": 0.0 }, "geometry": { "type": "Point", "coordinates": [ -1.968982823100021, 50.739416807049686 ] } },
{ "type": "Feature", "properties": { "visible_points": 0, "total_points": 55, "visibility_pct": 0.0 }, "geometry": { "type": "Point", "coordinates": [ -1.969670061525929, 50.739524909395143 ] } },
{ "type": "Feature", "properties": { "visible_points": 0, "total_points": 57, "visibility_pct": 0.0 }, "geometry": { "type": "Point", "coordinates": [ -1.969473687873914, 50.739524855272563 ] } },
{ "type": "Feature", "properties": { "visible_points": 0, "total_points": 56, "visibility_pct": 0.0 }, "geometry": { "type": "Point", "coordinates": [ -1.969277314222473, 50.739524800819254 ] } },
{ "type": "Feature", "properties": { "visible_points": 0, "total_points": 53, "visibility_pct": 0.0 }, "geometry": { "type": "Point", "coordinates": [ -1.969080940571617, 50.739524746035272 ] } },
{ "type": "Feature", "properties": { "visible_points": 0, "total_points": 47, "visibility_pct": 0.0 }, "geometry": { "type": "Point", "coordinates": [ -1.968884566921347, 50.739524690920568 ] } }
]
}
