{
"type": "FeatureCollection",
"name": "6c65fb66db2a_visibility",
"crs": { "type": "name", "properties": { "name": "urn:ogc:def:crs:OGC:1.3:CRS84" } },
"features": [
{ "type": "Feature", "properties": { "visible_points": 0, "total_points": 53, "visibility_pct": 0.0 }, "geometry": { "type": "Point", "coordinates": [ -2.136459821017779, 51.003050647888244 ] } },
{ "type": "Feature", "properties": { "visible_points": 8, "total_points": 48, "visibility_pct": 16.666666666666664 }, "geometry": { "type": "Point", "coordinates": [ -2.136262344330782, 51.00305087973814 ] } },
{ "type": "Feature", "properties": { "visible_points": 1, "total_points": 57, "visibility_pct": 1.7543859649122806 }, "geometry": { "type": "Point", "coordinates": [ -2.136756354357236, 51.00315820585206 ] } },
{ "type": "Feature", "properties": { "visible_points": 5, "total_points": 57, "visibility_pct": 8.7719298245614024 }, "geometry": { "type": "Point", "coordinates": [ -2.136558877217134, 51.003158438199165 ] } },
{ "type": "Feature", "properties": { "visible_points": 6, "total_points": 54, "visibility_pct": 11.111111111111111 }, "geometry": { "type": "Point", "coordinates": [ -2.136361400074448, 51.003158670212486 ] } },
{ "type": "Feature", "properties": { "visible_points": 7, "total_points": 48, "visibility_pct": 14.583333333333334 }, "geometry": { "type": "Point", "coordinates": [ -2.136163922929179, 51.003158901891979 ] } },
{ "type": "Feature", "properties": { "visible_points": 0, "total_points": 54, "visibility_pct": 0.0 }, "geometry": { "type": "Point", "coordinates": [ -2.137052889063744, 51.003265763073301 ] } },
{ "type": "Feature", "properties": { "visible_points": 6, "total_points": 57, "visibility_pct": 10.526315789473683 }, "geometry": { "type": "Point", "coordinates": [ -2.136855411470546, 51.003265995917651 ] } },
{ "type": "Feature", "properties": { "visible_points": 8, "total_points": 57, "visibility_pct": 14.035087719298245 }, "geometry": { "type": "Point", "coordinates": [ -2.136657933874751, 51.003266228428181 ] } },
{ "type": "Feature", "properties": { "visible_points": 5, "total_points": 57, "visibility_pct": 8.7719298245614024 }, "geometry": { "type": "Point", "coordinates": [ -2.136460456276381, 51.003266460604898 ] } },
{ "type": "Feature", "properties": { "visible_points": 8, "total_points": 53, "visibility_pct": 15.09433962264151 }, "geometry": { "type": "Point", "coordinates": [ -2.136262978675413, 51.003266692447774 ] } },
{ "type": "Feature", "properties": { "visible_points": 4, "total_points": 47, "visibility_pct": 8.5106382978723403 }, "geometry": { "type": "Point", "coordinates": [ -2.13606550107187, 51.003266923956879 ] } },
{ "type": "Feature", "properties": { "visible_points": 3, "total_points": 49, "visibility_pct": 6.1224489795918364 }, "geometry": { "type": "Point", "coordinates": [ -2.137151947091011, 51.003373552893599 ] } },
{ "type": "Feature", "properties": { "visible_points": 4, "total_points": 55, "visibility_pct": 7.2727272727272725 }, "geometry": { "type": "Point", "coordinates": [ -2.136954469042127, 51.003373785901339 ] } },
{ "type": "Feature", "properties": { "visible_points": 8, "total_points": 57, "visibility_pct": 14.035087719298245 }, "geometry": { "type": "Point", "coordinates": [ -2.136756990990643, 51.003374018575258 ] } },
{ "type": "Feature", "properties": { "visible_points": 6, "total_points": 57, "visibility_pct": 10.526315789473683 }, "geometry": { "type": "Point", "coordinates": [ -2.136559512936579, 51.003374250915385 ] } },
{ "type": "Feature", "properties": { "visible_points": 7, "total_points": 57, "visibility_pct": 12.280701754385964 }, "geometry": { "type": "Point", "coordinates": [ -2.136362034879913, 51.003374482921657 ] } },
{ "type": "Feature", "properties": { "visible_points": 0, "total_points": 49, "visibility_pct": 0.0 }, "geometry": { "type": "Point", "coordinates": [ -2.137053527071982, 51.003481575803086 ] } },
{ "type": "Feature", "properties": { "visible_points": 4, "total_points": 54, "visibility_pct": 7.4074074074074066 }, "geometry": { "type": "Point", "coordinates": [ -2.136856048564808, 51.003481808640394 ] } },
{ "type": "Feature", "properties": { "visible_points": 3, "total_points": 57, "visibility_pct": 5.2631578947368416 }, "geometry": { "type": "Point", "coordinates": [ -2.136658570055041, 51.003482041143911 ] } },
{ "type": "Feature", "properties": { "visible_points": 7, "total_points": 57, "visibility_pct": 12.280701754385964 }, "geometry": { "type": "Point", "coordinates": [ -2.136461091542687, 51.003482273313608 ] } },
{ "type": "Feature", "properties": { "visible_points": 0, "total_points": 48, "visibility_pct": 0.0 }, "geometry": { "type": "Point", "coordinates": [ -2.13695510659725, 51.003589598623613 ] } },
{ "type": "Feature", "properties": { "visible_points": 8, "total_points": 52, "visibility_pct": 15.384615384615385 }, "geometry": { "type": "Point", "coordinates": [ -2.136757627631785, 51.003589831290526 ] } }
]
}
