{
"type": "FeatureCollection",
"name": "f42521cecff1_visibility",
"crs": { "type": "name", "properties": { "name": "urn:ogc:def:crs:OGC:1.3:CRS84" } },
"features": [
{ "type": "Feature", "properties": { "visible_points": 1, "total_points": 52, "visibility_pct": 1.9230769230769231 }, "geometry": { "type": "Point", "coordinates": [ -2.042764683465883, 51.463234795387272 ] } },
{ "type": "Feature", "properties": { "visible_points": 1, "total_points": 55, "visibility_pct": 1.8181818181818181 }, "geometry": { "type": "Point", "coordinates": [ -2.04256522287894, 51.463234867895835 ] } },
{ "type": "Feature", "properties": { "visible_points": 9, "total_points": 56, "visibility_pct": 16.071428571428573 }, "geometry": { "type": "Point", "coordinates": [ -2.04236576229118, 51.463234940065078 ] } },
{ "type": "Feature", "properties": { "visible_points": 2, "total_points": 56, "visibility_pct": 3.5714285714285712 }, "geometry": { "type": "Point", "coordinates": [ -2.042166301702589, 51.463235011895009 ] } },
{ "type": "Feature", "properties": { "visible_points": 5, "total_points": 55, "visibility_pct": 9.0909090909090917 }, "geometry": { "type": "Point", "coordinates": [ -2.042864516165596, 51.463342659379144 ] } },
{ "type": "Feature", "properties": { "visible_points": 7, "total_points": 59, "visibility_pct": 11.864406779661017 }, "geometry": { "type": "Point", "coordinates": [ -2.042665055102324, 51.463342732052034 ] } },
{ "type": "Feature", "properties": { "visible_points": 4, "total_points": 61, "visibility_pct": 6.557377049180328 }, "geometry": { "type": "Point", "coordinates": [ -2.042465594038219, 51.463342804385626 ] } },
{ "type": "Feature", "properties": { "visible_points": 4, "total_points": 61, "visibility_pct": 6.557377049180328 }, "geometry": { "type": "Point", "coordinates": [ -2.042266132973289, 51.46334287637989 ] } },
{ "type": "Feature", "properties": { "visible_points": 6, "total_points": 60, "visibility_pct": 10.0 }, "geometry": { "type": "Point", "coordinates": [ -2.042764887802855, 51.463450596126755 ] } },
{ "type": "Feature", "properties": { "visible_points": 7, "total_points": 61, "visibility_pct": 11.475409836065573 }, "geometry": { "type": "Point", "coordinates": [ -2.042565426262415, 51.463450668624681 ] } },
{ "type": "Feature", "properties": { "visible_points": 10, "total_points": 61, "visibility_pct": 16.393442622950818 }, "geometry": { "type": "Point", "coordinates": [ -2.042365964721143, 51.463450740783294 ] } },
{ "type": "Feature", "properties": { "visible_points": 5, "total_points": 61, "visibility_pct": 8.1967213114754092 }, "geometry": { "type": "Point", "coordinates": [ -2.042166503179047, 51.463450812602602 ] } },
{ "type": "Feature", "properties": { "visible_points": 6, "total_points": 61, "visibility_pct": 9.8360655737704921 }, "geometry": { "type": "Point", "coordinates": [ -2.042665258963769, 51.46355853278223 ] } },
{ "type": "Feature", "properties": { "visible_points": 6, "total_points": 61, "visibility_pct": 9.8360655737704921 }, "geometry": { "type": "Point", "coordinates": [ -2.042465796946153, 51.463558605105192 ] } },
{ "type": "Feature", "properties": { "visible_points": 3, "total_points": 61, "visibility_pct": 4.918032786885246 }, "geometry": { "type": "Point", "coordinates": [ -2.042266334927713, 51.463558677088848 ] } },
{ "type": "Feature", "properties": { "visible_points": 0, "total_points": 59, "visibility_pct": 0.0 }, "geometry": { "type": "Point", "coordinates": [ -2.04206687290845, 51.463558748733163 ] } },
{ "type": "Feature", "properties": { "visible_points": 9, "total_points": 61, "visibility_pct": 14.754098360655737 }, "geometry": { "type": "Point", "coordinates": [ -2.042565629648323, 51.463666469345576 ] } },
{ "type": "Feature", "properties": { "visible_points": 5, "total_points": 61, "visibility_pct": 8.1967213114754092 }, "geometry": { "type": "Point", "coordinates": [ -2.042366167153537, 51.463666541493566 ] } },
{ "type": "Feature", "properties": { "visible_points": 2, "total_points": 59, "visibility_pct": 3.3898305084745761 }, "geometry": { "type": "Point", "coordinates": [ -2.042166704657924, 51.463666613302244 ] } },
{ "type": "Feature", "properties": { "visible_points": 0, "total_points": 54, "visibility_pct": 0.0 }, "geometry": { "type": "Point", "coordinates": [ -2.041967242161491, 51.463666684771582 ] } },
{ "type": "Feature", "properties": { "visible_points": 0, "total_points": 56, "visibility_pct": 0.0 }, "geometry": { "type": "Point", "coordinates": [ -2.042465999856523, 51.463774405816807 ] } },
{ "type": "Feature", "properties": { "visible_points": 0, "total_points": 55, "visibility_pct": 0.0 }, "geometry": { "type": "Point", "coordinates": [ -2.042266536884561, 51.463774477789826 ] } },
{ "type": "Feature", "properties": { "visible_points": 0, "total_points": 51, "visibility_pct": 0.0 }, "geometry": { "type": "Point", "coordinates": [ -2.042067073911773, 51.463774549423512 ] } }
]
}
