{
"type": "FeatureCollection",
"name": "SWIND_47_toilets",
"crs": { "type": "name", "properties": { "name": "urn:ogc:def:crs:OGC:1.3:CRS84" } },
"features": [
{ "type": "Feature", "properties": { "name": "Fleming Way Bus Interchange", "payment_info": "50p", "accessible": "True", "radar": "True", "women": "True", "men": "True", "baby_change": "True", "Mon": "06:30-20:00", "Tue": "06:30-20:00", "Wed": "06:30-20:00", "Thu": "06:30-20:00", "Fri": "06:30-20:00", "Sat": "06:30-20:00", "Sun": "06:30-20:00", "index_right": 111, "park_offical_id": "SWIND_47" }, "geometry": { "type": "Point", "coordinates": [ -1.78452462, 51.562763956 ] } },
{ "type": "Feature", "properties": { "name": "Unknown", "payment_info": "Cost unknown", "accessible": "False", "radar": "False", "women": "Unknown", "men": "Unknown", "baby_change": "Unknown", "Mon": "Unknown", "Tue": "Unknown", "Wed": "Unknown", "Thu": "Unknown", "Fri": "Unknown", "Sat": "Unknown", "Sun": "Unknown", "index_right": 111, "park_offical_id": "SWIND_47" }, "geometry": { "type": "Point", "coordinates": [ -1.787407994, 51.559825631 ] } },
{ "type": "Feature", "properties": { "name": "Unknown", "payment_info": "Free", "accessible": "False", "radar": "Unknown", "women": "Unknown", "men": "Unknown", "baby_change": "Unknown", "Mon": "Unknown", "Tue": "Unknown", "Wed": "Unknown", "Thu": "Unknown", "Fri": "Unknown", "Sat": "Unknown", "Sun": "Unknown", "index_right": 111, "park_offical_id": "SWIND_47" }, "geometry": { "type": "Point", "coordinates": [ -1.7754054, 51.5580085 ] } },
{ "type": "Feature", "properties": { "name": "Museum and Art Swindon  Civic Offices", "payment_info": "Free", "accessible": "True", "radar": "Unknown", "women": "True", "men": "True", "baby_change": "True", "Mon": "Closed", "Tue": "10:30-16:30", "Wed": "10:30-16:30", "Thu": "10:30-16:30", "Fri": "10:30-16:30", "Sat": "10:30-16:30", "Sun": "Closed", "index_right": 111, "park_offical_id": "SWIND_47" }, "geometry": { "type": "Point", "coordinates": [ -1.777993441, 51.560156317 ] } }
]
}
