{
"type": "FeatureCollection",
"name": "SWIND_123_toilets",
"crs": { "type": "name", "properties": { "name": "urn:ogc:def:crs:OGC:1.3:CRS84" } },
"features": [
{ "type": "Feature", "properties": { "name": "Fleming Way Bus Interchange", "payment_info": "50p", "accessible": "True", "radar": "True", "women": "True", "men": "True", "baby_change": "True", "Mon": "06:30-20:00", "Tue": "06:30-20:00", "Wed": "06:30-20:00", "Thu": "06:30-20:00", "Fri": "06:30-20:00", "Sat": "06:30-20:00", "Sun": "06:30-20:00", "index_right": 28, "park_offical_id": "SWIND_123" }, "geometry": { "type": "Point", "coordinates": [ -1.78452462, 51.562763956 ] } },
{ "type": "Feature", "properties": { "name": "Designer Outlet shopping centre", "payment_info": "Free", "accessible": "True", "radar": "Unknown", "women": "True", "men": "True", "baby_change": "True", "Mon": "10:00-20:00", "Tue": "10:00-20:00", "Wed": "10:00-20:00", "Thu": "10:00-20:00", "Fri": "10:00-20:00", "Sat": "10:00-20:00", "Sun": "10:00-18:00", "index_right": 28, "park_offical_id": "SWIND_123" }, "geometry": { "type": "Point", "coordinates": [ -1.797391176, 51.562459097 ] } },
{ "type": "Feature", "properties": { "name": "Swindon Station", "payment_info": "Free", "accessible": "True", "radar": "True", "women": "True", "men": "True", "baby_change": "True", "Mon": "Unknown", "Tue": "Unknown", "Wed": "Unknown", "Thu": "Unknown", "Fri": "Unknown", "Sat": "Unknown", "Sun": "Unknown", "index_right": 28, "park_offical_id": "SWIND_123" }, "geometry": { "type": "Point", "coordinates": [ -1.785868406, 51.565660332 ] } },
{ "type": "Feature", "properties": { "name": "Unknown", "payment_info": "Cost unknown", "accessible": "False", "radar": "False", "women": "Unknown", "men": "Unknown", "baby_change": "Unknown", "Mon": "Unknown", "Tue": "Unknown", "Wed": "Unknown", "Thu": "Unknown", "Fri": "Unknown", "Sat": "Unknown", "Sun": "Unknown", "index_right": 28, "park_offical_id": "SWIND_123" }, "geometry": { "type": "Point", "coordinates": [ -1.787407994, 51.559825631 ] } }
]
}
