{
"type": "FeatureCollection",
"name": "SWIND_173_toilets",
"crs": { "type": "name", "properties": { "name": "urn:ogc:def:crs:OGC:1.3:CRS84" } },
"features": [
{ "type": "Feature", "properties": { "name": "Westrop Surgery", "payment_info": "Free", "accessible": "True", "radar": "False", "women": "True", "men": "True", "baby_change": "Unknown", "Mon": "08:30-18:30", "Tue": "08:30-18:30", "Wed": "08:30-18:30", "Thu": "08:30-18:30", "Fri": "08:30-18:30", "Sat": "Closed", "Sun": "Closed", "index_right": 54, "park_offical_id": "SWIND_173" }, "geometry": { "type": "Point", "coordinates": [ -1.714291417, 51.633838371 ] } }
]
}
