{
"type": "FeatureCollection",
"name": "BATNO_71",
"crs": { "type": "name", "properties": { "name": "urn:ogc:def:crs:OGC:1.3:CRS84" } },
"features": [
{ "type": "Feature", "properties": { "osm_id": 12037817084, "name": null, "amenity": "bench", "man_made": null, "leisure": null, "playground": null, "memorial": null }, "geometry": { "type": "Point", "coordinates": [ -2.4030602, 51.3885865 ] } },
{ "type": "Feature", "properties": { "osm_id": 12037798654, "name": null, "amenity": null, "man_made": null, "leisure": "picnic_table", "playground": null, "memorial": null }, "geometry": { "type": "Point", "coordinates": [ -2.4046762, 51.3887053 ] } },
{ "type": "Feature", "properties": { "osm_id": 12037798655, "name": null, "amenity": "bench", "man_made": null, "leisure": null, "playground": null, "memorial": null }, "geometry": { "type": "Point", "coordinates": [ -2.4047661, 51.3889555 ] } },
{ "type": "Feature", "properties": { "osm_id": 12037798658, "name": null, "amenity": "bench", "man_made": null, "leisure": null, "playground": null, "memorial": null }, "geometry": { "type": "Point", "coordinates": [ -2.4049565, 51.3890149 ] } },
{ "type": "Feature", "properties": { "osm_id": 12037817083, "name": null, "amenity": "bench", "man_made": null, "leisure": null, "playground": null, "memorial": null }, "geometry": { "type": "Point", "coordinates": [ -2.4040741, 51.3890283 ] } },
{ "type": "Feature", "properties": { "osm_id": 12037817082, "name": null, "amenity": "bench", "man_made": null, "leisure": null, "playground": null, "memorial": null }, "geometry": { "type": "Point", "coordinates": [ -2.4045716, 51.3891706 ] } },
{ "type": "Feature", "properties": { "osm_id": 12037822161, "name": null, "amenity": "bench", "man_made": null, "leisure": null, "playground": null, "memorial": null }, "geometry": { "type": "Point", "coordinates": [ -2.4048882, 51.3892117 ] } }
]
}
