{
"type": "FeatureCollection",
"name": "BATNO_12",
"crs": { "type": "name", "properties": { "name": "urn:ogc:def:crs:OGC:1.3:CRS84" } },
"features": [
{ "type": "Feature", "properties": { "osm_id": 10785675253, "name": null, "amenity": "bench", "man_made": null, "leisure": null, "playground": null, "memorial": null }, "geometry": { "type": "Point", "coordinates": [ -2.3598552, 51.3946996 ] } },
{ "type": "Feature", "properties": { "osm_id": 10785675250, "name": null, "amenity": "bench", "man_made": null, "leisure": null, "playground": null, "memorial": null }, "geometry": { "type": "Point", "coordinates": [ -2.3598096, 51.3947448 ] } },
{ "type": "Feature", "properties": { "osm_id": 10785675252, "name": null, "amenity": "bench", "man_made": null, "leisure": null, "playground": null, "memorial": "bench" }, "geometry": { "type": "Point", "coordinates": [ -2.3597694, 51.3948001 ] } },
{ "type": "Feature", "properties": { "osm_id": 10785545172, "name": null, "amenity": "bench", "man_made": null, "leisure": null, "playground": null, "memorial": null }, "geometry": { "type": "Point", "coordinates": [ -2.3604025, 51.3950482 ] } },
{ "type": "Feature", "properties": { "osm_id": 10785545174, "name": null, "amenity": "bench", "man_made": null, "leisure": null, "playground": null, "memorial": null }, "geometry": { "type": "Point", "coordinates": [ -2.3603789, 51.3950486 ] } },
{ "type": "Feature", "properties": { "osm_id": 10785545166, "name": null, "amenity": "bench", "man_made": null, "leisure": null, "playground": null, "memorial": null }, "geometry": { "type": "Point", "coordinates": [ -2.3604011, 51.395062 ] } },
{ "type": "Feature", "properties": { "osm_id": 10785545171, "name": null, "amenity": "bench", "man_made": null, "leisure": null, "playground": null, "memorial": null }, "geometry": { "type": "Point", "coordinates": [ -2.3603803, 51.3950624 ] } }
]
}
