{
"type": "FeatureCollection",
"name": "PLYMO_35",
"crs": { "type": "name", "properties": { "name": "urn:ogc:def:crs:OGC:1.3:CRS84" } },
"features": [
{ "type": "Feature", "properties": { "osm_id": 12648322688, "name": null, "amenity": "bench", "man_made": null, "leisure": null, "playground": null, "memorial": null }, "geometry": { "type": "Point", "coordinates": [ -4.1734839, 50.391245 ] } },
{ "type": "Feature", "properties": { "osm_id": 12648322687, "name": null, "amenity": "bench", "man_made": null, "leisure": null, "playground": null, "memorial": null }, "geometry": { "type": "Point", "coordinates": [ -4.1734214, 50.3912769 ] } },
{ "type": "Feature", "properties": { "osm_id": 12648322689, "name": null, "amenity": "bench", "man_made": null, "leisure": null, "playground": null, "memorial": null }, "geometry": { "type": "Point", "coordinates": [ -4.1736046, 50.3912815 ] } },
{ "type": "Feature", "properties": { "osm_id": 12648322690, "name": null, "amenity": "bench", "man_made": null, "leisure": null, "playground": null, "memorial": null }, "geometry": { "type": "Point", "coordinates": [ -4.1736089, 50.3913377 ] } },
{ "type": "Feature", "properties": { "osm_id": 12648322685, "name": null, "amenity": "bench", "man_made": null, "leisure": null, "playground": null, "memorial": null }, "geometry": { "type": "Point", "coordinates": [ -4.1734636, 50.3915314 ] } },
{ "type": "Feature", "properties": { "osm_id": 12648322684, "name": null, "amenity": "bench", "man_made": null, "leisure": null, "playground": null, "memorial": null }, "geometry": { "type": "Point", "coordinates": [ -4.1735053, 50.3915786 ] } },
{ "type": "Feature", "properties": { "osm_id": 12648322686, "name": null, "amenity": "bench", "man_made": null, "leisure": null, "playground": null, "memorial": null }, "geometry": { "type": "Point", "coordinates": [ -4.1734735, 50.3916434 ] } }
]
}
