{
"type": "FeatureCollection",
"name": "PLYMO_29",
"crs": { "type": "name", "properties": { "name": "urn:ogc:def:crs:OGC:1.3:CRS84" } },
"features": [
{ "type": "Feature", "properties": { "osm_id": 9294870420, "name": null, "amenity": "bench", "man_made": null, "leisure": null, "playground": null, "memorial": null }, "geometry": { "type": "Point", "coordinates": [ -4.1175561, 50.4296192 ] } },
{ "type": "Feature", "properties": { "osm_id": 9294870421, "name": null, "amenity": "bench", "man_made": null, "leisure": null, "playground": null, "memorial": null }, "geometry": { "type": "Point", "coordinates": [ -4.1169474, 50.429864 ] } }
]
}
