{
"type": "FeatureCollection",
"name": "PLYMO_106",
"crs": { "type": "name", "properties": { "name": "urn:ogc:def:crs:OGC:1.3:CRS84" } },
"features": [
{ "type": "Feature", "properties": { "osm_id": 9913456951, "name": null, "amenity": "bench", "man_made": null, "leisure": null, "playground": null, "memorial": null }, "geometry": { "type": "Point", "coordinates": [ -4.1731689, 50.3839433 ] } },
{ "type": "Feature", "properties": { "osm_id": 12648322696, "name": null, "amenity": null, "man_made": null, "leisure": "picnic_table", "playground": null, "memorial": null }, "geometry": { "type": "Point", "coordinates": [ -4.1725869, 50.3839571 ] } },
{ "type": "Feature", "properties": { "osm_id": 12648322695, "name": null, "amenity": "bench", "man_made": null, "leisure": null, "playground": null, "memorial": null }, "geometry": { "type": "Point", "coordinates": [ -4.1726481, 50.3839714 ] } },
{ "type": "Feature", "properties": { "osm_id": 12648322694, "name": null, "amenity": null, "man_made": null, "leisure": "picnic_table", "playground": null, "memorial": null }, "geometry": { "type": "Point", "coordinates": [ -4.1734772, 50.3840403 ] } },
{ "type": "Feature", "properties": { "osm_id": 9913456950, "name": null, "amenity": "bench", "man_made": null, "leisure": null, "playground": null, "memorial": null }, "geometry": { "type": "Point", "coordinates": [ -4.1731166, 50.3841029 ] } },
{ "type": "Feature", "properties": { "osm_id": 12648322693, "name": null, "amenity": null, "man_made": null, "leisure": "picnic_table", "playground": null, "memorial": null }, "geometry": { "type": "Point", "coordinates": [ -4.1734923, 50.3841245 ] } },
{ "type": "Feature", "properties": { "osm_id": 12648322697, "name": null, "amenity": "bench", "man_made": null, "leisure": null, "playground": null, "memorial": null }, "geometry": { "type": "Point", "coordinates": [ -4.1724726, 50.3841752 ] } }
]
}
