{
"type": "FeatureCollection",
"name": "PLYMO_90",
"crs": { "type": "name", "properties": { "name": "urn:ogc:def:crs:OGC:1.3:CRS84" } },
"features": [
{ "type": "Feature", "properties": { "osm_id": 8977847946, "name": null, "amenity": "bench", "man_made": null, "leisure": null, "playground": null, "memorial": null }, "geometry": { "type": "Point", "coordinates": [ -4.0919899, 50.3559748 ] } },
{ "type": "Feature", "properties": { "osm_id": 8977847945, "name": null, "amenity": "bench", "man_made": null, "leisure": null, "playground": null, "memorial": null }, "geometry": { "type": "Point", "coordinates": [ -4.0920188, 50.3559989 ] } },
{ "type": "Feature", "properties": { "osm_id": 8977847947, "name": null, "amenity": "bench", "man_made": null, "leisure": null, "playground": null, "memorial": null }, "geometry": { "type": "Point", "coordinates": [ -4.0919805, 50.3560581 ] } }
]
}
