{
"type": "FeatureCollection",
"name": "STROU_27_toilets",
"crs": { "type": "name", "properties": { "name": "urn:ogc:def:crs:OGC:1.3:CRS84" } },
"features": [
{ "type": "Feature", "properties": { "name": "Bell Lane", "payment_info": "Free", "accessible": "False", "radar": "True", "women": "Unknown", "men": "Unknown", "baby_change": "False", "Mon": "07:00-18:00", "Tue": "07:00-18:00", "Wed": "07:00-18:00", "Thu": "07:00-18:00", "Fri": "07:00-18:00", "Sat": "07:00-18:00", "Sun": "07:00-18:00", "index_right": 36, "park_offical_id": "STROU_27" }, "geometry": { "type": "Point", "coordinates": [ -2.1869297, 51.706181 ] } }
]
}
