{
"type": "FeatureCollection",
"name": "WILTS_209",
"crs": { "type": "name", "properties": { "name": "urn:ogc:def:crs:OGC:1.3:CRS84" } },
"features": [
{ "type": "Feature", "properties": { "osm_id": 512526431, "name": null, "amenity": "bench", "man_made": null, "leisure": null, "playground": null, "memorial": null }, "geometry": { "type": "Point", "coordinates": [ -2.1990659, 51.2543003 ] } },
{ "type": "Feature", "properties": { "osm_id": 512526430, "name": null, "amenity": "bench", "man_made": null, "leisure": null, "playground": null, "memorial": null }, "geometry": { "type": "Point", "coordinates": [ -2.1990058, 51.2543164 ] } },
{ "type": "Feature", "properties": { "osm_id": 512526472, "name": null, "amenity": "bench", "man_made": null, "leisure": null, "playground": null, "memorial": null }, "geometry": { "type": "Point", "coordinates": [ -2.1990399, 51.2543815 ] } }
]
}
