{
"type": "FeatureCollection",
"name": "BATNO_74_toilets",
"crs": { "type": "name", "properties": { "name": "urn:ogc:def:crs:OGC:1.3:CRS84" } },
"features": [
{ "type": "Feature", "properties": { "name": "Odd Down Park  Ride", "payment_info": "Free", "accessible": "False", "radar": "Unknown", "women": "Unknown", "men": "Unknown", "baby_change": "Unknown", "Mon": "Unknown", "Tue": "Unknown", "Wed": "Unknown", "Thu": "Unknown", "Fri": "Unknown", "Sat": "Unknown", "Sun": "Unknown", "index_right": 97, "park_offical_id": "BATNO_74" }, "geometry": { "type": "Point", "coordinates": [ -2.384968356, 51.351644189 ] } }
]
}
