{
"type": "FeatureCollection",
"name": "BATNO_18_toilets",
"crs": { "type": "name", "properties": { "name": "urn:ogc:def:crs:OGC:1.3:CRS84" } },
"features": [
{ "type": "Feature", "properties": { "name": "Royal Victoria Park Childrens Play Area  Herberts Cafe", "payment_info": "20p", "accessible": "False", "radar": "True", "women": "True", "men": "True", "baby_change": "True", "Mon": "09:00-18:00", "Tue": "09:00-18:00", "Wed": "09:00-18:00", "Thu": "09:00-18:00", "Fri": "09:00-18:00", "Sat": "09:00-18:00", "Sun": "09:00-18:00", "index_right": 38, "park_offical_id": "BATNO_18" }, "geometry": { "type": "Point", "coordinates": [ -2.376608849, 51.386010629 ] } }
]
}
