{
"type": "FeatureCollection",
"name": "West Devon_street_lamps",
"crs": { "type": "name", "properties": { "name": "urn:ogc:def:crs:OGC:1.3:CRS84" } },
"features": [
{ "type": "Feature", "properties": { "element_type": "node", "osmid": 11133636176, "authority": "West Devon", "source": "osm", "year": null }, "geometry": { "type": "Point", "coordinates": [ -4.2010617, 50.6578833 ] } },
{ "type": "Feature", "properties": { "element_type": "node", "osmid": 11133636177, "authority": "West Devon", "source": "osm", "year": null }, "geometry": { "type": "Point", "coordinates": [ -4.2004313, 50.6581105 ] } },
{ "type": "Feature", "properties": { "element_type": "node", "osmid": 11133636178, "authority": "West Devon", "source": "osm", "year": null }, "geometry": { "type": "Point", "coordinates": [ -4.199908, 50.6582202 ] } },
{ "type": "Feature", "properties": { "element_type": "node", "osmid": 11133636179, "authority": "West Devon", "source": "osm", "year": null }, "geometry": { "type": "Point", "coordinates": [ -4.1991989, 50.6583379 ] } },
{ "type": "Feature", "properties": { "element_type": "node", "osmid": 11133636180, "authority": "West Devon", "source": "osm", "year": null }, "geometry": { "type": "Point", "coordinates": [ -4.1987271, 50.6584502 ] } },
{ "type": "Feature", "properties": { "element_type": "node", "osmid": 11133636181, "authority": "West Devon", "source": "osm", "year": null }, "geometry": { "type": "Point", "coordinates": [ -4.198212, 50.6585532 ] } },
{ "type": "Feature", "properties": { "element_type": "node", "osmid": 11133636182, "authority": "West Devon", "source": "osm", "year": null }, "geometry": { "type": "Point", "coordinates": [ -4.1976157, 50.6586504 ] } },
{ "type": "Feature", "properties": { "element_type": "node", "osmid": 11133636183, "authority": "West Devon", "source": "osm", "year": null }, "geometry": { "type": "Point", "coordinates": [ -4.1970184, 50.6587545 ] } },
{ "type": "Feature", "properties": { "element_type": "node", "osmid": 11133636184, "authority": "West Devon", "source": "osm", "year": null }, "geometry": { "type": "Point", "coordinates": [ -4.1964816, 50.6588317 ] } },
{ "type": "Feature", "properties": { "element_type": "node", "osmid": 11133636185, "authority": "West Devon", "source": "osm", "year": null }, "geometry": { "type": "Point", "coordinates": [ -4.1958618, 50.6589192 ] } },
{ "type": "Feature", "properties": { "element_type": "node", "osmid": 11133636186, "authority": "West Devon", "source": "osm", "year": null }, "geometry": { "type": "Point", "coordinates": [ -4.1952249, 50.6590216 ] } },
{ "type": "Feature", "properties": { "element_type": "node", "osmid": 11133636187, "authority": "West Devon", "source": "osm", "year": null }, "geometry": { "type": "Point", "coordinates": [ -4.194844, 50.659083 ] } },
{ "type": "Feature", "properties": { "element_type": "node", "osmid": 11133636188, "authority": "West Devon", "source": "osm", "year": null }, "geometry": { "type": "Point", "coordinates": [ -4.1943784, 50.659065 ] } },
{ "type": "Feature", "properties": { "element_type": "node", "osmid": 11133636189, "authority": "West Devon", "source": "osm", "year": null }, "geometry": { "type": "Point", "coordinates": [ -4.1936678, 50.659264 ] } }
]
}
