{
"type": "FeatureCollection",
"name": "NORSO_59",
"crs": { "type": "name", "properties": { "name": "urn:ogc:def:crs:OGC:1.3:CRS84" } },
"features": [
{ "type": "Feature", "properties": { "osm_id": 7863886121, "name": null, "amenity": "bench", "man_made": null, "leisure": null, "playground": null, "memorial": null }, "geometry": { "type": "Point", "coordinates": [ -2.858091, 51.4366707 ] } },
{ "type": "Feature", "properties": { "osm_id": 7863886118, "name": null, "amenity": "bench", "man_made": null, "leisure": null, "playground": null, "memorial": null }, "geometry": { "type": "Point", "coordinates": [ -2.8584449, 51.4366911 ] } },
{ "type": "Feature", "properties": { "osm_id": 7863886119, "name": null, "amenity": "bench", "man_made": null, "leisure": null, "playground": null, "memorial": null }, "geometry": { "type": "Point", "coordinates": [ -2.8582031, 51.4367537 ] } }
]
}
