{
"type": "FeatureCollection",
"name": "NORSO_123",
"crs": { "type": "name", "properties": { "name": "urn:ogc:def:crs:OGC:1.3:CRS84" } },
"features": [
{ "type": "Feature", "properties": { "osm_id": 6369047944, "name": null, "amenity": "bench", "man_made": null, "leisure": null, "playground": null, "memorial": null }, "geometry": { "type": "Point", "coordinates": [ -2.7611129, 51.4919223 ] } },
{ "type": "Feature", "properties": { "osm_id": 6369047945, "name": null, "amenity": "bench", "man_made": null, "leisure": null, "playground": null, "memorial": null }, "geometry": { "type": "Point", "coordinates": [ -2.7610119, 51.4919237 ] } },
{ "type": "Feature", "properties": { "osm_id": 6369047941, "name": null, "amenity": "bench", "man_made": null, "leisure": null, "playground": null, "memorial": null }, "geometry": { "type": "Point", "coordinates": [ -2.7612076, 51.4919243 ] } },
{ "type": "Feature", "properties": { "osm_id": 6369047943, "name": null, "amenity": "bench", "man_made": null, "leisure": null, "playground": null, "memorial": null }, "geometry": { "type": "Point", "coordinates": [ -2.7611597, 51.4920424 ] } }
]
}
