{
"type": "FeatureCollection",
"name": "NORSO_135",
"crs": { "type": "name", "properties": { "name": "urn:ogc:def:crs:OGC:1.3:CRS84" } },
"features": [
{ "type": "Feature", "properties": { "osm_id": 7865805731, "name": null, "amenity": null, "man_made": null, "leisure": "picnic_table", "playground": null, "memorial": null }, "geometry": { "type": "Point", "coordinates": [ -2.7575028, 51.4870138 ] } },
{ "type": "Feature", "properties": { "osm_id": 10606759276, "name": null, "amenity": "bench", "man_made": null, "leisure": null, "playground": null, "memorial": null }, "geometry": { "type": "Point", "coordinates": [ -2.7575339, 51.4870693 ] } },
{ "type": "Feature", "properties": { "osm_id": 10606759277, "name": null, "amenity": "bench", "man_made": null, "leisure": null, "playground": null, "memorial": null }, "geometry": { "type": "Point", "coordinates": [ -2.7574673, 51.4871469 ] } }
]
}
