{
"type": "FeatureCollection",
"name": "TEIGN_99",
"crs": { "type": "name", "properties": { "name": "urn:ogc:def:crs:OGC:1.3:CRS84" } },
"features": [
{ "type": "Feature", "properties": { "osm_id": 10084942125, "name": null, "amenity": "bench", "man_made": null, "leisure": null, "playground": null, "memorial": null }, "geometry": { "type": "Point", "coordinates": [ -3.6475959, 50.6300239 ] } },
{ "type": "Feature", "properties": { "osm_id": 10084943017, "name": null, "amenity": "bench", "man_made": null, "leisure": null, "playground": null, "memorial": null }, "geometry": { "type": "Point", "coordinates": [ -3.6471003, 50.6304975 ] } },
{ "type": "Feature", "properties": { "osm_id": 10084942124, "name": null, "amenity": "bench", "man_made": null, "leisure": null, "playground": null, "memorial": null }, "geometry": { "type": "Point", "coordinates": [ -3.6477119, 50.6305311 ] } },
{ "type": "Feature", "properties": { "osm_id": 10084942320, "name": null, "amenity": "bench", "man_made": null, "leisure": null, "playground": null, "memorial": null }, "geometry": { "type": "Point", "coordinates": [ -3.6476887, 50.6305384 ] } },
{ "type": "Feature", "properties": { "osm_id": 10084942127, "name": null, "amenity": "bench", "man_made": null, "leisure": null, "playground": null, "memorial": null }, "geometry": { "type": "Point", "coordinates": [ -3.6476203, 50.6307339 ] } },
{ "type": "Feature", "properties": { "osm_id": 10084942321, "name": null, "amenity": "bench", "man_made": null, "leisure": null, "playground": null, "memorial": null }, "geometry": { "type": "Point", "coordinates": [ -3.6474824, 50.6307585 ] } },
{ "type": "Feature", "properties": { "osm_id": 10084942128, "name": null, "amenity": null, "man_made": null, "leisure": "picnic_table", "playground": null, "memorial": null }, "geometry": { "type": "Point", "coordinates": [ -3.6475976, 50.6307628 ] } },
{ "type": "Feature", "properties": { "osm_id": 10084942224, "name": null, "amenity": null, "man_made": null, "leisure": "picnic_table", "playground": null, "memorial": null }, "geometry": { "type": "Point", "coordinates": [ -3.6475134, 50.6307785 ] } }
]
}
