{
"type": "FeatureCollection",
"name": "BRIST_2_toilets",
"crs": { "type": "name", "properties": { "name": "urn:ogc:def:crs:OGC:1.3:CRS84" } },
"features": [
{ "type": "Feature", "properties": { "name": "University of Bristol Botanic Garden", "payment_info": "Free", "accessible": "True", "radar": "False", "women": "True", "men": "True", "baby_change": "True", "Mon": "10:00-16:30", "Tue": "10:00-16:30", "Wed": "10:00-16:30", "Thu": "10:00-16:30", "Fri": "10:00-16:30", "Sat": "10:00-16:30", "Sun": "10:00-16:30", "index_right": 88, "park_offical_id": "BRIST_2" }, "geometry": { "type": "Point", "coordinates": [ -2.62494117, 51.477405756 ] } }
]
}
