{
"type": "FeatureCollection",
"name": "BRIST_122_toilets",
"crs": { "type": "name", "properties": { "name": "urn:ogc:def:crs:OGC:1.3:CRS84" } },
"features": [
{ "type": "Feature", "properties": { "name": "The Blaise Inn", "payment_info": "Free", "accessible": "False", "radar": "Unknown", "women": "Unknown", "men": "Unknown", "baby_change": "False", "Mon": "Unknown", "Tue": "Unknown", "Wed": "Unknown", "Thu": "Unknown", "Fri": "Unknown", "Sat": "Unknown", "Sun": "Unknown", "index_right": 27, "park_offical_id": "BRIST_122" }, "geometry": { "type": "Point", "coordinates": [ -2.6323843, 51.507034637 ] } },
{ "type": "Feature", "properties": { "name": "Henbury Sports Centre", "payment_info": "Free", "accessible": "True", "radar": "False", "women": "True", "men": "True", "baby_change": "True", "Mon": "Unknown", "Tue": "Unknown", "Wed": "Unknown", "Thu": "Unknown", "Fri": "Unknown", "Sat": "Unknown", "Sun": "Unknown", "index_right": 27, "park_offical_id": "BRIST_122" }, "geometry": { "type": "Point", "coordinates": [ -2.632716894, 51.509346775 ] } },
{ "type": "Feature", "properties": { "name": "Blaise Castle Estate Museum and Roman Villa", "payment_info": "Free", "accessible": "False", "radar": "False", "women": "Unknown", "men": "Unknown", "baby_change": "True", "Mon": "Unknown", "Tue": "Unknown", "Wed": "Unknown", "Thu": "Unknown", "Fri": "Unknown", "Sat": "Unknown", "Sun": "Unknown", "index_right": 27, "park_offical_id": "BRIST_122" }, "geometry": { "type": "Point", "coordinates": [ -2.632421851, 51.505744128 ] } },
{ "type": "Feature", "properties": { "name": "Blaise Castle Estate", "payment_info": "Free", "accessible": "False", "radar": "False", "women": "True", "men": "True", "baby_change": "True", "Mon": "Unknown", "Tue": "Unknown", "Wed": "Unknown", "Thu": "Unknown", "Fri": "Unknown", "Sat": "Unknown", "Sun": "Unknown", "index_right": 27, "park_offical_id": "BRIST_122" }, "geometry": { "type": "Point", "coordinates": [ -2.6365599, 51.5054081 ] } }
]
}
