{
"type": "FeatureCollection",
"name": "BRIST_106_toilets",
"crs": { "type": "name", "properties": { "name": "urn:ogc:def:crs:OGC:1.3:CRS84" } },
"features": [
{ "type": "Feature", "properties": { "name": "Stoke Road Toilets", "payment_info": "Free", "accessible": "True", "radar": "True", "women": "True", "men": "True", "baby_change": "True", "Mon": "08:00-20:00", "Tue": "08:00-20:00", "Wed": "08:00-20:00", "Thu": "08:00-20:00", "Fri": "08:00-20:00", "Sat": "08:00-20:00", "Sun": "08:00-20:00", "index_right": 9, "park_offical_id": "BRIST_106" }, "geometry": { "type": "Point", "coordinates": [ -2.617684894, 51.471796894 ] } },
{ "type": "Feature", "properties": { "name": "Helios Medical Centre", "payment_info": "Free", "accessible": "True", "radar": "Unknown", "women": "Unknown", "men": "Unknown", "baby_change": "True", "Mon": "Unknown", "Tue": "Unknown", "Wed": "Unknown", "Thu": "Unknown", "Fri": "Unknown", "Sat": "Unknown", "Sun": "Unknown", "index_right": 9, "park_offical_id": "BRIST_106" }, "geometry": { "type": "Point", "coordinates": [ -2.630753517, 51.475455945 ] } },
{ "type": "Feature", "properties": { "name": "University of Bristol Botanic Garden", "payment_info": "Free", "accessible": "True", "radar": "False", "women": "True", "men": "True", "baby_change": "True", "Mon": "10:00-16:30", "Tue": "10:00-16:30", "Wed": "10:00-16:30", "Thu": "10:00-16:30", "Fri": "10:00-16:30", "Sat": "10:00-16:30", "Sun": "10:00-16:30", "index_right": 9, "park_offical_id": "BRIST_106" }, "geometry": { "type": "Point", "coordinates": [ -2.62494117, 51.477405756 ] } }
]
}
