{
"type": "FeatureCollection",
"name": "BRIST_189_toilets",
"crs": { "type": "name", "properties": { "name": "urn:ogc:def:crs:OGC:1.3:CRS84" } },
"features": [
{ "type": "Feature", "properties": { "name": "Canford Park", "payment_info": "Free", "accessible": "True", "radar": "False", "women": "True", "men": "True", "baby_change": "Unknown", "Mon": "08:00-20:00", "Tue": "08:00-20:00", "Wed": "08:00-20:00", "Thu": "08:00-20:00", "Fri": "08:00-20:00", "Sat": "08:00-20:00", "Sun": "08:00-20:00", "index_right": 81, "park_offical_id": "BRIST_189" }, "geometry": { "type": "Point", "coordinates": [ -2.626352012, 51.493136083 ] } },
{ "type": "Feature", "properties": { "name": "White Lion", "payment_info": "Free", "accessible": "True", "radar": "False", "women": "True", "men": "True", "baby_change": "True", "Mon": "Unknown", "Tue": "Unknown", "Wed": "Unknown", "Thu": "Unknown", "Fri": "Unknown", "Sat": "Unknown", "Sun": "Unknown", "index_right": 81, "park_offical_id": "BRIST_189" }, "geometry": { "type": "Point", "coordinates": [ -2.617232362, 51.495024489 ] } },
{ "type": "Feature", "properties": { "name": "Grupo Lounge", "payment_info": "Free", "accessible": "True", "radar": "False", "women": "True", "men": "True", "baby_change": "True", "Mon": "Unknown", "Tue": "Unknown", "Wed": "Unknown", "Thu": "Unknown", "Fri": "Unknown", "Sat": "Unknown", "Sun": "Unknown", "index_right": 81, "park_offical_id": "BRIST_189" }, "geometry": { "type": "Point", "coordinates": [ -2.619217454, 51.492839699 ] } },
{ "type": "Feature", "properties": { "name": "BP GarageMS Simply Food", "payment_info": "Free", "accessible": "True", "radar": "True", "women": "True", "men": "True", "baby_change": "True", "Mon": "06:00-22:00", "Tue": "06:00-22:00", "Wed": "06:00-22:00", "Thu": "06:00-22:00", "Fri": "06:00-22:00", "Sat": "06:00-22:00", "Sun": "06:00-22:00", "index_right": 81, "park_offical_id": "BRIST_189" }, "geometry": { "type": "Point", "coordinates": [ -2.620657682, 51.495497368 ] } }
]
}
