{
"type": "FeatureCollection",
"name": "BRIST_175_toilets",
"crs": { "type": "name", "properties": { "name": "urn:ogc:def:crs:OGC:1.3:CRS84" } },
"features": [
{ "type": "Feature", "properties": { "name": "Burger King 4 Eastgate Road Eastgate Centre BS5 6XX ", "payment_info": "Free", "accessible": "True", "radar": "Unknown", "women": "True", "men": "True", "baby_change": "Unknown", "Mon": "Unknown", "Tue": "Unknown", "Wed": "Unknown", "Thu": "Unknown", "Fri": "Unknown", "Sat": "Unknown", "Sun": "Unknown", "index_right": 70, "park_offical_id": "BRIST_175" }, "geometry": { "type": "Point", "coordinates": [ -2.565085061, 51.473973596 ] } },
{ "type": "Feature", "properties": { "name": "Tesco Eastgate Extra", "payment_info": "Free", "accessible": "Unknown", "radar": "False", "women": "True", "men": "True", "baby_change": "True", "Mon": "06:00-00:00", "Tue": "06:00-00:00", "Wed": "06:00-00:00", "Thu": "06:00-00:00", "Fri": "06:00-00:00", "Sat": "06:00-00:00", "Sun": "10:00-16:00", "index_right": 70, "park_offical_id": "BRIST_175" }, "geometry": { "type": "Point", "coordinates": [ -2.563051879, 51.473304144 ] } },
{ "type": "Feature", "properties": { "name": "Burger King 4 Eastgate Road Eastgate Centre BS5 6XX", "payment_info": "Free", "accessible": "True", "radar": "False", "women": "True", "men": "True", "baby_change": "True", "Mon": "Unknown", "Tue": "Unknown", "Wed": "Unknown", "Thu": "Unknown", "Fri": "Unknown", "Sat": "Unknown", "Sun": "Unknown", "index_right": 70, "park_offical_id": "BRIST_175" }, "geometry": { "type": "Point", "coordinates": [ -2.565082312, 51.473960721 ] } }
]
}
