{
"type": "FeatureCollection",
"name": "BOUCH_13_toilets",
"crs": { "type": "name", "properties": { "name": "urn:ogc:def:crs:OGC:1.3:CRS84" } },
"features": [
{ "type": "Feature", "properties": { "name": "Christchurch Station", "payment_info": "Free", "accessible": "True", "radar": "Unknown", "women": "True", "men": "True", "baby_change": "False", "Mon": "06:30-12:55", "Tue": "06:30-12:55", "Wed": "06:30-12:55", "Thu": "06:30-12:55", "Fri": "06:30-12:55", "Sat": "06:30-12:55", "Sun": "06:30-12:55", "index_right": 34, "park_offical_id": "BOUCH_13" }, "geometry": { "type": "Point", "coordinates": [ -1.784549578, 50.73820038 ] } }
]
}
