{
"type": "FeatureCollection",
"name": "BOUCH_87_toilets",
"crs": { "type": "name", "properties": { "name": "urn:ogc:def:crs:OGC:1.3:CRS84" } },
"features": [
{ "type": "Feature", "properties": { "name": "Bournemouth Coach Station ", "payment_info": "Free", "accessible": "True", "radar": "False", "women": "Unknown", "men": "Unknown", "baby_change": "True", "Mon": "Unknown", "Tue": "Unknown", "Wed": "Unknown", "Thu": "Unknown", "Fri": "Unknown", "Sat": "Unknown", "Sun": "Unknown", "index_right": 184, "park_offical_id": "BOUCH_87" }, "geometry": { "type": "Point", "coordinates": [ -1.864693165, 50.72677477 ] } }
]
}
