{
"type": "FeatureCollection",
"name": "BOUCH_39_toilets",
"crs": { "type": "name", "properties": { "name": "urn:ogc:def:crs:OGC:1.3:CRS84" } },
"features": [
{ "type": "Feature", "properties": { "name": "Highcliffe Castle public toilets", "payment_info": "Free", "accessible": "True", "radar": "False", "women": "True", "men": "True", "baby_change": "Unknown", "Mon": "Unknown", "Tue": "Unknown", "Wed": "Unknown", "Thu": "Unknown", "Fri": "Unknown", "Sat": "Unknown", "Sun": "Unknown", "index_right": 131, "park_offical_id": "BOUCH_39" }, "geometry": { "type": "Point", "coordinates": [ -1.7148591, 50.7371118 ] } },
{ "type": "Feature", "properties": { "name": "Friars Cliff Beach public toilets", "payment_info": "Free", "accessible": "False", "radar": "Unknown", "women": "Unknown", "men": "Unknown", "baby_change": "Unknown", "Mon": "Unknown", "Tue": "Unknown", "Wed": "Unknown", "Thu": "Unknown", "Fri": "Unknown", "Sat": "Unknown", "Sun": "Unknown", "index_right": 131, "park_offical_id": "BOUCH_39" }, "geometry": { "type": "Point", "coordinates": [ -1.727954149, 50.733316282 ] } },
{ "type": "Feature", "properties": { "name": "Avon Beach", "payment_info": "Cost unknown", "accessible": "True", "radar": "True", "women": "True", "men": "True", "baby_change": "True", "Mon": "09:00-18:00", "Tue": "09:00-18:00", "Wed": "09:00-18:00", "Thu": "09:00-18:00", "Fri": "09:00-18:00", "Sat": "09:00-18:00", "Sun": "09:00-18:00", "index_right": 131, "park_offical_id": "BOUCH_39" }, "geometry": { "type": "Point", "coordinates": [ -1.734080315, 50.729532062 ] } },
{ "type": "Feature", "properties": { "name": "The Noisy Lobster", "payment_info": "Free", "accessible": "False", "radar": "False", "women": "True", "men": "True", "baby_change": "True", "Mon": "09:00-17:00", "Tue": "09:00-17:00", "Wed": "09:00-17:00", "Thu": "09:00-17:00", "Fri": "09:00-17:00", "Sat": "09:00-17:00", "Sun": "09:00-17:00", "index_right": 131, "park_offical_id": "BOUCH_39" }, "geometry": { "type": "Point", "coordinates": [ -1.734310985, 50.729229854 ] } }
]
}
