{
"type": "FeatureCollection",
"name": "BOUCH_235_toilets",
"crs": { "type": "name", "properties": { "name": "urn:ogc:def:crs:OGC:1.3:CRS84" } },
"features": [
{ "type": "Feature", "properties": { "name": "Civic Offices", "payment_info": "Free", "accessible": "True", "radar": "True", "women": "True", "men": "True", "baby_change": "Unknown", "Mon": "Unknown", "Tue": "Unknown", "Wed": "Unknown", "Thu": "Unknown", "Fri": "Unknown", "Sat": "Unknown", "Sun": "Unknown", "index_right": 82, "park_offical_id": "BOUCH_235" }, "geometry": { "type": "Point", "coordinates": [ -1.770268679, 50.734690017 ] } },
{ "type": "Feature", "properties": { "name": "Purewell Cross public toilets", "payment_info": "Free", "accessible": "False", "radar": "Unknown", "women": "True", "men": "True", "baby_change": "Unknown", "Mon": "09:00-17:00", "Tue": "09:00-17:00", "Wed": "09:00-17:00", "Thu": "09:00-17:00", "Fri": "09:00-17:00", "Sat": "09:00-17:00", "Sun": "09:00-17:00", "index_right": 82, "park_offical_id": "BOUCH_235" }, "geometry": { "type": "Point", "coordinates": [ -1.75961656, 50.73561512 ] } },
{ "type": "Feature", "properties": { "name": "Saxon Square", "payment_info": "Free", "accessible": "True", "radar": "Unknown", "women": "True", "men": "True", "baby_change": "True", "Mon": "Unknown", "Tue": "Unknown", "Wed": "Unknown", "Thu": "Unknown", "Fri": "Unknown", "Sat": "Unknown", "Sun": "Unknown", "index_right": 82, "park_offical_id": "BOUCH_235" }, "geometry": { "type": "Point", "coordinates": [ -1.7769193, 50.7348883 ] } }
]
}
