{
"type": "FeatureCollection",
"name": "BOUCH_86_toilets",
"crs": { "type": "name", "properties": { "name": "urn:ogc:def:crs:OGC:1.3:CRS84" } },
"features": [
{ "type": "Feature", "properties": { "name": "Fishermans Walk Public Toilets", "payment_info": "Free", "accessible": "False", "radar": "Unknown", "women": "True", "men": "True", "baby_change": "Unknown", "Mon": "Unknown", "Tue": "Unknown", "Wed": "Unknown", "Thu": "Unknown", "Fri": "Unknown", "Sat": "Unknown", "Sun": "Unknown", "index_right": 183, "park_offical_id": "BOUCH_86" }, "geometry": { "type": "Point", "coordinates": [ -1.8181368, 50.7258045 ] } }
]
}
