{
"type": "FeatureCollection",
"name": "FORDE_3",
"crs": { "type": "name", "properties": { "name": "urn:ogc:def:crs:OGC:1.3:CRS84" } },
"features": [
{ "type": "Feature", "properties": { "osm_id": 9101896043, "name": null, "amenity": "bench", "man_made": null, "leisure": null, "playground": null, "memorial": null }, "geometry": { "type": "Point", "coordinates": [ -2.609389, 51.7928136 ] } },
{ "type": "Feature", "properties": { "osm_id": 9101896085, "name": null, "amenity": "bench", "man_made": null, "leisure": null, "playground": null, "memorial": null }, "geometry": { "type": "Point", "coordinates": [ -2.6090387, 51.7932744 ] } },
{ "type": "Feature", "properties": { "osm_id": 9101896095, "name": null, "amenity": "bench", "man_made": null, "leisure": null, "playground": null, "memorial": null }, "geometry": { "type": "Point", "coordinates": [ -2.6089526, 51.7938637 ] } },
{ "type": "Feature", "properties": { "osm_id": 9101896050, "name": null, "amenity": "bench", "man_made": null, "leisure": null, "playground": null, "memorial": null }, "geometry": { "type": "Point", "coordinates": [ -2.6092265, 51.7940438 ] } },
{ "type": "Feature", "properties": { "osm_id": 9101896039, "name": null, "amenity": "bench", "man_made": null, "leisure": null, "playground": null, "memorial": null }, "geometry": { "type": "Point", "coordinates": [ -2.6092245, 51.7940574 ] } },
{ "type": "Feature", "properties": { "osm_id": 9101896083, "name": null, "amenity": "bench", "man_made": null, "leisure": null, "playground": null, "memorial": null }, "geometry": { "type": "Point", "coordinates": [ -2.6092208, 51.7940746 ] } },
{ "type": "Feature", "properties": { "osm_id": 9101896064, "name": null, "amenity": "bench", "man_made": null, "leisure": null, "playground": null, "memorial": null }, "geometry": { "type": "Point", "coordinates": [ -2.6092267, 51.7940888 ] } },
{ "type": "Feature", "properties": { "osm_id": 9101896046, "name": null, "amenity": "bench", "man_made": null, "leisure": null, "playground": null, "memorial": null }, "geometry": { "type": "Point", "coordinates": [ -2.6092326, 51.7941019 ] } },
{ "type": "Feature", "properties": { "osm_id": 9101896091, "name": null, "amenity": "bench", "man_made": null, "leisure": null, "playground": null, "memorial": null }, "geometry": { "type": "Point", "coordinates": [ -2.6092387, 51.794114 ] } },
{ "type": "Feature", "properties": { "osm_id": 9101896072, "name": null, "amenity": "bench", "man_made": null, "leisure": null, "playground": null, "memorial": null }, "geometry": { "type": "Point", "coordinates": [ -2.6092491, 51.794124 ] } },
{ "type": "Feature", "properties": { "osm_id": 9101896053, "name": null, "amenity": "bench", "man_made": null, "leisure": null, "playground": null, "memorial": null }, "geometry": { "type": "Point", "coordinates": [ -2.6092663, 51.7941379 ] } },
{ "type": "Feature", "properties": { "osm_id": 9101896098, "name": null, "amenity": "bench", "man_made": null, "leisure": null, "playground": null, "memorial": null }, "geometry": { "type": "Point", "coordinates": [ -2.6092882, 51.7941457 ] } },
{ "type": "Feature", "properties": { "osm_id": 9101896068, "name": null, "amenity": "bench", "man_made": null, "leisure": null, "playground": null, "memorial": null }, "geometry": { "type": "Point", "coordinates": [ -2.6093121, 51.7941512 ] } },
{ "type": "Feature", "properties": { "osm_id": 9101896057, "name": null, "amenity": "bench", "man_made": null, "leisure": null, "playground": null, "memorial": null }, "geometry": { "type": "Point", "coordinates": [ -2.6101755, 51.7943811 ] } }
]
}
