{
"type": "FeatureCollection",
"name": "SOUHA_103",
"crs": { "type": "name", "properties": { "name": "urn:ogc:def:crs:OGC:1.3:CRS84" } },
"features": [
{ "type": "Feature", "properties": { "osm_id": 9630461721, "name": null, "amenity": "bench", "man_made": null, "leisure": null, "playground": null, "memorial": null }, "geometry": { "type": "Point", "coordinates": [ -4.0512209, 50.3648964 ] } },
{ "type": "Feature", "properties": { "osm_id": 9851777196, "name": null, "amenity": null, "man_made": null, "leisure": "picnic_table", "playground": null, "memorial": null }, "geometry": { "type": "Point", "coordinates": [ -4.0512904, 50.3649677 ] } },
{ "type": "Feature", "properties": { "osm_id": 9851777195, "name": null, "amenity": null, "man_made": null, "leisure": "picnic_table", "playground": null, "memorial": null }, "geometry": { "type": "Point", "coordinates": [ -4.0512554, 50.3649908 ] } },
{ "type": "Feature", "properties": { "osm_id": 9630461722, "name": null, "amenity": null, "man_made": null, "leisure": "picnic_table", "playground": null, "memorial": null }, "geometry": { "type": "Point", "coordinates": [ -4.0512187, 50.3650157 ] } },
{ "type": "Feature", "properties": { "osm_id": 9851777197, "name": null, "amenity": null, "man_made": null, "leisure": "picnic_table", "playground": null, "memorial": null }, "geometry": { "type": "Point", "coordinates": [ -4.0514539, 50.3650817 ] } },
{ "type": "Feature", "properties": { "osm_id": 9851777198, "name": null, "amenity": null, "man_made": null, "leisure": "picnic_table", "playground": null, "memorial": null }, "geometry": { "type": "Point", "coordinates": [ -4.0514107, 50.3651018 ] } },
{ "type": "Feature", "properties": { "osm_id": 9630462222, "name": null, "amenity": null, "man_made": null, "leisure": "picnic_table", "playground": null, "memorial": null }, "geometry": { "type": "Point", "coordinates": [ -4.0513728, 50.3651249 ] } }
]
}
