{
"type": "FeatureCollection",
"name": "SOUHA_39",
"crs": { "type": "name", "properties": { "name": "urn:ogc:def:crs:OGC:1.3:CRS84" } },
"features": [
{ "type": "Feature", "properties": { "osm_id": 12750097267, "name": null, "amenity": "bench", "man_made": null, "leisure": null, "playground": null, "memorial": null }, "geometry": { "type": "Point", "coordinates": [ -3.5971017, 50.3837499 ] } },
{ "type": "Feature", "properties": { "osm_id": 10780560900, "name": null, "amenity": "bench", "man_made": null, "leisure": null, "playground": null, "memorial": null }, "geometry": { "type": "Point", "coordinates": [ -3.596831, 50.3838194 ] } },
{ "type": "Feature", "properties": { "osm_id": 12750097268, "name": null, "amenity": "bench", "man_made": null, "leisure": null, "playground": null, "memorial": null }, "geometry": { "type": "Point", "coordinates": [ -3.5981332, 50.3839738 ] } },
{ "type": "Feature", "properties": { "osm_id": 10780560899, "name": null, "amenity": "bench", "man_made": null, "leisure": null, "playground": null, "memorial": null }, "geometry": { "type": "Point", "coordinates": [ -3.5969454, 50.3839948 ] } },
{ "type": "Feature", "properties": { "osm_id": 10780560898, "name": null, "amenity": "bench", "man_made": null, "leisure": null, "playground": null, "memorial": null }, "geometry": { "type": "Point", "coordinates": [ -3.5969684, 50.3840174 ] } },
{ "type": "Feature", "properties": { "osm_id": 12750097269, "name": null, "amenity": "bench", "man_made": null, "leisure": null, "playground": null, "memorial": null }, "geometry": { "type": "Point", "coordinates": [ -3.5981329, 50.384092 ] } },
{ "type": "Feature", "properties": { "osm_id": 10780560897, "name": null, "amenity": "bench", "man_made": null, "leisure": null, "playground": null, "memorial": null }, "geometry": { "type": "Point", "coordinates": [ -3.597079, 50.3841568 ] } },
{ "type": "Feature", "properties": { "osm_id": 10780560896, "name": null, "amenity": "bench", "man_made": null, "leisure": null, "playground": null, "memorial": null }, "geometry": { "type": "Point", "coordinates": [ -3.5971038, 50.3841754 ] } },
{ "type": "Feature", "properties": { "osm_id": 12750097270, "name": null, "amenity": "bench", "man_made": null, "leisure": null, "playground": null, "memorial": null }, "geometry": { "type": "Point", "coordinates": [ -3.5982059, 50.3842132 ] } },
{ "type": "Feature", "properties": { "osm_id": 12750097271, "name": null, "amenity": "bench", "man_made": null, "leisure": null, "playground": null, "memorial": null }, "geometry": { "type": "Point", "coordinates": [ -3.5982046, 50.3843624 ] } },
{ "type": "Feature", "properties": { "osm_id": 10780560895, "name": null, "amenity": "bench", "man_made": null, "leisure": null, "playground": null, "memorial": null }, "geometry": { "type": "Point", "coordinates": [ -3.5972536, 50.3843646 ] } },
{ "type": "Feature", "properties": { "osm_id": 10780560894, "name": null, "amenity": "bench", "man_made": null, "leisure": null, "playground": null, "memorial": null }, "geometry": { "type": "Point", "coordinates": [ -3.5972773, 50.384386 ] } },
{ "type": "Feature", "properties": { "osm_id": 12750097272, "name": null, "amenity": null, "man_made": null, "leisure": "picnic_table", "playground": null, "memorial": null }, "geometry": { "type": "Point", "coordinates": [ -3.5973842, 50.3844039 ] } },
{ "type": "Feature", "properties": { "osm_id": 12750097273, "name": null, "amenity": null, "man_made": null, "leisure": "picnic_table", "playground": null, "memorial": null }, "geometry": { "type": "Point", "coordinates": [ -3.5974004, 50.384426 ] } },
{ "type": "Feature", "properties": { "osm_id": 12750097274, "name": null, "amenity": "bench", "man_made": null, "leisure": null, "playground": null, "memorial": null }, "geometry": { "type": "Point", "coordinates": [ -3.597308, 50.3844261 ] } }
]
}
