{
"type": "FeatureCollection",
"name": "SOUHA_46",
"crs": { "type": "name", "properties": { "name": "urn:ogc:def:crs:OGC:1.3:CRS84" } },
"features": [
{ "type": "Feature", "properties": { "osm_id": 3453942700, "name": null, "amenity": "bench", "man_made": null, "leisure": null, "playground": null, "memorial": null }, "geometry": { "type": "Point", "coordinates": [ -3.7073858, 50.4308401 ] } },
{ "type": "Feature", "properties": { "osm_id": 4387193791, "name": null, "amenity": "bench", "man_made": null, "leisure": null, "playground": null, "memorial": null }, "geometry": { "type": "Point", "coordinates": [ -3.7065631, 50.4309459 ] } }
]
}
