{
"type": "FeatureCollection",
"name": "52f22e836e85_visibility",
"crs": { "type": "name", "properties": { "name": "urn:ogc:def:crs:OGC:1.3:CRS84" } },
"features": [
{ "type": "Feature", "properties": { "visible_points": 0, "total_points": 49, "visibility_pct": 0.0 }, "geometry": { "type": "Point", "coordinates": [ -3.212407315828413, 50.871325923393094 ] } },
{ "type": "Feature", "properties": { "visible_points": 0, "total_points": 51, "visibility_pct": 0.0 }, "geometry": { "type": "Point", "coordinates": [ -3.212210437318578, 50.871327968861593 ] } },
{ "type": "Feature", "properties": { "visible_points": 0, "total_points": 52, "visibility_pct": 0.0 }, "geometry": { "type": "Point", "coordinates": [ -3.212013558786286, 50.871330013998048 ] } },
{ "type": "Feature", "properties": { "visible_points": 0, "total_points": 56, "visibility_pct": 0.0 }, "geometry": { "type": "Point", "coordinates": [ -3.212311676412778, 50.871434833491087 ] } },
{ "type": "Feature", "properties": { "visible_points": 0, "total_points": 57, "visibility_pct": 0.0 }, "geometry": { "type": "Point", "coordinates": [ -3.212114797450125, 50.871436878800999 ] } },
{ "type": "Feature", "properties": { "visible_points": 0, "total_points": 56, "visibility_pct": 0.0 }, "geometry": { "type": "Point", "coordinates": [ -3.211917918465021, 50.871438923778847 ] } },
{ "type": "Feature", "properties": { "visible_points": 0, "total_points": 55, "visibility_pct": 0.0 }, "geometry": { "type": "Point", "coordinates": [ -3.211721039457468, 50.87144096842465 ] } },
{ "type": "Feature", "properties": { "visible_points": 0, "total_points": 61, "visibility_pct": 0.0 }, "geometry": { "type": "Point", "coordinates": [ -3.212216036566771, 50.871543743511374 ] } },
{ "type": "Feature", "properties": { "visible_points": 0, "total_points": 61, "visibility_pct": 0.0 }, "geometry": { "type": "Point", "coordinates": [ -3.212019157151298, 50.871545788662694 ] } },
{ "type": "Feature", "properties": { "visible_points": 0, "total_points": 60, "visibility_pct": 0.0 }, "geometry": { "type": "Point", "coordinates": [ -3.211822277713381, 50.871547833481962 ] } },
{ "type": "Feature", "properties": { "visible_points": 0, "total_points": 58, "visibility_pct": 0.0 }, "geometry": { "type": "Point", "coordinates": [ -3.211625398253017, 50.871549877969173 ] } },
{ "type": "Feature", "properties": { "visible_points": 2, "total_points": 61, "visibility_pct": 3.278688524590164 }, "geometry": { "type": "Point", "coordinates": [ -3.212317276136226, 50.871650608129237 ] } },
{ "type": "Feature", "properties": { "visible_points": 0, "total_points": 61, "visibility_pct": 0.0 }, "geometry": { "type": "Point", "coordinates": [ -3.21212039629039, 50.871652653453999 ] } },
{ "type": "Feature", "properties": { "visible_points": 0, "total_points": 61, "visibility_pct": 0.0 }, "geometry": { "type": "Point", "coordinates": [ -3.211923516422098, 50.871654698446726 ] } },
{ "type": "Feature", "properties": { "visible_points": 0, "total_points": 61, "visibility_pct": 0.0 }, "geometry": { "type": "Point", "coordinates": [ -3.211726636531363, 50.87165674310738 ] } },
{ "type": "Feature", "properties": { "visible_points": 1, "total_points": 61, "visibility_pct": 1.639344262295082 }, "geometry": { "type": "Point", "coordinates": [ -3.212221635882287, 50.871759518152778 ] } },
{ "type": "Feature", "properties": { "visible_points": 1, "total_points": 61, "visibility_pct": 1.639344262295082 }, "geometry": { "type": "Point", "coordinates": [ -3.212024755583629, 50.871761563318948 ] } },
{ "type": "Feature", "properties": { "visible_points": 0, "total_points": 54, "visibility_pct": 0.0 }, "geometry": { "type": "Point", "coordinates": [ -3.212322875927004, 50.871866382758988 ] } },
{ "type": "Feature", "properties": { "visible_points": 0, "total_points": 56, "visibility_pct": 0.0 }, "geometry": { "type": "Point", "coordinates": [ -3.212125995197969, 50.871868428098622 ] } },
{ "type": "Feature", "properties": { "visible_points": 0, "total_points": 56, "visibility_pct": 0.0 }, "geometry": { "type": "Point", "coordinates": [ -3.211929114446485, 50.871870473106213 ] } },
{ "type": "Feature", "properties": { "visible_points": 0, "total_points": 49, "visibility_pct": 0.0 }, "geometry": { "type": "Point", "coordinates": [ -3.212227235265127, 50.87197529278577 ] } },
{ "type": "Feature", "properties": { "visible_points": 0, "total_points": 49, "visibility_pct": 0.0 }, "geometry": { "type": "Point", "coordinates": [ -3.212030354083269, 50.871977337966811 ] } },
{ "type": "Feature", "properties": { "visible_points": 0, "total_points": 43, "visibility_pct": 0.0 }, "geometry": { "type": "Point", "coordinates": [ -3.212131594172871, 50.872084202734868 ] } }
]
}
