{
"type": "FeatureCollection",
"name": "8f3012f08b6c_visibility",
"crs": { "type": "name", "properties": { "name": "urn:ogc:def:crs:OGC:1.3:CRS84" } },
"features": [
{ "type": "Feature", "properties": { "visible_points": 11, "total_points": 52, "visibility_pct": 21.153846153846153 }, "geometry": { "type": "Point", "coordinates": [ -3.255908042899251, 50.746483120539828 ] } },
{ "type": "Feature", "properties": { "visible_points": 0, "total_points": 52, "visibility_pct": 0.0 }, "geometry": { "type": "Point", "coordinates": [ -3.255711691423411, 50.746485235429148 ] } },
{ "type": "Feature", "properties": { "visible_points": 1, "total_points": 51, "visibility_pct": 1.9607843137254901 }, "geometry": { "type": "Point", "coordinates": [ -3.255515339923893, 50.746487349987881 ] } },
{ "type": "Feature", "properties": { "visible_points": 0, "total_points": 49, "visibility_pct": 0.0 }, "geometry": { "type": "Point", "coordinates": [ -3.255318988400715, 50.74648946421604 ] } },
{ "type": "Feature", "properties": { "visible_points": 12, "total_points": 55, "visibility_pct": 21.818181818181817 }, "geometry": { "type": "Point", "coordinates": [ -3.25600910782556, 50.746589950409614 ] } },
{ "type": "Feature", "properties": { "visible_points": 10, "total_points": 55, "visibility_pct": 18.181818181818183 }, "geometry": { "type": "Point", "coordinates": [ -3.255812755908777, 50.746592065472058 ] } },
{ "type": "Feature", "properties": { "visible_points": 0, "total_points": 55, "visibility_pct": 0.0 }, "geometry": { "type": "Point", "coordinates": [ -3.255616403968322, 50.746594180203921 ] } },
{ "type": "Feature", "properties": { "visible_points": 1, "total_points": 54, "visibility_pct": 1.8518518518518516 }, "geometry": { "type": "Point", "coordinates": [ -3.255420052004196, 50.746596294605204 ] } },
{ "type": "Feature", "properties": { "visible_points": 1, "total_points": 51, "visibility_pct": 1.9607843137254901 }, "geometry": { "type": "Point", "coordinates": [ -3.255223700016411, 50.746598408675922 ] } },
{ "type": "Feature", "properties": { "visible_points": 8, "total_points": 55, "visibility_pct": 14.545454545454545 }, "geometry": { "type": "Point", "coordinates": [ -3.255913820858745, 50.746698895422341 ] } },
{ "type": "Feature", "properties": { "visible_points": 0, "total_points": 55, "visibility_pct": 0.0 }, "geometry": { "type": "Point", "coordinates": [ -3.25571746847735, 50.746701010327342 ] } },
{ "type": "Feature", "properties": { "visible_points": 1, "total_points": 55, "visibility_pct": 1.8181818181818181 }, "geometry": { "type": "Point", "coordinates": [ -3.255521116072281, 50.746703124901778 ] } },
{ "type": "Feature", "properties": { "visible_points": 0, "total_points": 55, "visibility_pct": 0.0 }, "geometry": { "type": "Point", "coordinates": [ -3.255324763643541, 50.746705239145633 ] } },
{ "type": "Feature", "properties": { "visible_points": 10, "total_points": 53, "visibility_pct": 18.867924528301888 }, "geometry": { "type": "Point", "coordinates": [ -3.256014886273322, 50.746805725280041 ] } },
{ "type": "Feature", "properties": { "visible_points": 7, "total_points": 55, "visibility_pct": 12.727272727272727 }, "geometry": { "type": "Point", "coordinates": [ -3.255818533450982, 50.74680784035818 ] } },
{ "type": "Feature", "properties": { "visible_points": 0, "total_points": 55, "visibility_pct": 0.0 }, "geometry": { "type": "Point", "coordinates": [ -3.255622180604965, 50.746809955105746 ] } },
{ "type": "Feature", "properties": { "visible_points": 0, "total_points": 55, "visibility_pct": 0.0 }, "geometry": { "type": "Point", "coordinates": [ -3.255425827735278, 50.74681206952274 ] } },
{ "type": "Feature", "properties": { "visible_points": 6, "total_points": 52, "visibility_pct": 11.538461538461538 }, "geometry": { "type": "Point", "coordinates": [ -3.255919598889221, 50.746914670296412 ] } },
{ "type": "Feature", "properties": { "visible_points": 4, "total_points": 54, "visibility_pct": 7.4074074074074066 }, "geometry": { "type": "Point", "coordinates": [ -3.255723245602255, 50.746916785217117 ] } },
{ "type": "Feature", "properties": { "visible_points": 0, "total_points": 55, "visibility_pct": 0.0 }, "geometry": { "type": "Point", "coordinates": [ -3.255526892291624, 50.746918899807248 ] } },
{ "type": "Feature", "properties": { "visible_points": 1, "total_points": 48, "visibility_pct": 2.083333333333333 }, "geometry": { "type": "Point", "coordinates": [ -3.255824311064158, 50.747023615235868 ] } }
]
}
