{
"type": "FeatureCollection",
"name": "c241d53ac303_visibility",
"crs": { "type": "name", "properties": { "name": "urn:ogc:def:crs:OGC:1.3:CRS84" } },
"features": [
{ "type": "Feature", "properties": { "visible_points": 3, "total_points": 47, "visibility_pct": 6.3829787234042552 }, "geometry": { "type": "Point", "coordinates": [ -3.202187600357329, 50.788190058621858 ] } },
{ "type": "Feature", "properties": { "visible_points": 5, "total_points": 53, "visibility_pct": 9.433962264150944 }, "geometry": { "type": "Point", "coordinates": [ -3.201991066783219, 50.78819208478447 ] } },
{ "type": "Feature", "properties": { "visible_points": 4, "total_points": 56, "visibility_pct": 7.1428571428571423 }, "geometry": { "type": "Point", "coordinates": [ -3.201794533186225, 50.788194110615677 ] } },
{ "type": "Feature", "properties": { "visible_points": 8, "total_points": 46, "visibility_pct": 17.391304347826086 }, "geometry": { "type": "Point", "coordinates": [ -3.202288636189771, 50.788296932699495 ] } },
{ "type": "Feature", "properties": { "visible_points": 0, "total_points": 52, "visibility_pct": 0.0 }, "geometry": { "type": "Point", "coordinates": [ -3.202092102168395, 50.788298959025909 ] } },
{ "type": "Feature", "properties": { "visible_points": 0, "total_points": 56, "visibility_pct": 0.0 }, "geometry": { "type": "Point", "coordinates": [ -3.201895568124129, 50.788300985020904 ] } },
{ "type": "Feature", "properties": { "visible_points": 0, "total_points": 57, "visibility_pct": 0.0 }, "geometry": { "type": "Point", "coordinates": [ -3.201699034056974, 50.788303010684466 ] } },
{ "type": "Feature", "properties": { "visible_points": 6, "total_points": 57, "visibility_pct": 10.526315789473683 }, "geometry": { "type": "Point", "coordinates": [ -3.201502499966939, 50.788305036016617 ] } },
{ "type": "Feature", "properties": { "visible_points": 5, "total_points": 51, "visibility_pct": 9.8039215686274517 }, "geometry": { "type": "Point", "coordinates": [ -3.201305965840419, 50.788307061004126 ] } },
{ "type": "Feature", "properties": { "visible_points": 4, "total_points": 44, "visibility_pct": 9.0909090909090917 }, "geometry": { "type": "Point", "coordinates": [ -3.201109431601058, 50.788309085456859 ] } },
{ "type": "Feature", "properties": { "visible_points": 4, "total_points": 50, "visibility_pct": 8.0 }, "geometry": { "type": "Point", "coordinates": [ -3.202193138023719, 50.788405833184569 ] } },
{ "type": "Feature", "properties": { "visible_points": 0, "total_points": 56, "visibility_pct": 0.0 }, "geometry": { "type": "Point", "coordinates": [ -3.201996603532177, 50.788407859343351 ] } },
{ "type": "Feature", "properties": { "visible_points": 1, "total_points": 57, "visibility_pct": 1.7543859649122806 }, "geometry": { "type": "Point", "coordinates": [ -3.201800069017749, 50.788409885170715 ] } },
{ "type": "Feature", "properties": { "visible_points": 0, "total_points": 57, "visibility_pct": 0.0 }, "geometry": { "type": "Point", "coordinates": [ -3.20160353448044, 50.788411910666639 ] } },
{ "type": "Feature", "properties": { "visible_points": 0, "total_points": 53, "visibility_pct": 0.0 }, "geometry": { "type": "Point", "coordinates": [ -3.201406999920245, 50.788413935831159 ] } },
{ "type": "Feature", "properties": { "visible_points": 0, "total_points": 47, "visibility_pct": 0.0 }, "geometry": { "type": "Point", "coordinates": [ -3.201210465285236, 50.788415960584864 ] } },
{ "type": "Feature", "properties": { "visible_points": 6, "total_points": 57, "visibility_pct": 10.526315789473683 }, "geometry": { "type": "Point", "coordinates": [ -3.201901104448678, 50.788516759574172 ] } },
{ "type": "Feature", "properties": { "visible_points": 8, "total_points": 57, "visibility_pct": 14.035087719298245 }, "geometry": { "type": "Point", "coordinates": [ -3.201704569464089, 50.788518785233904 ] } },
{ "type": "Feature", "properties": { "visible_points": 6, "total_points": 54, "visibility_pct": 11.111111111111111 }, "geometry": { "type": "Point", "coordinates": [ -3.201508034456616, 50.788520810562218 ] } },
{ "type": "Feature", "properties": { "visible_points": 6, "total_points": 48, "visibility_pct": 12.5 }, "geometry": { "type": "Point", "coordinates": [ -3.201311499415638, 50.788522835548228 ] } },
{ "type": "Feature", "properties": { "visible_points": 6, "total_points": 42, "visibility_pct": 14.285714285714285 }, "geometry": { "type": "Point", "coordinates": [ -3.201114964269296, 50.788524860009431 ] } },
{ "type": "Feature", "properties": { "visible_points": 8, "total_points": 48, "visibility_pct": 16.666666666666664 }, "geometry": { "type": "Point", "coordinates": [ -3.201412533985496, 50.78862971037114 ] } },
{ "type": "Feature", "properties": { "visible_points": 10, "total_points": 43, "visibility_pct": 23.255813953488371 }, "geometry": { "type": "Point", "coordinates": [ -3.201215998439627, 50.788631735130075 ] } }
]
}
