{
"type": "FeatureCollection",
"name": "c332998a98a3_visibility",
"crs": { "type": "name", "properties": { "name": "urn:ogc:def:crs:OGC:1.3:CRS84" } },
"features": [
{ "type": "Feature", "properties": { "visible_points": 0, "total_points": 51, "visibility_pct": 0.0 }, "geometry": { "type": "Point", "coordinates": [ -3.163706730837283, 50.697883209221395 ] } },
{ "type": "Feature", "properties": { "visible_points": 6, "total_points": 52, "visibility_pct": 11.538461538461538 }, "geometry": { "type": "Point", "coordinates": [ -3.163510574797839, 50.697885166564575 ] } },
{ "type": "Feature", "properties": { "visible_points": 7, "total_points": 52, "visibility_pct": 13.461538461538462 }, "geometry": { "type": "Point", "coordinates": [ -3.163314418736701, 50.697887123577743 ] } },
{ "type": "Feature", "properties": { "visible_points": 6, "total_points": 49, "visibility_pct": 12.244897959183673 }, "geometry": { "type": "Point", "coordinates": [ -3.163118262653862, 50.697889080260943 ] } },
{ "type": "Feature", "properties": { "visible_points": 0, "total_points": 52, "visibility_pct": 0.0 }, "geometry": { "type": "Point", "coordinates": [ -3.163807480408827, 50.697990123418222 ] } },
{ "type": "Feature", "properties": { "visible_points": 2, "total_points": 52, "visibility_pct": 3.8461538461538463 }, "geometry": { "type": "Point", "coordinates": [ -3.163611323933423, 50.697992080935087 ] } },
{ "type": "Feature", "properties": { "visible_points": 6, "total_points": 52, "visibility_pct": 11.538461538461538 }, "geometry": { "type": "Point", "coordinates": [ -3.163415167436313, 50.697994038121955 ] } },
{ "type": "Feature", "properties": { "visible_points": 0, "total_points": 52, "visibility_pct": 0.0 }, "geometry": { "type": "Point", "coordinates": [ -3.163219010917513, 50.697995994978847 ] } },
{ "type": "Feature", "properties": { "visible_points": 0, "total_points": 50, "visibility_pct": 0.0 }, "geometry": { "type": "Point", "coordinates": [ -3.163022854377013, 50.697997951505741 ] } },
{ "type": "Feature", "properties": { "visible_points": 1, "total_points": 52, "visibility_pct": 1.9230769230769231 }, "geometry": { "type": "Point", "coordinates": [ -3.163712073526658, 50.698098995212277 ] } },
{ "type": "Feature", "properties": { "visible_points": 0, "total_points": 52, "visibility_pct": 0.0 }, "geometry": { "type": "Point", "coordinates": [ -3.163515916593588, 50.69810095257283 ] } },
{ "type": "Feature", "properties": { "visible_points": 0, "total_points": 52, "visibility_pct": 0.0 }, "geometry": { "type": "Point", "coordinates": [ -3.163319759638813, 50.698102909603421 ] } },
{ "type": "Feature", "properties": { "visible_points": 0, "total_points": 52, "visibility_pct": 0.0 }, "geometry": { "type": "Point", "coordinates": [ -3.163123602662347, 50.698104866304014 ] } },
{ "type": "Feature", "properties": { "visible_points": 0, "total_points": 51, "visibility_pct": 0.0 }, "geometry": { "type": "Point", "coordinates": [ -3.163812823577556, 50.698205909396123 ] } },
{ "type": "Feature", "properties": { "visible_points": 0, "total_points": 52, "visibility_pct": 0.0 }, "geometry": { "type": "Point", "coordinates": [ -3.163616666208517, 50.698207866930382 ] } },
{ "type": "Feature", "properties": { "visible_points": 0, "total_points": 52, "visibility_pct": 0.0 }, "geometry": { "type": "Point", "coordinates": [ -3.163420508817775, 50.698209824134643 ] } },
{ "type": "Feature", "properties": { "visible_points": 0, "total_points": 52, "visibility_pct": 0.0 }, "geometry": { "type": "Point", "coordinates": [ -3.163224351405335, 50.698211781008951 ] } },
{ "type": "Feature", "properties": { "visible_points": 0, "total_points": 51, "visibility_pct": 0.0 }, "geometry": { "type": "Point", "coordinates": [ -3.163717416281111, 50.698314781194597 ] } },
{ "type": "Feature", "properties": { "visible_points": 0, "total_points": 52, "visibility_pct": 0.0 }, "geometry": { "type": "Point", "coordinates": [ -3.163521258454394, 50.698316738572558 ] } },
{ "type": "Feature", "properties": { "visible_points": 0, "total_points": 52, "visibility_pct": 0.0 }, "geometry": { "type": "Point", "coordinates": [ -3.163325100605983, 50.698318695620529 ] } },
{ "type": "Feature", "properties": { "visible_points": 1, "total_points": 48, "visibility_pct": 2.083333333333333 }, "geometry": { "type": "Point", "coordinates": [ -3.163229691958207, 50.698427567030492 ] } }
]
}
