{
"type": "FeatureCollection",
"name": "e6c92380b0f6_visibility",
"crs": { "type": "name", "properties": { "name": "urn:ogc:def:crs:OGC:1.3:CRS84" } },
"features": [
{ "type": "Feature", "properties": { "visible_points": 5, "total_points": 47, "visibility_pct": 10.638297872340425 }, "geometry": { "type": "Point", "coordinates": [ -3.463995512292147, 50.74195882175178 ] } },
{ "type": "Feature", "properties": { "visible_points": 5, "total_points": 53, "visibility_pct": 9.433962264150944 }, "geometry": { "type": "Point", "coordinates": [ -3.463799197211359, 50.741961287164543 ] } },
{ "type": "Feature", "properties": { "visible_points": 4, "total_points": 59, "visibility_pct": 6.7796610169491522 }, "geometry": { "type": "Point", "coordinates": [ -3.463602882102983, 50.741963752246882 ] } },
{ "type": "Feature", "properties": { "visible_points": 0, "total_points": 62, "visibility_pct": 0.0 }, "geometry": { "type": "Point", "coordinates": [ -3.463406566967033, 50.741966216998733 ] } },
{ "type": "Feature", "properties": { "visible_points": 0, "total_points": 58, "visibility_pct": 0.0 }, "geometry": { "type": "Point", "coordinates": [ -3.463210251803515, 50.741968681420168 ] } },
{ "type": "Feature", "properties": { "visible_points": 1, "total_points": 53, "visibility_pct": 1.8867924528301887 }, "geometry": { "type": "Point", "coordinates": [ -3.463013936612421, 50.741971145511158 ] } },
{ "type": "Feature", "properties": { "visible_points": 2, "total_points": 48, "visibility_pct": 4.1666666666666661 }, "geometry": { "type": "Point", "coordinates": [ -3.462817621393772, 50.741973609271682 ] } },
{ "type": "Feature", "properties": { "visible_points": 4, "total_points": 42, "visibility_pct": 9.5238095238095237 }, "geometry": { "type": "Point", "coordinates": [ -3.462621306147555, 50.741976072701782 ] } },
{ "type": "Feature", "properties": { "visible_points": 1, "total_points": 38, "visibility_pct": 2.6315789473684208 }, "geometry": { "type": "Point", "coordinates": [ -3.464293351708472, 50.74206300034772 ] } },
{ "type": "Feature", "properties": { "visible_points": 0, "total_points": 44, "visibility_pct": 0.0 }, "geometry": { "type": "Point", "coordinates": [ -3.464097036216648, 50.742065466265096 ] } },
{ "type": "Feature", "properties": { "visible_points": 0, "total_points": 50, "visibility_pct": 0.0 }, "geometry": { "type": "Point", "coordinates": [ -3.46390072069724, 50.74206793185202 ] } },
{ "type": "Feature", "properties": { "visible_points": 0, "total_points": 56, "visibility_pct": 0.0 }, "geometry": { "type": "Point", "coordinates": [ -3.463704405150246, 50.742070397108499 ] } },
{ "type": "Feature", "properties": { "visible_points": 0, "total_points": 62, "visibility_pct": 0.0 }, "geometry": { "type": "Point", "coordinates": [ -3.463508089575679, 50.742072862034533 ] } },
{ "type": "Feature", "properties": { "visible_points": 0, "total_points": 61, "visibility_pct": 0.0 }, "geometry": { "type": "Point", "coordinates": [ -3.463311773973537, 50.742075326630136 ] } },
{ "type": "Feature", "properties": { "visible_points": 0, "total_points": 56, "visibility_pct": 0.0 }, "geometry": { "type": "Point", "coordinates": [ -3.463115458343824, 50.742077790895266 ] } },
{ "type": "Feature", "properties": { "visible_points": 0, "total_points": 51, "visibility_pct": 0.0 }, "geometry": { "type": "Point", "coordinates": [ -3.462919142686539, 50.742080254829979 ] } },
{ "type": "Feature", "properties": { "visible_points": 0, "total_points": 45, "visibility_pct": 0.0 }, "geometry": { "type": "Point", "coordinates": [ -3.4627228270017, 50.742082718434212 ] } },
{ "type": "Feature", "properties": { "visible_points": 0, "total_points": 40, "visibility_pct": 0.0 }, "geometry": { "type": "Point", "coordinates": [ -3.464198560589302, 50.742172110760883 ] } },
{ "type": "Feature", "properties": { "visible_points": 0, "total_points": 46, "visibility_pct": 0.0 }, "geometry": { "type": "Point", "coordinates": [ -3.464002244622552, 50.7421745765308 ] } },
{ "type": "Feature", "properties": { "visible_points": 3, "total_points": 47, "visibility_pct": 6.3829787234042552 }, "geometry": { "type": "Point", "coordinates": [ -3.462824348241063, 50.742189364212472 ] } },
{ "type": "Feature", "properties": { "visible_points": 2, "total_points": 41, "visibility_pct": 4.8780487804878048 }, "geometry": { "type": "Point", "coordinates": [ -3.46262803208116, 50.742191827669508 ] } }
]
}
