{
"type": "FeatureCollection",
"name": "EXETE_24_toilets",
"crs": { "type": "name", "properties": { "name": "urn:ogc:def:crs:OGC:1.3:CRS84" } },
"features": [
{ "type": "Feature", "properties": { "name": "King George playing fields", "payment_info": "Free", "accessible": "False", "radar": "Unknown", "women": "True", "men": "True", "baby_change": "Unknown", "Mon": "08:00-20:00", "Tue": "08:00-20:00", "Wed": "08:00-20:00", "Thu": "08:00-20:00", "Fri": "08:00-20:00", "Sat": "08:00-20:00", "Sun": "08:00-20:00", "index_right": 42, "park_offical_id": "EXETE_24" }, "geometry": { "type": "Point", "coordinates": [ -3.496087, 50.700898 ] } }
]
}
