{
"type": "FeatureCollection",
"name": "EXETE_32_toilets",
"crs": { "type": "name", "properties": { "name": "urn:ogc:def:crs:OGC:1.3:CRS84" } },
"features": [
{ "type": "Feature", "properties": { "name": "RDE Hospital", "payment_info": "Free", "accessible": "True", "radar": "False", "women": "True", "men": "True", "baby_change": "Unknown", "Mon": "Unknown", "Tue": "Unknown", "Wed": "Unknown", "Thu": "Unknown", "Fri": "Unknown", "Sat": "Unknown", "Sun": "Unknown", "index_right": 51, "park_offical_id": "EXETE_32" }, "geometry": { "type": "Point", "coordinates": [ -3.506661057, 50.716324791 ] } },
{ "type": "Feature", "properties": { "name": "Lidl", "payment_info": "Free", "accessible": "Unknown", "radar": "Unknown", "women": "True", "men": "True", "baby_change": "Unknown", "Mon": "Unknown", "Tue": "Unknown", "Wed": "Unknown", "Thu": "Unknown", "Fri": "Unknown", "Sat": "Unknown", "Sun": "Unknown", "index_right": 51, "park_offical_id": "EXETE_32" }, "geometry": { "type": "Point", "coordinates": [ -3.498005569, 50.713876104 ] } }
]
}
