{
"type": "FeatureCollection",
"name": "CHELT_46_toilets",
"crs": { "type": "name", "properties": { "name": "urn:ogc:def:crs:OGC:1.3:CRS84" } },
"features": [
{ "type": "Feature", "properties": { "name": "Public Toilet", "payment_info": "Free", "accessible": "False", "radar": "Unknown", "women": "True", "men": "True", "baby_change": "Unknown", "Mon": "Unknown", "Tue": "Unknown", "Wed": "Unknown", "Thu": "Unknown", "Fri": "Unknown", "Sat": "Unknown", "Sun": "Unknown", "index_right": 48, "park_offical_id": "CHELT_46" }, "geometry": { "type": "Point", "coordinates": [ -2.072709203, 51.903376159 ] } },
{ "type": "Feature", "properties": { "name": "Unknown", "payment_info": "Free", "accessible": "True", "radar": "True", "women": "True", "men": "True", "baby_change": "True", "Mon": "Unknown", "Tue": "Unknown", "Wed": "Unknown", "Thu": "Unknown", "Fri": "Unknown", "Sat": "Unknown", "Sun": "Unknown", "index_right": 48, "park_offical_id": "CHELT_46" }, "geometry": { "type": "Point", "coordinates": [ -2.051374699, 51.905167636 ] } },
{ "type": "Feature", "properties": { "name": "Pittville Park", "payment_info": "Free", "accessible": "True", "radar": "False", "women": "True", "men": "True", "baby_change": "False", "Mon": "Unknown", "Tue": "Unknown", "Wed": "Unknown", "Thu": "Unknown", "Fri": "Unknown", "Sat": "Unknown", "Sun": "Unknown", "index_right": 48, "park_offical_id": "CHELT_46" }, "geometry": { "type": "Point", "coordinates": [ -2.068575919, 51.909989776 ] } },
{ "type": "Feature", "properties": { "name": "BP Connect Filling Station  Cheltenham", "payment_info": "Cost unknown", "accessible": "True", "radar": "False", "women": "Unknown", "men": "Unknown", "baby_change": "Unknown", "Mon": "00:00-00:00", "Tue": "00:00-00:00", "Wed": "00:00-00:00", "Thu": "00:00-00:00", "Fri": "00:00-00:00", "Sat": "00:00-00:00", "Sun": "00:00-00:00", "index_right": 48, "park_offical_id": "CHELT_46" }, "geometry": { "type": "Point", "coordinates": [ -2.062715292, 51.906899291 ] } }
]
}
