{
"type": "FeatureCollection",
"name": "CHELT_3_toilets",
"crs": { "type": "name", "properties": { "name": "urn:ogc:def:crs:OGC:1.3:CRS84" } },
"features": [
{ "type": "Feature", "properties": { "name": "BP Connect Filling Station  Cheltenham", "payment_info": "Cost unknown", "accessible": "True", "radar": "False", "women": "Unknown", "men": "Unknown", "baby_change": "Unknown", "Mon": "00:00-00:00", "Tue": "00:00-00:00", "Wed": "00:00-00:00", "Thu": "00:00-00:00", "Fri": "00:00-00:00", "Sat": "00:00-00:00", "Sun": "00:00-00:00", "index_right": 35, "park_offical_id": "CHELT_3" }, "geometry": { "type": "Point", "coordinates": [ -2.062715292, 51.906899291 ] } }
]
}
