{
"type": "FeatureCollection",
"name": "PLYMO_308_toilets",
"crs": { "type": "name", "properties": { "name": "urn:ogc:def:crs:OGC:1.3:CRS84" } },
"features": [
{ "type": "Feature", "properties": { "name": "Devils Point", "payment_info": "Free", "accessible": "False", "radar": "Unknown", "women": "True", "men": "True", "baby_change": "True", "Mon": "08:30-18:30", "Tue": "08:30-18:30", "Wed": "08:30-18:30", "Thu": "08:30-18:30", "Fri": "08:30-18:30", "Sat": "08:30-18:30", "Sun": "08:30-18:30", "index_right": 70, "park_offical_id": "PLYMO_308" }, "geometry": { "type": "Point", "coordinates": [ -4.161763044, 50.362407599 ] } },
{ "type": "Feature", "properties": { "name": "Richmond Walk", "payment_info": "20p", "accessible": "True", "radar": "Unknown", "women": "Unknown", "men": "Unknown", "baby_change": "Unknown", "Mon": "00:00-00:00", "Tue": "00:00-00:00", "Wed": "00:00-00:00", "Thu": "00:00-00:00", "Fri": "00:00-00:00", "Sat": "00:00-00:00", "Sun": "00:00-00:00", "index_right": 70, "park_offical_id": "PLYMO_308" }, "geometry": { "type": "Point", "coordinates": [ -4.168919921, 50.364921541 ] } },
{ "type": "Feature", "properties": { "name": "Unknown", "payment_info": "Free", "accessible": "False", "radar": "Unknown", "women": "Unknown", "men": "Unknown", "baby_change": "Unknown", "Mon": "Unknown", "Tue": "Unknown", "Wed": "Unknown", "Thu": "Unknown", "Fri": "Unknown", "Sat": "Unknown", "Sun": "Unknown", "index_right": 70, "park_offical_id": "PLYMO_308" }, "geometry": { "type": "Point", "coordinates": [ -4.1574509, 50.3653851 ] } },
{ "type": "Feature", "properties": { "name": "Cremyll Street", "payment_info": "Free", "accessible": "False", "radar": "Unknown", "women": "True", "men": "True", "baby_change": "Unknown", "Mon": "08:30-18:30", "Tue": "08:30-18:30", "Wed": "08:30-18:30", "Thu": "08:30-18:30", "Fri": "08:30-18:30", "Sat": "08:30-18:30", "Sun": "08:30-18:30", "index_right": 70, "park_offical_id": "PLYMO_308" }, "geometry": { "type": "Point", "coordinates": [ -4.162496358, 50.365856809 ] } }
]
}
