{
"type": "FeatureCollection",
"name": "PLYMO_123_toilets",
"crs": { "type": "name", "properties": { "name": "urn:ogc:def:crs:OGC:1.3:CRS84" } },
"features": [
{ "type": "Feature", "properties": { "name": "West Park Library", "payment_info": "Free", "accessible": "False", "radar": "False", "women": "Unknown", "men": "Unknown", "baby_change": "Unknown", "Mon": "Unknown", "Tue": "Unknown", "Wed": "Unknown", "Thu": "Unknown", "Fri": "Unknown", "Sat": "Unknown", "Sun": "Unknown", "index_right": 20, "park_offical_id": "PLYMO_123" }, "geometry": { "type": "Point", "coordinates": [ -4.166511297, 50.412570338 ] } },
{ "type": "Feature", "properties": { "name": "Tesco", "payment_info": "Cost unknown", "accessible": "True", "radar": "Unknown", "women": "True", "men": "True", "baby_change": "True", "Mon": "09:00-17:00", "Tue": "09:00-17:00", "Wed": "09:00-17:00", "Thu": "09:00-17:00", "Fri": "09:00-17:00", "Sat": "09:00-17:00", "Sun": "09:00-17:00", "index_right": 20, "park_offical_id": "PLYMO_123" }, "geometry": { "type": "Point", "coordinates": [ -4.149468541, 50.409582473 ] } }
]
}
