{
"type": "FeatureCollection",
"name": "PLYMO_9_toilets",
"crs": { "type": "name", "properties": { "name": "urn:ogc:def:crs:OGC:1.3:CRS84" } },
"features": [
{ "type": "Feature", "properties": { "name": "Hoe Promenade", "payment_info": "Free", "accessible": "False", "radar": "Unknown", "women": "True", "men": "True", "baby_change": "Unknown", "Mon": "08:30-19:00", "Tue": "08:30-19:00", "Wed": "08:30-19:00", "Thu": "08:30-19:00", "Fri": "08:30-19:00", "Sat": "08:30-19:00", "Sun": "08:30-19:00", "index_right": 137, "park_offical_id": "PLYMO_9" }, "geometry": { "type": "Point", "coordinates": [ -4.140175242, 50.36543339 ] } },
{ "type": "Feature", "properties": { "name": "West Hoe Park", "payment_info": "Free", "accessible": "True", "radar": "Unknown", "women": "True", "men": "True", "baby_change": "True", "Mon": "09:00-18:00", "Tue": "09:00-18:00", "Wed": "09:00-18:00", "Thu": "09:00-18:00", "Fri": "09:00-18:00", "Sat": "09:00-18:00", "Sun": "09:00-18:00", "index_right": 137, "park_offical_id": "PLYMO_9" }, "geometry": { "type": "Point", "coordinates": [ -4.146019778, 50.364382472 ] } },
{ "type": "Feature", "properties": { "name": "West Hoe", "payment_info": "Free", "accessible": "False", "radar": "True", "women": "True", "men": "True", "baby_change": "Unknown", "Mon": "08:30-19:30", "Tue": "08:30-19:30", "Wed": "08:30-19:30", "Thu": "08:30-19:30", "Fri": "08:30-19:30", "Sat": "08:30-19:30", "Sun": "08:30-19:30", "index_right": 137, "park_offical_id": "PLYMO_9" }, "geometry": { "type": "Point", "coordinates": [ -4.144974669, 50.364283599 ] } }
]
}
