{
"type": "FeatureCollection",
"name": "PLYMO_245_toilets",
"crs": { "type": "name", "properties": { "name": "urn:ogc:def:crs:OGC:1.3:CRS84" } },
"features": [
{ "type": "Feature", "properties": { "name": "West Park Library", "payment_info": "Free", "accessible": "False", "radar": "False", "women": "Unknown", "men": "Unknown", "baby_change": "Unknown", "Mon": "Unknown", "Tue": "Unknown", "Wed": "Unknown", "Thu": "Unknown", "Fri": "Unknown", "Sat": "Unknown", "Sun": "Unknown", "index_right": 48, "park_offical_id": "PLYMO_245" }, "geometry": { "type": "Point", "coordinates": [ -4.166511297, 50.412570338 ] } }
]
}
