{
"type": "FeatureCollection",
"name": "PLYMO_51_toilets",
"crs": { "type": "name", "properties": { "name": "urn:ogc:def:crs:OGC:1.3:CRS84" } },
"features": [
{ "type": "Feature", "properties": { "name": "Devonport Library", "payment_info": "Free", "accessible": "False", "radar": "False", "women": "Unknown", "men": "Unknown", "baby_change": "Unknown", "Mon": "Unknown", "Tue": "Unknown", "Wed": "Unknown", "Thu": "Unknown", "Fri": "Unknown", "Sat": "Unknown", "Sun": "Unknown", "index_right": 95, "park_offical_id": "PLYMO_51" }, "geometry": { "type": "Point", "coordinates": [ -4.174611568, 50.371828221 ] } },
{ "type": "Feature", "properties": { "name": "Mutton Cove", "payment_info": "Free", "accessible": "False", "radar": "Unknown", "women": "True", "men": "True", "baby_change": "Unknown", "Mon": "08:30-18:00", "Tue": "08:30-18:00", "Wed": "08:30-18:00", "Thu": "08:30-18:00", "Fri": "08:30-18:00", "Sat": "08:30-18:00", "Sun": "08:30-18:00", "index_right": 95, "park_offical_id": "PLYMO_51" }, "geometry": { "type": "Point", "coordinates": [ -4.176487898, 50.365856541 ] } }
]
}
