{
"type": "FeatureCollection",
"name": "9b56d97c084a_visibility",
"crs": { "type": "name", "properties": { "name": "urn:ogc:def:crs:OGC:1.3:CRS84" } },
"features": [
{ "type": "Feature", "properties": { "visible_points": 0, "total_points": 48, "visibility_pct": 0.0 }, "geometry": { "type": "Point", "coordinates": [ -4.090645274798749, 51.101702144817388 ] } },
{ "type": "Feature", "properties": { "visible_points": 0, "total_points": 53, "visibility_pct": 0.0 }, "geometry": { "type": "Point", "coordinates": [ -4.090447505434512, 51.101705682697741 ] } },
{ "type": "Feature", "properties": { "visible_points": 0, "total_points": 56, "visibility_pct": 0.0 }, "geometry": { "type": "Point", "coordinates": [ -4.090249736030247, 51.101709220243684 ] } },
{ "type": "Feature", "properties": { "visible_points": 0, "total_points": 55, "visibility_pct": 0.0 }, "geometry": { "type": "Point", "coordinates": [ -4.090051966585954, 51.101712757455161 ] } },
{ "type": "Feature", "properties": { "visible_points": 0, "total_points": 47, "visibility_pct": 0.0 }, "geometry": { "type": "Point", "coordinates": [ -4.090749026177869, 51.101808210730525 ] } },
{ "type": "Feature", "properties": { "visible_points": 0, "total_points": 52, "visibility_pct": 0.0 }, "geometry": { "type": "Point", "coordinates": [ -4.0905512563741, 51.101811748790212 ] } },
{ "type": "Feature", "properties": { "visible_points": 0, "total_points": 56, "visibility_pct": 0.0 }, "geometry": { "type": "Point", "coordinates": [ -4.090353486530301, 51.101815286515453 ] } },
{ "type": "Feature", "properties": { "visible_points": 0, "total_points": 56, "visibility_pct": 0.0 }, "geometry": { "type": "Point", "coordinates": [ -4.090155716646477, 51.101818823906221 ] } },
{ "type": "Feature", "properties": { "visible_points": 8, "total_points": 55, "visibility_pct": 14.545454545454545 }, "geometry": { "type": "Point", "coordinates": [ -4.089957946722627, 51.101822360962579 ] } },
{ "type": "Feature", "properties": { "visible_points": 6, "total_points": 49, "visibility_pct": 12.244897959183673 }, "geometry": { "type": "Point", "coordinates": [ -4.089760176758761, 51.101825897684456 ] } },
{ "type": "Feature", "properties": { "visible_points": 0, "total_points": 50, "visibility_pct": 0.0 }, "geometry": { "type": "Point", "coordinates": [ -4.090655007793242, 51.101917814784713 ] } },
{ "type": "Feature", "properties": { "visible_points": 0, "total_points": 55, "visibility_pct": 0.0 }, "geometry": { "type": "Point", "coordinates": [ -4.090457237509913, 51.101921352689253 ] } },
{ "type": "Feature", "properties": { "visible_points": 16, "total_points": 56, "visibility_pct": 28.571428571428569 }, "geometry": { "type": "Point", "coordinates": [ -4.090259467186549, 51.101924890259355 ] } },
{ "type": "Feature", "properties": { "visible_points": 14, "total_points": 56, "visibility_pct": 25.0 }, "geometry": { "type": "Point", "coordinates": [ -4.090061696823163, 51.101928427495004 ] } },
{ "type": "Feature", "properties": { "visible_points": 12, "total_points": 52, "visibility_pct": 23.076923076923077 }, "geometry": { "type": "Point", "coordinates": [ -4.089863926419757, 51.101931964396215 ] } },
{ "type": "Feature", "properties": { "visible_points": 7, "total_points": 45, "visibility_pct": 15.555555555555555 }, "geometry": { "type": "Point", "coordinates": [ -4.089666155976331, 51.101935500962952 ] } },
{ "type": "Feature", "properties": { "visible_points": 6, "total_points": 38, "visibility_pct": 15.789473684210526 }, "geometry": { "type": "Point", "coordinates": [ -4.089468385492889, 51.101939037195251 ] } },
{ "type": "Feature", "properties": { "visible_points": 10, "total_points": 46, "visibility_pct": 21.739130434782609 }, "geometry": { "type": "Point", "coordinates": [ -4.090758759691947, 51.102023880681244 ] } },
{ "type": "Feature", "properties": { "visible_points": 12, "total_points": 52, "visibility_pct": 23.076923076923077 }, "geometry": { "type": "Point", "coordinates": [ -4.090560988969082, 51.102027418765118 ] } },
{ "type": "Feature", "properties": { "visible_points": 14, "total_points": 56, "visibility_pct": 25.0 }, "geometry": { "type": "Point", "coordinates": [ -4.090363218206178, 51.102030956514533 ] } },
{ "type": "Feature", "properties": { "visible_points": 14, "total_points": 56, "visibility_pct": 25.0 }, "geometry": { "type": "Point", "coordinates": [ -4.090165447403254, 51.102034493929494 ] } },
{ "type": "Feature", "properties": { "visible_points": 13, "total_points": 54, "visibility_pct": 24.074074074074073 }, "geometry": { "type": "Point", "coordinates": [ -4.089967676560305, 51.102038031009982 ] } },
{ "type": "Feature", "properties": { "visible_points": 10, "total_points": 47, "visibility_pct": 21.276595744680851 }, "geometry": { "type": "Point", "coordinates": [ -4.089769905677332, 51.102041567756054 ] } }
]
}
