{
"type": "FeatureCollection",
"name": "SOMER_70_toilets",
"crs": { "type": "name", "properties": { "name": "urn:ogc:def:crs:OGC:1.3:CRS84" } },
"features": [
{ "type": "Feature", "properties": { "name": "Bridgewater Services  M5", "payment_info": "Free", "accessible": "True", "radar": "Unknown", "women": "True", "men": "True", "baby_change": "Unknown", "Mon": "Unknown", "Tue": "Unknown", "Wed": "Unknown", "Thu": "Unknown", "Fri": "Unknown", "Sat": "Unknown", "Sun": "Unknown", "index_right": 422, "park_offical_id": "SOMER_70" }, "geometry": { "type": "Point", "coordinates": [ -2.9962879, 51.1047846 ] } }
]
}
