{
"type": "FeatureCollection",
"name": "SOMER_1027_toilets",
"crs": { "type": "name", "properties": { "name": "urn:ogc:def:crs:OGC:1.3:CRS84" } },
"features": [
{ "type": "Feature", "properties": { "name": "Unknown", "payment_info": "Cost unknown", "accessible": "False", "radar": "Unknown", "women": "Unknown", "men": "Unknown", "baby_change": "Unknown", "Mon": "Unknown", "Tue": "Unknown", "Wed": "Unknown", "Thu": "Unknown", "Fri": "Unknown", "Sat": "Unknown", "Sun": "Unknown", "index_right": 13, "park_offical_id": "SOMER_1027" }, "geometry": { "type": "Point", "coordinates": [ -3.0087301, 51.12756345 ] } }
]
}
