{
"type": "FeatureCollection",
"name": "EASDE_79",
"crs": { "type": "name", "properties": { "name": "urn:ogc:def:crs:OGC:1.3:CRS84" } },
"features": [
{ "type": "Feature", "properties": { "osm_id": 13244316398, "name": null, "amenity": null, "man_made": null, "leisure": "picnic_table", "playground": null, "memorial": null }, "geometry": { "type": "Point", "coordinates": [ -3.4018634, 50.6130416 ] } },
{ "type": "Feature", "properties": { "osm_id": 13244316394, "name": null, "amenity": null, "man_made": null, "leisure": "picnic_table", "playground": null, "memorial": null }, "geometry": { "type": "Point", "coordinates": [ -3.402615, 50.6130758 ] } },
{ "type": "Feature", "properties": { "osm_id": 13244316396, "name": null, "amenity": null, "man_made": null, "leisure": "picnic_table", "playground": null, "memorial": null }, "geometry": { "type": "Point", "coordinates": [ -3.4017019, 50.6131416 ] } },
{ "type": "Feature", "properties": { "osm_id": 13244316395, "name": null, "amenity": null, "man_made": null, "leisure": "picnic_table", "playground": null, "memorial": null }, "geometry": { "type": "Point", "coordinates": [ -3.4024515, 50.6132833 ] } },
{ "type": "Feature", "properties": { "osm_id": 13244316397, "name": null, "amenity": null, "man_made": null, "leisure": "picnic_table", "playground": null, "memorial": null }, "geometry": { "type": "Point", "coordinates": [ -3.4021804, 50.6133022 ] } }
]
}
