{
"type": "FeatureCollection",
"name": "MIDDE_304_toilets",
"crs": { "type": "name", "properties": { "name": "urn:ogc:def:crs:OGC:1.3:CRS84" } },
"features": [
{ "type": "Feature", "properties": { "name": "Station Road", "payment_info": "Free", "accessible": "False", "radar": "True", "women": "True", "men": "True", "baby_change": "False", "Mon": "07:00-19:00", "Tue": "07:00-19:00", "Wed": "07:00-19:00", "Thu": "07:00-19:00", "Fri": "07:00-19:00", "Sat": "07:00-19:00", "Sun": "07:00-19:00", "index_right": 101, "park_offical_id": "MIDDE_304" }, "geometry": { "type": "Point", "coordinates": [ -3.39160502, 50.858967179 ] } }
]
}
