{
"type": "FeatureCollection",
"name": "MIDDE_19_toilets",
"crs": { "type": "name", "properties": { "name": "urn:ogc:def:crs:OGC:1.3:CRS84" } },
"features": [
{ "type": "Feature", "properties": { "name": "Unknown", "payment_info": "Cost unknown", "accessible": "True", "radar": "Unknown", "women": "Unknown", "men": "Unknown", "baby_change": "Unknown", "Mon": "00:00-00:00", "Tue": "00:00-00:00", "Wed": "00:00-00:00", "Thu": "00:00-00:00", "Fri": "00:00-00:00", "Sat": "00:00-00:00", "Sun": "00:00-00:00", "index_right": 43, "park_offical_id": "MIDDE_19" }, "geometry": { "type": "Point", "coordinates": [ -3.330067625, 50.905342235 ] } }
]
}
