{
"type": "FeatureCollection",
"name": "930e6d5502c9_visibility",
"crs": { "type": "name", "properties": { "name": "urn:ogc:def:crs:OGC:1.3:CRS84" } },
"features": [
{ "type": "Feature", "properties": { "visible_points": 0, "total_points": 47, "visibility_pct": 0.0 }, "geometry": { "type": "Point", "coordinates": [ -3.751993934401973, 50.515699686393312 ] } },
{ "type": "Feature", "properties": { "visible_points": 4, "total_points": 48, "visibility_pct": 8.3333333333333321 }, "geometry": { "type": "Point", "coordinates": [ -3.751798582986809, 50.515702626671917 ] } },
{ "type": "Feature", "properties": { "visible_points": 0, "total_points": 48, "visibility_pct": 0.0 }, "geometry": { "type": "Point", "coordinates": [ -3.751603231538993, 50.515705566622721 ] } },
{ "type": "Feature", "properties": { "visible_points": 2, "total_points": 48, "visibility_pct": 4.1666666666666661 }, "geometry": { "type": "Point", "coordinates": [ -3.751900250066545, 50.515809024034226 ] } },
{ "type": "Feature", "properties": { "visible_points": 5, "total_points": 48, "visibility_pct": 10.416666666666668 }, "geometry": { "type": "Point", "coordinates": [ -3.751704898187749, 50.515811964158011 ] } },
{ "type": "Feature", "properties": { "visible_points": 5, "total_points": 48, "visibility_pct": 10.416666666666668 }, "geometry": { "type": "Point", "coordinates": [ -3.751509546276307, 50.515814903954031 ] } },
{ "type": "Feature", "properties": { "visible_points": 2, "total_points": 48, "visibility_pct": 4.1666666666666661 }, "geometry": { "type": "Point", "coordinates": [ -3.751314194332224, 50.515817843422262 ] } },
{ "type": "Feature", "properties": { "visible_points": 5, "total_points": 48, "visibility_pct": 10.416666666666668 }, "geometry": { "type": "Point", "coordinates": [ -3.75180656530013, 50.515918361600122 ] } },
{ "type": "Feature", "properties": { "visible_points": 6, "total_points": 48, "visibility_pct": 12.5 }, "geometry": { "type": "Point", "coordinates": [ -3.751611212957704, 50.515921301569122 ] } },
{ "type": "Feature", "properties": { "visible_points": 5, "total_points": 48, "visibility_pct": 10.416666666666668 }, "geometry": { "type": "Point", "coordinates": [ -3.751415860582629, 50.515924241210335 ] } },
{ "type": "Feature", "properties": { "visible_points": 0, "total_points": 48, "visibility_pct": 0.0 }, "geometry": { "type": "Point", "coordinates": [ -3.751220508199852, 50.515927180488916 ] } },
{ "type": "Feature", "properties": { "visible_points": 3, "total_points": 48, "visibility_pct": 6.25 }, "geometry": { "type": "Point", "coordinates": [ -3.751908232876147, 50.516024758949051 ] } },
{ "type": "Feature", "properties": { "visible_points": 5, "total_points": 48, "visibility_pct": 10.416666666666668 }, "geometry": { "type": "Point", "coordinates": [ -3.751712880102728, 50.516027699091033 ] } },
{ "type": "Feature", "properties": { "visible_points": 3, "total_points": 48, "visibility_pct": 6.25 }, "geometry": { "type": "Point", "coordinates": [ -3.751517527296667, 50.516030638905242 ] } },
{ "type": "Feature", "properties": { "visible_points": 0, "total_points": 48, "visibility_pct": 0.0 }, "geometry": { "type": "Point", "coordinates": [ -3.751322174457957, 50.516033578391642 ] } },
{ "type": "Feature", "properties": { "visible_points": 0, "total_points": 47, "visibility_pct": 0.0 }, "geometry": { "type": "Point", "coordinates": [ -3.752009900915801, 50.5161311562048 ] } },
{ "type": "Feature", "properties": { "visible_points": 3, "total_points": 48, "visibility_pct": 6.25 }, "geometry": { "type": "Point", "coordinates": [ -3.751814547711386, 50.516134096519757 ] } },
{ "type": "Feature", "properties": { "visible_points": 2, "total_points": 48, "visibility_pct": 4.1666666666666661 }, "geometry": { "type": "Point", "coordinates": [ -3.751619194474335, 50.516137036506933 ] } },
{ "type": "Feature", "properties": { "visible_points": 0, "total_points": 47, "visibility_pct": 0.0 }, "geometry": { "type": "Point", "coordinates": [ -3.75142384120463, 50.516139976166329 ] } },
{ "type": "Feature", "properties": { "visible_points": 1, "total_points": 45, "visibility_pct": 2.2222222222222223 }, "geometry": { "type": "Point", "coordinates": [ -3.751720862115639, 50.516243434015472 ] } }
]
}
