{
"type": "FeatureCollection",
"name": "f9fad27c6c81_visibility",
"crs": { "type": "name", "properties": { "name": "urn:ogc:def:crs:OGC:1.3:CRS84" } },
"features": [
{ "type": "Feature", "properties": { "visible_points": 0, "total_points": 55, "visibility_pct": 0.0 }, "geometry": { "type": "Point", "coordinates": [ -1.78993033207219, 51.52435225128005 ] } },
{ "type": "Feature", "properties": { "visible_points": 0, "total_points": 57, "visibility_pct": 0.0 }, "geometry": { "type": "Point", "coordinates": [ -1.789730603796329, 51.524351893080016 ] } },
{ "type": "Feature", "properties": { "visible_points": 0, "total_points": 58, "visibility_pct": 0.0 }, "geometry": { "type": "Point", "coordinates": [ -1.790029696598748, 51.524460327838426 ] } },
{ "type": "Feature", "properties": { "visible_points": 2, "total_points": 61, "visibility_pct": 3.278688524590164 }, "geometry": { "type": "Point", "coordinates": [ -1.78982996783975, 51.524459969804475 ] } },
{ "type": "Feature", "properties": { "visible_points": 0, "total_points": 62, "visibility_pct": 0.0 }, "geometry": { "type": "Point", "coordinates": [ -1.789630239084954, 51.524459611430522 ] } },
{ "type": "Feature", "properties": { "visible_points": 0, "total_points": 62, "visibility_pct": 0.0 }, "geometry": { "type": "Point", "coordinates": [ -1.789430510334383, 51.524459252716518 ] } },
{ "type": "Feature", "properties": { "visible_points": 0, "total_points": 58, "visibility_pct": 0.0 }, "geometry": { "type": "Point", "coordinates": [ -1.789230781588017, 51.524458893662512 ] } },
{ "type": "Feature", "properties": { "visible_points": 1, "total_points": 62, "visibility_pct": 1.6129032258064515 }, "geometry": { "type": "Point", "coordinates": [ -1.789929332362097, 51.524568046445836 ] } },
{ "type": "Feature", "properties": { "visible_points": 2, "total_points": 62, "visibility_pct": 3.225806451612903 }, "geometry": { "type": "Point", "coordinates": [ -1.789729603124165, 51.524567688237958 ] } },
{ "type": "Feature", "properties": { "visible_points": 3, "total_points": 62, "visibility_pct": 4.838709677419355 }, "geometry": { "type": "Point", "coordinates": [ -1.789529873890442, 51.524567329690065 ] } },
{ "type": "Feature", "properties": { "visible_points": 4, "total_points": 62, "visibility_pct": 6.4516129032258061 }, "geometry": { "type": "Point", "coordinates": [ -1.78933014466094, 51.524566970802155 ] } },
{ "type": "Feature", "properties": { "visible_points": 0, "total_points": 61, "visibility_pct": 0.0 }, "geometry": { "type": "Point", "coordinates": [ -1.790028697363381, 51.52467612300412 ] } },
{ "type": "Feature", "properties": { "visible_points": 2, "total_points": 62, "visibility_pct": 3.225806451612903 }, "geometry": { "type": "Point", "coordinates": [ -1.789828967642304, 51.524675764962339 ] } },
{ "type": "Feature", "properties": { "visible_points": 3, "total_points": 62, "visibility_pct": 4.838709677419355 }, "geometry": { "type": "Point", "coordinates": [ -1.789629237925435, 51.524675406580521 ] } },
{ "type": "Feature", "properties": { "visible_points": 4, "total_points": 62, "visibility_pct": 6.4516129032258061 }, "geometry": { "type": "Point", "coordinates": [ -1.789429508212789, 51.5246750478587 ] } },
{ "type": "Feature", "properties": { "visible_points": 1, "total_points": 59, "visibility_pct": 1.6949152542372881 }, "geometry": { "type": "Point", "coordinates": [ -1.789229778504353, 51.52467468879685 ] } },
{ "type": "Feature", "properties": { "visible_points": 0, "total_points": 61, "visibility_pct": 0.0 }, "geometry": { "type": "Point", "coordinates": [ -1.789928332639375, 51.524783841603615 ] } },
{ "type": "Feature", "properties": { "visible_points": 7, "total_points": 62, "visibility_pct": 11.29032258064516 }, "geometry": { "type": "Point", "coordinates": [ -1.789728602439364, 51.524783483387885 ] } },
{ "type": "Feature", "properties": { "visible_points": 6, "total_points": 61, "visibility_pct": 9.8360655737704921 }, "geometry": { "type": "Point", "coordinates": [ -1.789528872243564, 51.524783124832162 ] } },
{ "type": "Feature", "properties": { "visible_points": 1, "total_points": 58, "visibility_pct": 1.7241379310344827 }, "geometry": { "type": "Point", "coordinates": [ -1.789329142051985, 51.524782765936408 ] } },
{ "type": "Feature", "properties": { "visible_points": 9, "total_points": 57, "visibility_pct": 15.789473684210526 }, "geometry": { "type": "Point", "coordinates": [ -1.78982796743223, 51.524891560112174 ] } },
{ "type": "Feature", "properties": { "visible_points": 10, "total_points": 58, "visibility_pct": 17.241379310344829 }, "geometry": { "type": "Point", "coordinates": [ -1.789628236753277, 51.524891201722539 ] } },
{ "type": "Feature", "properties": { "visible_points": 0, "total_points": 56, "visibility_pct": 0.0 }, "geometry": { "type": "Point", "coordinates": [ -1.789428506078543, 51.524890842992868 ] } }
]
}
