{
"type": "FeatureCollection",
"name": "GLOUC_55",
"crs": { "type": "name", "properties": { "name": "urn:ogc:def:crs:OGC:1.3:CRS84" } },
"features": [
{ "type": "Feature", "properties": { "osm_id": 12135755877, "name": null, "amenity": "bench", "man_made": null, "leisure": null, "playground": null, "memorial": null }, "geometry": { "type": "Point", "coordinates": [ -2.2466598, 51.8675951 ] } },
{ "type": "Feature", "properties": { "osm_id": 12135755876, "name": null, "amenity": "bench", "man_made": null, "leisure": null, "playground": null, "memorial": null }, "geometry": { "type": "Point", "coordinates": [ -2.2466498, 51.8676274 ] } }
]
}
