{
"type": "FeatureCollection",
"name": "GLOUC_113",
"crs": { "type": "name", "properties": { "name": "urn:ogc:def:crs:OGC:1.3:CRS84" } },
"features": [
{ "type": "Feature", "properties": { "osm_id": 11012589254, "name": null, "amenity": "bench", "man_made": null, "leisure": null, "playground": null, "memorial": null }, "geometry": { "type": "Point", "coordinates": [ -2.2295975, 51.863458 ] } },
{ "type": "Feature", "properties": { "osm_id": 11012593696, "name": null, "amenity": "bench", "man_made": null, "leisure": null, "playground": null, "memorial": null }, "geometry": { "type": "Point", "coordinates": [ -2.2300322, 51.8636051 ] } },
{ "type": "Feature", "properties": { "osm_id": 11012589760, "name": null, "amenity": "bench", "man_made": null, "leisure": null, "playground": null, "memorial": null }, "geometry": { "type": "Point", "coordinates": [ -2.230124, 51.8636748 ] } }
]
}
