{
"type": "FeatureCollection",
"name": "1720f8de6d9c_visibility",
"crs": { "type": "name", "properties": { "name": "urn:ogc:def:crs:OGC:1.3:CRS84" } },
"features": [
{ "type": "Feature", "properties": { "visible_points": 5, "total_points": 46, "visibility_pct": 10.869565217391305 }, "geometry": { "type": "Point", "coordinates": [ -4.157832993395147, 50.371869595299863 ] } },
{ "type": "Feature", "properties": { "visible_points": 8, "total_points": 46, "visibility_pct": 17.391304347826086 }, "geometry": { "type": "Point", "coordinates": [ -4.157638284754084, 50.371873207655511 ] } },
{ "type": "Feature", "properties": { "visible_points": 10, "total_points": 46, "visibility_pct": 21.739130434782609 }, "geometry": { "type": "Point", "coordinates": [ -4.157443576075531, 50.371876819683912 ] } },
{ "type": "Feature", "properties": { "visible_points": 0, "total_points": 45, "visibility_pct": 0.0 }, "geometry": { "type": "Point", "coordinates": [ -4.157248867359493, 50.371880431385016 ] } },
{ "type": "Feature", "properties": { "visible_points": 7, "total_points": 46, "visibility_pct": 15.217391304347828 }, "geometry": { "type": "Point", "coordinates": [ -4.157935241420204, 50.371975630088336 ] } },
{ "type": "Feature", "properties": { "visible_points": 10, "total_points": 46, "visibility_pct": 21.739130434782609 }, "geometry": { "type": "Point", "coordinates": [ -4.157740532390632, 50.371979242599167 ] } },
{ "type": "Feature", "properties": { "visible_points": 9, "total_points": 46, "visibility_pct": 19.565217391304348 }, "geometry": { "type": "Point", "coordinates": [ -4.157545823323567, 50.371982854782722 ] } },
{ "type": "Feature", "properties": { "visible_points": 10, "total_points": 46, "visibility_pct": 21.739130434782609 }, "geometry": { "type": "Point", "coordinates": [ -4.157351114219009, 50.371986466639015 ] } },
{ "type": "Feature", "properties": { "visible_points": 0, "total_points": 45, "visibility_pct": 0.0 }, "geometry": { "type": "Point", "coordinates": [ -4.15715640507697, 50.371990078168061 ] } },
{ "type": "Feature", "properties": { "visible_points": 0, "total_points": 46, "visibility_pct": 0.0 }, "geometry": { "type": "Point", "coordinates": [ -4.158037489871266, 50.372081664802202 ] } },
{ "type": "Feature", "properties": { "visible_points": 8, "total_points": 46, "visibility_pct": 17.391304347826086 }, "geometry": { "type": "Point", "coordinates": [ -4.157842780453179, 50.372085277468194 ] } },
{ "type": "Feature", "properties": { "visible_points": 10, "total_points": 46, "visibility_pct": 21.739130434782609 }, "geometry": { "type": "Point", "coordinates": [ -4.157648070997594, 50.37208888980696 ] } },
{ "type": "Feature", "properties": { "visible_points": 7, "total_points": 46, "visibility_pct": 15.217391304347828 }, "geometry": { "type": "Point", "coordinates": [ -4.157453361504528, 50.372092501818422 ] } },
{ "type": "Feature", "properties": { "visible_points": 0, "total_points": 46, "visibility_pct": 0.0 }, "geometry": { "type": "Point", "coordinates": [ -4.157258651973962, 50.372096113502643 ] } },
{ "type": "Feature", "properties": { "visible_points": 4, "total_points": 46, "visibility_pct": 8.695652173913043 }, "geometry": { "type": "Point", "coordinates": [ -4.157945028941731, 50.37219131226265 ] } },
{ "type": "Feature", "properties": { "visible_points": 8, "total_points": 46, "visibility_pct": 17.391304347826086 }, "geometry": { "type": "Point", "coordinates": [ -4.15775031909763, 50.372194924756577 ] } },
{ "type": "Feature", "properties": { "visible_points": 11, "total_points": 46, "visibility_pct": 23.913043478260871 }, "geometry": { "type": "Point", "coordinates": [ -4.157555609216041, 50.372198536923243 ] } },
{ "type": "Feature", "properties": { "visible_points": 7, "total_points": 46, "visibility_pct": 15.217391304347828 }, "geometry": { "type": "Point", "coordinates": [ -4.157360899296958, 50.372202148762639 ] } },
{ "type": "Feature", "properties": { "visible_points": 5, "total_points": 46, "visibility_pct": 10.869565217391305 }, "geometry": { "type": "Point", "coordinates": [ -4.157657857353555, 50.37230457195345 ] } },
{ "type": "Feature", "properties": { "visible_points": 5, "total_points": 46, "visibility_pct": 10.869565217391305 }, "geometry": { "type": "Point", "coordinates": [ -4.157463147045955, 50.372308183948029 ] } }
]
}
