{
"type": "FeatureCollection",
"name": "TORBA_43_toilets",
"crs": { "type": "name", "properties": { "name": "urn:ogc:def:crs:OGC:1.3:CRS84" } },
"features": [
{ "type": "Feature", "properties": { "name": "Market Street", "payment_info": "30p", "accessible": "True", "radar": "False", "women": "True", "men": "True", "baby_change": "Unknown", "Mon": "Unknown", "Tue": "Unknown", "Wed": "Unknown", "Thu": "Unknown", "Fri": "Unknown", "Sat": "Unknown", "Sun": "Unknown", "index_right": 51, "park_offical_id": "TORBA_43" }, "geometry": { "type": "Point", "coordinates": [ -3.528842926, 50.466458946 ] } }
]
}
