{
"type": "FeatureCollection",
"name": "TORBA_19_toilets",
"crs": { "type": "name", "properties": { "name": "urn:ogc:def:crs:OGC:1.3:CRS84" } },
"features": [
{ "type": "Feature", "properties": { "name": "Sainsburys", "payment_info": "Cost unknown", "accessible": "True", "radar": "Unknown", "women": "True", "men": "True", "baby_change": "True", "Mon": "Unknown", "Tue": "Unknown", "Wed": "Unknown", "Thu": "Unknown", "Fri": "Unknown", "Sat": "Unknown", "Sun": "Unknown", "index_right": 24, "park_offical_id": "TORBA_19" }, "geometry": { "type": "Point", "coordinates": [ -3.554903269, 50.487913949 ] } }
]
}
