{
"type": "FeatureCollection",
"name": "TORBA_126_toilets",
"crs": { "type": "name", "properties": { "name": "urn:ogc:def:crs:OGC:1.3:CRS84" } },
"features": [
{ "type": "Feature", "properties": { "name": "Palace Avenue", "payment_info": "20p", "accessible": "True", "radar": "False", "women": "True", "men": "True", "baby_change": "Unknown", "Mon": "Unknown", "Tue": "Unknown", "Wed": "Unknown", "Thu": "Unknown", "Fri": "Unknown", "Sat": "Unknown", "Sun": "Unknown", "index_right": 15, "park_offical_id": "TORBA_126" }, "geometry": { "type": "Point", "coordinates": [ -3.5707526, 50.4352518 ] } }
]
}
