{
"type": "FeatureCollection",
"name": "TORBA_23_toilets",
"crs": { "type": "name", "properties": { "name": "urn:ogc:def:crs:OGC:1.3:CRS84" } },
"features": [
{ "type": "Feature", "properties": { "name": "McDonalds", "payment_info": "Free", "accessible": "True", "radar": "Unknown", "women": "True", "men": "True", "baby_change": "Unknown", "Mon": "Unknown", "Tue": "Unknown", "Wed": "Unknown", "Thu": "Unknown", "Fri": "Unknown", "Sat": "Unknown", "Sun": "Unknown", "index_right": 29, "park_offical_id": "TORBA_23" }, "geometry": { "type": "Point", "coordinates": [ -3.588012457, 50.421760089 ] } },
{ "type": "Feature", "properties": { "name": "Sainsburys", "payment_info": "Free", "accessible": "True", "radar": "Unknown", "women": "True", "men": "True", "baby_change": "True", "Mon": "Unknown", "Tue": "Unknown", "Wed": "Unknown", "Thu": "Unknown", "Fri": "Unknown", "Sat": "Unknown", "Sun": "Unknown", "index_right": 29, "park_offical_id": "TORBA_23" }, "geometry": { "type": "Point", "coordinates": [ -3.588709831, 50.421261082 ] } }
]
}
