{
"type": "FeatureCollection",
"name": "GLOUC_113_toilets",
"crs": { "type": "name", "properties": { "name": "urn:ogc:def:crs:OGC:1.3:CRS84" } },
"features": [
{ "type": "Feature", "properties": { "name": "Gloucester Rail Station", "payment_info": "Free", "accessible": "True", "radar": "Unknown", "women": "True", "men": "True", "baby_change": "Unknown", "Mon": "Unknown", "Tue": "Unknown", "Wed": "Unknown", "Thu": "Unknown", "Fri": "Unknown", "Sat": "Unknown", "Sun": "Unknown", "index_right": 5, "park_offical_id": "GLOUC_113" }, "geometry": { "type": "Point", "coordinates": [ -2.238654255, 51.865467939 ] } }
]
}
