{
"type": "FeatureCollection",
"name": "0580dba0dfe2_visibility",
"crs": { "type": "name", "properties": { "name": "urn:ogc:def:crs:OGC:1.3:CRS84" } },
"features": [
{ "type": "Feature", "properties": { "visible_points": 0, "total_points": 40, "visibility_pct": 0.0 }, "geometry": { "type": "Point", "coordinates": [ -2.765145583979866, 50.734758747793869 ] } },
{ "type": "Feature", "properties": { "visible_points": 0, "total_points": 47, "visibility_pct": 0.0 }, "geometry": { "type": "Point", "coordinates": [ -2.764949250350288, 50.734760039379935 ] } },
{ "type": "Feature", "properties": { "visible_points": 0, "total_points": 54, "visibility_pct": 0.0 }, "geometry": { "type": "Point", "coordinates": [ -2.76475291670635, 50.734761330635436 ] } },
{ "type": "Feature", "properties": { "visible_points": 0, "total_points": 60, "visibility_pct": 0.0 }, "geometry": { "type": "Point", "coordinates": [ -2.764556583048067, 50.734762621560421 ] } },
{ "type": "Feature", "properties": { "visible_points": 0, "total_points": 64, "visibility_pct": 0.0 }, "geometry": { "type": "Point", "coordinates": [ -2.764360249375439, 50.734763912154826 ] } },
{ "type": "Feature", "properties": { "visible_points": 0, "total_points": 62, "visibility_pct": 0.0 }, "geometry": { "type": "Point", "coordinates": [ -2.764163915688465, 50.734765202418693 ] } },
{ "type": "Feature", "properties": { "visible_points": 0, "total_points": 56, "visibility_pct": 0.0 }, "geometry": { "type": "Point", "coordinates": [ -2.763967581987155, 50.734766492352016 ] } },
{ "type": "Feature", "properties": { "visible_points": 0, "total_points": 50, "visibility_pct": 0.0 }, "geometry": { "type": "Point", "coordinates": [ -2.763771248271514, 50.734767781954787 ] } },
{ "type": "Feature", "properties": { "visible_points": 0, "total_points": 44, "visibility_pct": 0.0 }, "geometry": { "type": "Point", "coordinates": [ -2.765049176818633, 50.734867296084943 ] } },
{ "type": "Feature", "properties": { "visible_points": 0, "total_points": 51, "visibility_pct": 0.0 }, "geometry": { "type": "Point", "coordinates": [ -2.764852842731469, 50.734868587510988 ] } },
{ "type": "Feature", "properties": { "visible_points": 0, "total_points": 58, "visibility_pct": 0.0 }, "geometry": { "type": "Point", "coordinates": [ -2.764656508629968, 50.734869878606489 ] } },
{ "type": "Feature", "properties": { "visible_points": 0, "total_points": 64, "visibility_pct": 0.0 }, "geometry": { "type": "Point", "coordinates": [ -2.764460174514107, 50.734871169371452 ] } },
{ "type": "Feature", "properties": { "visible_points": 0, "total_points": 64, "visibility_pct": 0.0 }, "geometry": { "type": "Point", "coordinates": [ -2.764263840383906, 50.73487245980585 ] } },
{ "type": "Feature", "properties": { "visible_points": 0, "total_points": 59, "visibility_pct": 0.0 }, "geometry": { "type": "Point", "coordinates": [ -2.764067506239365, 50.734873749909696 ] } },
{ "type": "Feature", "properties": { "visible_points": 0, "total_points": 53, "visibility_pct": 0.0 }, "geometry": { "type": "Point", "coordinates": [ -2.76387117208049, 50.734875039683011 ] } },
{ "type": "Feature", "properties": { "visible_points": 3, "total_points": 47, "visibility_pct": 6.3829787234042552 }, "geometry": { "type": "Point", "coordinates": [ -2.76367483790728, 50.734876329125768 ] } },
{ "type": "Feature", "properties": { "visible_points": 0, "total_points": 64, "visibility_pct": 0.0 }, "geometry": { "type": "Point", "coordinates": [ -2.764363765536909, 50.734979717103052 ] } },
{ "type": "Feature", "properties": { "visible_points": 0, "total_points": 60, "visibility_pct": 0.0 }, "geometry": { "type": "Point", "coordinates": [ -2.764167430949134, 50.734981007377456 ] } },
{ "type": "Feature", "properties": { "visible_points": 0, "total_points": 55, "visibility_pct": 0.0 }, "geometry": { "type": "Point", "coordinates": [ -2.763971096347024, 50.734982297321302 ] } },
{ "type": "Feature", "properties": { "visible_points": 3, "total_points": 49, "visibility_pct": 6.1224489795918364 }, "geometry": { "type": "Point", "coordinates": [ -2.763774761730578, 50.734983586934575 ] } },
{ "type": "Feature", "properties": { "visible_points": 1, "total_points": 61, "visibility_pct": 1.639344262295082 }, "geometry": { "type": "Point", "coordinates": [ -2.764267356116466, 50.735088264755241 ] } },
{ "type": "Feature", "properties": { "visible_points": 1, "total_points": 56, "visibility_pct": 1.7857142857142856 }, "geometry": { "type": "Point", "coordinates": [ -2.764071021071121, 50.73508955486961 ] } },
{ "type": "Feature", "properties": { "visible_points": 5, "total_points": 50, "visibility_pct": 10.0 }, "geometry": { "type": "Point", "coordinates": [ -2.763874686011433, 50.735090844653449 ] } }
]
}
