{
"type": "FeatureCollection",
"name": "79e3949effd9_visibility",
"crs": { "type": "name", "properties": { "name": "urn:ogc:def:crs:OGC:1.3:CRS84" } },
"features": [
{ "type": "Feature", "properties": { "visible_points": 8, "total_points": 44, "visibility_pct": 18.181818181818183 }, "geometry": { "type": "Point", "coordinates": [ -2.763993557484002, 50.732779905581403 ] } },
{ "type": "Feature", "properties": { "visible_points": 6, "total_points": 45, "visibility_pct": 13.333333333333334 }, "geometry": { "type": "Point", "coordinates": [ -2.76379723210661, 50.732781195198726 ] } },
{ "type": "Feature", "properties": { "visible_points": 2, "total_points": 46, "visibility_pct": 4.3478260869565215 }, "geometry": { "type": "Point", "coordinates": [ -2.763600906714785, 50.732782484485497 ] } },
{ "type": "Feature", "properties": { "visible_points": 13, "total_points": 48, "visibility_pct": 27.083333333333332 }, "geometry": { "type": "Point", "coordinates": [ -2.76409347756718, 50.73288716317515 ] } },
{ "type": "Feature", "properties": { "visible_points": 6, "total_points": 50, "visibility_pct": 12.0 }, "geometry": { "type": "Point", "coordinates": [ -2.763897151742439, 50.732888452961753 ] } },
{ "type": "Feature", "properties": { "visible_points": 0, "total_points": 51, "visibility_pct": 0.0 }, "geometry": { "type": "Point", "coordinates": [ -2.763700825903269, 50.732889742417775 ] } },
{ "type": "Feature", "properties": { "visible_points": 2, "total_points": 50, "visibility_pct": 4.0 }, "geometry": { "type": "Point", "coordinates": [ -2.763504500049673, 50.732891031543247 ] } },
{ "type": "Feature", "properties": { "visible_points": 11, "total_points": 55, "visibility_pct": 20.0 }, "geometry": { "type": "Point", "coordinates": [ -2.76380074555352, 50.732997000261413 ] } },
{ "type": "Feature", "properties": { "visible_points": 3, "total_points": 55, "visibility_pct": 5.4545454545454541 }, "geometry": { "type": "Point", "coordinates": [ -2.76360441925257, 50.732998289556143 ] } },
{ "type": "Feature", "properties": { "visible_points": 0, "total_points": 54, "visibility_pct": 0.0 }, "geometry": { "type": "Point", "coordinates": [ -2.763408092937199, 50.732999578520314 ] } },
{ "type": "Feature", "properties": { "visible_points": 17, "total_points": 55, "visibility_pct": 30.909090909090907 }, "geometry": { "type": "Point", "coordinates": [ -2.763704338917242, 50.733105547480385 ] } },
{ "type": "Feature", "properties": { "visible_points": 1, "total_points": 55, "visibility_pct": 1.8181818181818181 }, "geometry": { "type": "Point", "coordinates": [ -2.763508012154509, 50.733106836613814 ] } },
{ "type": "Feature", "properties": { "visible_points": 9, "total_points": 55, "visibility_pct": 16.363636363636363 }, "geometry": { "type": "Point", "coordinates": [ -2.76380425904368, 50.733212805315979 ] } },
{ "type": "Feature", "properties": { "visible_points": 2, "total_points": 55, "visibility_pct": 3.6363636363636362 }, "geometry": { "type": "Point", "coordinates": [ -2.763607931833592, 50.733214094618653 ] } },
{ "type": "Feature", "properties": { "visible_points": 1, "total_points": 52, "visibility_pct": 1.9230769230769231 }, "geometry": { "type": "Point", "coordinates": [ -2.763411604609082, 50.733215383590796 ] } },
{ "type": "Feature", "properties": { "visible_points": 1, "total_points": 51, "visibility_pct": 1.9607843137254901 }, "geometry": { "type": "Point", "coordinates": [ -2.763707851974452, 50.733321352534873 ] } },
{ "type": "Feature", "properties": { "visible_points": 0, "total_points": 49, "visibility_pct": 0.0 }, "geometry": { "type": "Point", "coordinates": [ -2.763511524302579, 50.73332264167626 ] } },
{ "type": "Feature", "properties": { "visible_points": 10, "total_points": 46, "visibility_pct": 21.739130434782609 }, "geometry": { "type": "Point", "coordinates": [ -2.763807772577087, 50.733428610362431 ] } },
{ "type": "Feature", "properties": { "visible_points": 1, "total_points": 45, "visibility_pct": 2.2222222222222223 }, "geometry": { "type": "Point", "coordinates": [ -2.763611444457854, 50.733429899673084 ] } },
{ "type": "Feature", "properties": { "visible_points": 0, "total_points": 40, "visibility_pct": 0.0 }, "geometry": { "type": "Point", "coordinates": [ -2.763711365074906, 50.733537157581253 ] } }
]
}
