{
"type": "FeatureCollection",
"name": "SOUGL_171",
"crs": { "type": "name", "properties": { "name": "urn:ogc:def:crs:OGC:1.3:CRS84" } },
"features": [
{ "type": "Feature", "properties": { "osm_id": 7899801198, "name": null, "amenity": "bench", "man_made": null, "leisure": null, "playground": null, "memorial": null }, "geometry": { "type": "Point", "coordinates": [ -2.4135553, 51.5426249 ] } },
{ "type": "Feature", "properties": { "osm_id": 7899801199, "name": null, "amenity": "bench", "man_made": null, "leisure": null, "playground": null, "memorial": null }, "geometry": { "type": "Point", "coordinates": [ -2.4136204, 51.5427337 ] } }
]
}
