{
"type": "FeatureCollection",
"name": "SOUGL_378",
"crs": { "type": "name", "properties": { "name": "urn:ogc:def:crs:OGC:1.3:CRS84" } },
"features": [
{ "type": "Feature", "properties": { "osm_id": 12078128733, "name": null, "amenity": "bench", "man_made": null, "leisure": null, "playground": null, "memorial": null }, "geometry": { "type": "Point", "coordinates": [ -2.4744569, 51.4594061 ] } },
{ "type": "Feature", "properties": { "osm_id": 12078142253, "name": null, "amenity": "bench", "man_made": null, "leisure": null, "playground": null, "memorial": null }, "geometry": { "type": "Point", "coordinates": [ -2.4745671, 51.4594154 ] } },
{ "type": "Feature", "properties": { "osm_id": 12078142254, "name": null, "amenity": "bench", "man_made": null, "leisure": null, "playground": null, "memorial": null }, "geometry": { "type": "Point", "coordinates": [ -2.4744355, 51.4594403 ] } }
]
}
