{
"type": "FeatureCollection",
"name": "3c2f1b76c575_visibility",
"crs": { "type": "name", "properties": { "name": "urn:ogc:def:crs:OGC:1.3:CRS84" } },
"features": [
{ "type": "Feature", "properties": { "visible_points": 10, "total_points": 45, "visibility_pct": 22.222222222222221 }, "geometry": { "type": "Point", "coordinates": [ -2.183622481345906, 51.843197917901293 ] } },
{ "type": "Feature", "properties": { "visible_points": 11, "total_points": 44, "visibility_pct": 25.0 }, "geometry": { "type": "Point", "coordinates": [ -2.18342134399844, 51.843198234275825 ] } },
{ "type": "Feature", "properties": { "visible_points": 6, "total_points": 48, "visibility_pct": 12.5 }, "geometry": { "type": "Point", "coordinates": [ -2.183924627591212, 51.843305333924789 ] } },
{ "type": "Feature", "properties": { "visible_points": 11, "total_points": 49, "visibility_pct": 22.448979591836736 }, "geometry": { "type": "Point", "coordinates": [ -2.183723489772909, 51.843305650811956 ] } },
{ "type": "Feature", "properties": { "visible_points": 13, "total_points": 49, "visibility_pct": 26.530612244897959 }, "geometry": { "type": "Point", "coordinates": [ -2.183522351950979, 51.843305967355157 ] } },
{ "type": "Feature", "properties": { "visible_points": 8, "total_points": 48, "visibility_pct": 16.666666666666664 }, "geometry": { "type": "Point", "coordinates": [ -2.183321214125432, 51.843306283554398 ] } },
{ "type": "Feature", "properties": { "visible_points": 6, "total_points": 49, "visibility_pct": 12.244897959183673 }, "geometry": { "type": "Point", "coordinates": [ -2.184025636970753, 51.84341306658213 ] } },
{ "type": "Feature", "properties": { "visible_points": 12, "total_points": 49, "visibility_pct": 24.489795918367346 }, "geometry": { "type": "Point", "coordinates": [ -2.183824498677989, 51.843413383637952 ] } },
{ "type": "Feature", "properties": { "visible_points": 12, "total_points": 49, "visibility_pct": 24.489795918367346 }, "geometry": { "type": "Point", "coordinates": [ -2.183623360381595, 51.843413700349835 ] } },
{ "type": "Feature", "properties": { "visible_points": 5, "total_points": 49, "visibility_pct": 10.204081632653061 }, "geometry": { "type": "Point", "coordinates": [ -2.18342222208158, 51.843414016717766 ] } },
{ "type": "Feature", "properties": { "visible_points": 8, "total_points": 49, "visibility_pct": 16.326530612244898 }, "geometry": { "type": "Point", "coordinates": [ -2.183925508061153, 51.8435211163793 ] } },
{ "type": "Feature", "properties": { "visible_points": 15, "total_points": 49, "visibility_pct": 30.612244897959183 }, "geometry": { "type": "Point", "coordinates": [ -2.18372436929029, 51.843521433259852 ] } },
{ "type": "Feature", "properties": { "visible_points": 7, "total_points": 49, "visibility_pct": 14.285714285714285 }, "geometry": { "type": "Point", "coordinates": [ -2.183523230515805, 51.843521749796466 ] } },
{ "type": "Feature", "properties": { "visible_points": 12, "total_points": 48, "visibility_pct": 25.0 }, "geometry": { "type": "Point", "coordinates": [ -2.18382537867707, 51.843629166085236 ] } },
{ "type": "Feature", "properties": { "visible_points": 13, "total_points": 49, "visibility_pct": 26.530612244897959 }, "geometry": { "type": "Point", "coordinates": [ -2.183624239428116, 51.843629482790504 ] } },
{ "type": "Feature", "properties": { "visible_points": 7, "total_points": 44, "visibility_pct": 15.909090909090908 }, "geometry": { "type": "Point", "coordinates": [ -2.183926388541942, 51.843736898825952 ] } },
{ "type": "Feature", "properties": { "visible_points": 16, "total_points": 45, "visibility_pct": 35.555555555555557 }, "geometry": { "type": "Point", "coordinates": [ -2.183725248818512, 51.843737215699903 ] } },
{ "type": "Feature", "properties": { "visible_points": 9, "total_points": 46, "visibility_pct": 19.565217391304348 }, "geometry": { "type": "Point", "coordinates": [ -2.183524109091458, 51.843737532229902 ] } },
{ "type": "Feature", "properties": { "visible_points": 8, "total_points": 40, "visibility_pct": 20.0 }, "geometry": { "type": "Point", "coordinates": [ -2.183826258686997, 51.843844948524634 ] } },
{ "type": "Feature", "properties": { "visible_points": 10, "total_points": 41, "visibility_pct": 24.390243902439025 }, "geometry": { "type": "Point", "coordinates": [ -2.183625118485466, 51.843845265223315 ] } }
]
}
