{
"type": "FeatureCollection",
"name": "COTSW_282",
"crs": { "type": "name", "properties": { "name": "urn:ogc:def:crs:OGC:1.3:CRS84" } },
"features": [
{ "type": "Feature", "properties": { "osm_id": 9763004906, "name": null, "amenity": "bench", "man_made": null, "leisure": null, "playground": null, "memorial": null }, "geometry": { "type": "Point", "coordinates": [ -2.0938538, 51.8916213 ] } },
{ "type": "Feature", "properties": { "osm_id": 9763008786, "name": null, "amenity": "bench", "man_made": null, "leisure": null, "playground": null, "memorial": null }, "geometry": { "type": "Point", "coordinates": [ -2.0946004, 51.8921154 ] } },
{ "type": "Feature", "properties": { "osm_id": 9763018033, "name": null, "amenity": "bench", "man_made": null, "leisure": null, "playground": null, "memorial": null }, "geometry": { "type": "Point", "coordinates": [ -2.0938485, 51.8921647 ] } }
]
}
