{
"type": "FeatureCollection",
"name": "COTSW_242",
"crs": { "type": "name", "properties": { "name": "urn:ogc:def:crs:OGC:1.3:CRS84" } },
"features": [
{ "type": "Feature", "properties": { "osm_id": 11778497241, "name": null, "amenity": "bench", "man_made": null, "leisure": null, "playground": null, "memorial": null }, "geometry": { "type": "Point", "coordinates": [ -2.1169538, 52.0332951 ] } },
{ "type": "Feature", "properties": { "osm_id": 11778497242, "name": null, "amenity": "bench", "man_made": null, "leisure": null, "playground": null, "memorial": null }, "geometry": { "type": "Point", "coordinates": [ -2.1168185, 52.0332959 ] } },
{ "type": "Feature", "properties": { "osm_id": 11778497249, "name": null, "amenity": "bench", "man_made": null, "leisure": null, "playground": null, "memorial": null }, "geometry": { "type": "Point", "coordinates": [ -2.1169049, 52.033331 ] } },
{ "type": "Feature", "properties": { "osm_id": 11778497250, "name": null, "amenity": "bench", "man_made": null, "leisure": null, "playground": null, "memorial": null }, "geometry": { "type": "Point", "coordinates": [ -2.1166249, 52.0333578 ] } },
{ "type": "Feature", "properties": { "osm_id": 11778497243, "name": null, "amenity": "bench", "man_made": null, "leisure": null, "playground": null, "memorial": null }, "geometry": { "type": "Point", "coordinates": [ -2.1165722, 52.0334594 ] } },
{ "type": "Feature", "properties": { "osm_id": 11778497246, "name": null, "amenity": null, "man_made": null, "leisure": "picnic_table", "playground": null, "memorial": null }, "geometry": { "type": "Point", "coordinates": [ -2.1168522, 52.0334728 ] } },
{ "type": "Feature", "properties": { "osm_id": 11778497239, "name": null, "amenity": "bench", "man_made": null, "leisure": null, "playground": null, "memorial": null }, "geometry": { "type": "Point", "coordinates": [ -2.1166696, 52.0335379 ] } }
]
}
