{
"type": "FeatureCollection",
"name": "COTSW_514",
"crs": { "type": "name", "properties": { "name": "urn:ogc:def:crs:OGC:1.3:CRS84" } },
"features": [
{ "type": "Feature", "properties": { "osm_id": 1938324715, "name": null, "amenity": "bench", "man_made": null, "leisure": null, "playground": null, "memorial": null }, "geometry": { "type": "Point", "coordinates": [ -2.2168103, 52.064635 ] } },
{ "type": "Feature", "properties": { "osm_id": 1938324718, "name": null, "amenity": "bench", "man_made": null, "leisure": null, "playground": null, "memorial": null }, "geometry": { "type": "Point", "coordinates": [ -2.2168653, 52.0646746 ] } },
{ "type": "Feature", "properties": { "osm_id": 1938324726, "name": null, "amenity": "bench", "man_made": null, "leisure": null, "playground": null, "memorial": null }, "geometry": { "type": "Point", "coordinates": [ -2.216872, 52.0647075 ] } },
{ "type": "Feature", "properties": { "osm_id": 1938324723, "name": null, "amenity": "bench", "man_made": null, "leisure": null, "playground": null, "memorial": null }, "geometry": { "type": "Point", "coordinates": [ -2.2170074, 52.0647587 ] } },
{ "type": "Feature", "properties": { "osm_id": 1938324696, "name": null, "amenity": "bench", "man_made": null, "leisure": null, "playground": null, "memorial": null }, "geometry": { "type": "Point", "coordinates": [ -2.2170155, 52.0647776 ] } },
{ "type": "Feature", "properties": { "osm_id": 1934473504, "name": null, "amenity": "bench", "man_made": null, "leisure": null, "playground": null, "memorial": null }, "geometry": { "type": "Point", "coordinates": [ -2.2168814, 52.0647793 ] } },
{ "type": "Feature", "properties": { "osm_id": 1938324699, "name": null, "amenity": "bench", "man_made": null, "leisure": null, "playground": null, "memorial": null }, "geometry": { "type": "Point", "coordinates": [ -2.2170182, 52.0647991 ] } }
]
}
