{
"type": "FeatureCollection",
"name": "COTSW_149",
"crs": { "type": "name", "properties": { "name": "urn:ogc:def:crs:OGC:1.3:CRS84" } },
"features": [
{ "type": "Feature", "properties": { "osm_id": 12023095195, "name": null, "amenity": "bench", "man_made": null, "leisure": null, "playground": null, "memorial": null }, "geometry": { "type": "Point", "coordinates": [ -1.9753784, 51.7093286 ] } },
{ "type": "Feature", "properties": { "osm_id": 12023095196, "name": null, "amenity": "bench", "man_made": null, "leisure": null, "playground": null, "memorial": null }, "geometry": { "type": "Point", "coordinates": [ -1.9756785, 51.7093663 ] } },
{ "type": "Feature", "properties": { "osm_id": 12023095197, "name": null, "amenity": "bench", "man_made": null, "leisure": null, "playground": null, "memorial": null }, "geometry": { "type": "Point", "coordinates": [ -1.9759604, 51.7094022 ] } },
{ "type": "Feature", "properties": { "osm_id": 12023095176, "name": null, "amenity": "bench", "man_made": null, "leisure": null, "playground": null, "memorial": null }, "geometry": { "type": "Point", "coordinates": [ -1.9751205, 51.7103195 ] } },
{ "type": "Feature", "properties": { "osm_id": 11202260420, "name": null, "amenity": "bench", "man_made": null, "leisure": null, "playground": null, "memorial": null }, "geometry": { "type": "Point", "coordinates": [ -1.9711093, 51.7103668 ] } },
{ "type": "Feature", "properties": { "osm_id": 12023095175, "name": null, "amenity": "bench", "man_made": null, "leisure": null, "playground": null, "memorial": null }, "geometry": { "type": "Point", "coordinates": [ -1.9754582, 51.7103873 ] } },
{ "type": "Feature", "properties": { "osm_id": 11537311160, "name": null, "amenity": "bench", "man_made": null, "leisure": null, "playground": null, "memorial": null }, "geometry": { "type": "Point", "coordinates": [ -1.9711889, 51.7104187 ] } }
]
}
