{
"type": "FeatureCollection",
"name": "SWIND_69",
"crs": { "type": "name", "properties": { "name": "urn:ogc:def:crs:OGC:1.3:CRS84" } },
"features": [
{ "type": "Feature", "properties": { "osm_id": 11804478375, "name": null, "amenity": "bench", "man_made": null, "leisure": null, "playground": null, "memorial": null }, "geometry": { "type": "Point", "coordinates": [ -1.8295557, 51.5472965 ] } },
{ "type": "Feature", "properties": { "osm_id": 11804478376, "name": null, "amenity": "bench", "man_made": null, "leisure": null, "playground": null, "memorial": null }, "geometry": { "type": "Point", "coordinates": [ -1.8289029, 51.5477502 ] } },
{ "type": "Feature", "properties": { "osm_id": 11804478377, "name": null, "amenity": "bench", "man_made": null, "leisure": null, "playground": null, "memorial": null }, "geometry": { "type": "Point", "coordinates": [ -1.8289541, 51.547959 ] } },
{ "type": "Feature", "properties": { "osm_id": 13755717207, "name": null, "amenity": "bench", "man_made": null, "leisure": null, "playground": null, "memorial": null }, "geometry": { "type": "Point", "coordinates": [ -1.8279556, 51.5487687 ] } }
]
}
