{
"type": "FeatureCollection",
"name": "23173d430d41_visibility",
"crs": { "type": "name", "properties": { "name": "urn:ogc:def:crs:OGC:1.3:CRS84" } },
"features": [
{ "type": "Feature", "properties": { "visible_points": 8, "total_points": 49, "visibility_pct": 16.326530612244898 }, "geometry": { "type": "Point", "coordinates": [ -2.333722290328069, 51.70088079305885 ] } },
{ "type": "Feature", "properties": { "visible_points": 3, "total_points": 50, "visibility_pct": 6.0 }, "geometry": { "type": "Point", "coordinates": [ -2.333521790917388, 51.700881362245326 ] } },
{ "type": "Feature", "properties": { "visible_points": 10, "total_points": 53, "visibility_pct": 18.867924528301888 }, "geometry": { "type": "Point", "coordinates": [ -2.333823335541297, 51.700988403250157 ] } },
{ "type": "Feature", "properties": { "visible_points": 7, "total_points": 53, "visibility_pct": 13.20754716981132 }, "geometry": { "type": "Point", "coordinates": [ -2.33362283565351, 51.70098897260943 ] } },
{ "type": "Feature", "properties": { "visible_points": 6, "total_points": 53, "visibility_pct": 11.320754716981133 }, "geometry": { "type": "Point", "coordinates": [ -2.333422335759092, 51.700989541626527 ] } },
{ "type": "Feature", "properties": { "visible_points": 7, "total_points": 52, "visibility_pct": 13.461538461538462 }, "geometry": { "type": "Point", "coordinates": [ -2.33322183585805, 51.700990110301454 ] } },
{ "type": "Feature", "properties": { "visible_points": 12, "total_points": 53, "visibility_pct": 22.641509433962266 }, "geometry": { "type": "Point", "coordinates": [ -2.333723880873363, 51.701096582884304 ] } },
{ "type": "Feature", "properties": { "visible_points": 10, "total_points": 53, "visibility_pct": 18.867924528301888 }, "geometry": { "type": "Point", "coordinates": [ -2.333523380501835, 51.701097152074198 ] } },
{ "type": "Feature", "properties": { "visible_points": 8, "total_points": 53, "visibility_pct": 15.09433962264151 }, "geometry": { "type": "Point", "coordinates": [ -2.333322880123671, 51.701097720921908 ] } },
{ "type": "Feature", "properties": { "visible_points": 0, "total_points": 53, "visibility_pct": 0.0 }, "geometry": { "type": "Point", "coordinates": [ -2.333122379738889, 51.701098289427435 ] } },
{ "type": "Feature", "properties": { "visible_points": 12, "total_points": 53, "visibility_pct": 22.641509433962266 }, "geometry": { "type": "Point", "coordinates": [ -2.333824926576949, 51.701204193069934 ] } },
{ "type": "Feature", "properties": { "visible_points": 7, "total_points": 53, "visibility_pct": 13.20754716981132 }, "geometry": { "type": "Point", "coordinates": [ -2.333624425728307, 51.70120476243261 ] } },
{ "type": "Feature", "properties": { "visible_points": 3, "total_points": 53, "visibility_pct": 5.6603773584905666 }, "geometry": { "type": "Point", "coordinates": [ -2.333423924873033, 51.701205331453124 ] } },
{ "type": "Feature", "properties": { "visible_points": 1, "total_points": 53, "visibility_pct": 1.8867924528301887 }, "geometry": { "type": "Point", "coordinates": [ -2.333223424011126, 51.701205900131455 ] } },
{ "type": "Feature", "properties": { "visible_points": 5, "total_points": 53, "visibility_pct": 9.433962264150944 }, "geometry": { "type": "Point", "coordinates": [ -2.333925972764273, 51.701311803166298 ] } },
{ "type": "Feature", "properties": { "visible_points": 1, "total_points": 53, "visibility_pct": 1.8867924528301887 }, "geometry": { "type": "Point", "coordinates": [ -2.333725471438516, 51.7013123727018 ] } },
{ "type": "Feature", "properties": { "visible_points": 7, "total_points": 53, "visibility_pct": 13.20754716981132 }, "geometry": { "type": "Point", "coordinates": [ -2.333524970106124, 51.701312941895111 ] } },
{ "type": "Feature", "properties": { "visible_points": 4, "total_points": 52, "visibility_pct": 7.6923076923076925 }, "geometry": { "type": "Point", "coordinates": [ -2.333324468767097, 51.701313510746225 ] } },
{ "type": "Feature", "properties": { "visible_points": 6, "total_points": 50, "visibility_pct": 12.0 }, "geometry": { "type": "Point", "coordinates": [ -2.333626015822953, 51.701420552247846 ] } },
{ "type": "Feature", "properties": { "visible_points": 5, "total_points": 49, "visibility_pct": 10.204081632653061 }, "geometry": { "type": "Point", "coordinates": [ -2.333425514006803, 51.701421121271743 ] } }
]
}
