{
"type": "FeatureCollection",
"name": "TORRI_12_toilets",
"crs": { "type": "name", "properties": { "name": "urn:ogc:def:crs:OGC:1.3:CRS84" } },
"features": [
{ "type": "Feature", "properties": { "name": "The Quay", "payment_info": "Free", "accessible": "False", "radar": "True", "women": "True", "men": "True", "baby_change": "False", "Mon": "00:00-00:00", "Tue": "00:00-00:00", "Wed": "00:00-00:00", "Thu": "00:00-00:00", "Fri": "00:00-00:00", "Sat": "00:00-00:00", "Sun": "00:00-00:00", "index_right": 7, "park_offical_id": "TORRI_12" }, "geometry": { "type": "Point", "coordinates": [ -4.204185605, 51.018744233 ] } },
{ "type": "Feature", "properties": { "name": "Town Hall", "payment_info": "Free", "accessible": "False", "radar": "Unknown", "women": "True", "men": "True", "baby_change": "Unknown", "Mon": "Unknown", "Tue": "Unknown", "Wed": "Unknown", "Thu": "Unknown", "Fri": "Unknown", "Sat": "Unknown", "Sun": "Unknown", "index_right": 7, "park_offical_id": "TORRI_12" }, "geometry": { "type": "Point", "coordinates": [ -4.2050235, 51.0166186 ] } },
{ "type": "Feature", "properties": { "name": "Pannier Market", "payment_info": "Free", "accessible": "False", "radar": "Unknown", "women": "True", "men": "True", "baby_change": "Unknown", "Mon": "08:00-18:00", "Tue": "08:00-18:00", "Wed": "08:00-18:00", "Thu": "08:00-18:00", "Fri": "08:00-18:00", "Sat": "08:00-18:00", "Sun": "08:00-18:00", "index_right": 7, "park_offical_id": "TORRI_12" }, "geometry": { "type": "Point", "coordinates": [ -4.207482, 51.016663 ] } }
]
}
