{
"type": "FeatureCollection",
"name": "TORRI_34_toilets",
"crs": { "type": "name", "properties": { "name": "urn:ogc:def:crs:OGC:1.3:CRS84" } },
"features": [
{ "type": "Feature", "properties": { "name": "Churchfields Car Park", "payment_info": "Free", "accessible": "False", "radar": "True", "women": "True", "men": "True", "baby_change": "True", "Mon": "08:00-21:00", "Tue": "08:00-21:00", "Wed": "08:00-21:00", "Thu": "08:00-21:00", "Fri": "08:00-21:00", "Sat": "08:00-21:00", "Sun": "08:00-21:00", "index_right": 27, "park_offical_id": "TORRI_34" }, "geometry": { "type": "Point", "coordinates": [ -4.1919086, 51.0549439 ] } }
]
}
