{
"type": "FeatureCollection",
"name": "TORRI_40_toilets",
"crs": { "type": "name", "properties": { "name": "urn:ogc:def:crs:OGC:1.3:CRS84" } },
"features": [
{ "type": "Feature", "properties": { "name": "Northam Community Centre", "payment_info": "Free", "accessible": "True", "radar": "Unknown", "women": "True", "men": "True", "baby_change": "False", "Mon": "Unknown", "Tue": "Unknown", "Wed": "Unknown", "Thu": "Unknown", "Fri": "Unknown", "Sat": "Unknown", "Sun": "Unknown", "index_right": 32, "park_offical_id": "TORRI_40" }, "geometry": { "type": "Point", "coordinates": [ -4.213785231, 51.039478037 ] } }
]
}
