{
"type": "FeatureCollection",
"name": "NORSO_19_toilets",
"crs": { "type": "name", "properties": { "name": "urn:ogc:def:crs:OGC:1.3:CRS84" } },
"features": [
{ "type": "Feature", "properties": { "name": "Unknown", "payment_info": "Free", "accessible": "False", "radar": "Unknown", "women": "Unknown", "men": "Unknown", "baby_change": "Unknown", "Mon": "Unknown", "Tue": "Unknown", "Wed": "Unknown", "Thu": "Unknown", "Fri": "Unknown", "Sat": "Unknown", "Sun": "Unknown", "index_right": 38, "park_offical_id": "NORSO_19" }, "geometry": { "type": "Point", "coordinates": [ -2.96520622, 51.35067404 ] } },
{ "type": "Feature", "properties": { "name": "Grove Park", "payment_info": "020", "accessible": "False", "radar": "Unknown", "women": "True", "men": "True", "baby_change": "Unknown", "Mon": "Unknown", "Tue": "Unknown", "Wed": "Unknown", "Thu": "Unknown", "Fri": "Unknown", "Sat": "Unknown", "Sun": "Unknown", "index_right": 38, "park_offical_id": "NORSO_19" }, "geometry": { "type": "Point", "coordinates": [ -2.97941686, 51.35148196 ] } }
]
}
