{
"type": "FeatureCollection",
"name": "EXETE_169",
"crs": { "type": "name", "properties": { "name": "urn:ogc:def:crs:OGC:1.3:CRS84" } },
"features": [
{ "type": "Feature", "properties": { "osm_id": 12966935796, "name": null, "amenity": "bench", "man_made": null, "leisure": null, "playground": null, "memorial": null }, "geometry": { "type": "Point", "coordinates": [ -3.522172, 50.7080854 ] } },
{ "type": "Feature", "properties": { "osm_id": 10315686409, "name": null, "amenity": "bench", "man_made": null, "leisure": null, "playground": null, "memorial": null }, "geometry": { "type": "Point", "coordinates": [ -3.5202512, 50.7098586 ] } },
{ "type": "Feature", "properties": { "osm_id": 10315686013, "name": null, "amenity": "bench", "man_made": null, "leisure": null, "playground": null, "memorial": null }, "geometry": { "type": "Point", "coordinates": [ -3.5222349, 50.7101061 ] } },
{ "type": "Feature", "properties": { "osm_id": 10315686211, "name": null, "amenity": "bench", "man_made": null, "leisure": null, "playground": null, "memorial": null }, "geometry": { "type": "Point", "coordinates": [ -3.5183352, 50.7066553 ] } },
{ "type": "Feature", "properties": { "osm_id": 10315685019, "name": null, "amenity": "bench", "man_made": null, "leisure": null, "playground": null, "memorial": null }, "geometry": { "type": "Point", "coordinates": [ -3.5262715, 50.713568 ] } },
{ "type": "Feature", "properties": { "osm_id": 10315686309, "name": null, "amenity": "bench", "man_made": null, "leisure": null, "playground": null, "memorial": null }, "geometry": { "type": "Point", "coordinates": [ -3.5262892, 50.7135957 ] } },
{ "type": "Feature", "properties": { "osm_id": 10315685018, "name": null, "amenity": "bench", "man_made": null, "leisure": null, "playground": null, "memorial": null }, "geometry": { "type": "Point", "coordinates": [ -3.5266244, 50.7141355 ] } },
{ "type": "Feature", "properties": { "osm_id": 10315686209, "name": null, "amenity": "bench", "man_made": null, "leisure": null, "playground": null, "memorial": null }, "geometry": { "type": "Point", "coordinates": [ -3.5266348, 50.7141593 ] } },
{ "type": "Feature", "properties": { "osm_id": 10315685017, "name": null, "amenity": "bench", "man_made": null, "leisure": null, "playground": null, "memorial": null }, "geometry": { "type": "Point", "coordinates": [ -3.5267968, 50.7149586 ] } }
]
}
