{
"type": "FeatureCollection",
"name": "023df4091353_visibility",
"crs": { "type": "name", "properties": { "name": "urn:ogc:def:crs:OGC:1.3:CRS84" } },
"features": [
{ "type": "Feature", "properties": { "visible_points": 3, "total_points": 42, "visibility_pct": 7.1428571428571423 }, "geometry": { "type": "Point", "coordinates": [ -3.238116221789576, 51.124448812311414 ] } },
{ "type": "Feature", "properties": { "visible_points": 2, "total_points": 45, "visibility_pct": 4.4444444444444446 }, "geometry": { "type": "Point", "coordinates": [ -3.237918270426239, 51.124450908533078 ] } },
{ "type": "Feature", "properties": { "visible_points": 0, "total_points": 46, "visibility_pct": 0.0 }, "geometry": { "type": "Point", "coordinates": [ -3.23772031903901, 51.124453004419721 ] } },
{ "type": "Feature", "properties": { "visible_points": 3, "total_points": 49, "visibility_pct": 6.1224489795918364 }, "geometry": { "type": "Point", "coordinates": [ -3.238020129893149, 51.12455774152523 ] } },
{ "type": "Feature", "properties": { "visible_points": 4, "total_points": 51, "visibility_pct": 7.8431372549019605 }, "geometry": { "type": "Point", "coordinates": [ -3.237822178052856, 51.124559837587093 ] } },
{ "type": "Feature", "properties": { "visible_points": 0, "total_points": 52, "visibility_pct": 0.0 }, "geometry": { "type": "Point", "coordinates": [ -3.237624226188668, 51.124561933313935 ] } },
{ "type": "Feature", "properties": { "visible_points": 3, "total_points": 55, "visibility_pct": 5.4545454545454541 }, "geometry": { "type": "Point", "coordinates": [ -3.237924037543647, 51.124666670660908 ] } },
{ "type": "Feature", "properties": { "visible_points": 3, "total_points": 56, "visibility_pct": 5.3571428571428568 }, "geometry": { "type": "Point", "coordinates": [ -3.237726085226399, 51.124668766562991 ] } },
{ "type": "Feature", "properties": { "visible_points": 0, "total_points": 57, "visibility_pct": 0.0 }, "geometry": { "type": "Point", "coordinates": [ -3.237528132885255, 51.124670862130024 ] } },
{ "type": "Feature", "properties": { "visible_points": 6, "total_points": 60, "visibility_pct": 10.0 }, "geometry": { "type": "Point", "coordinates": [ -3.237827944741085, 51.124775599718447 ] } },
{ "type": "Feature", "properties": { "visible_points": 2, "total_points": 61, "visibility_pct": 3.278688524590164 }, "geometry": { "type": "Point", "coordinates": [ -3.237629991946868, 51.124777695460729 ] } },
{ "type": "Feature", "properties": { "visible_points": 4, "total_points": 64, "visibility_pct": 6.25 }, "geometry": { "type": "Point", "coordinates": [ -3.237731851485439, 51.124884528697848 ] } },
{ "type": "Feature", "properties": { "visible_points": 0, "total_points": 64, "visibility_pct": 0.0 }, "geometry": { "type": "Point", "coordinates": [ -3.237533898214263, 51.124886624280343 ] } },
{ "type": "Feature", "properties": { "visible_points": 0, "total_points": 60, "visibility_pct": 0.0 }, "geometry": { "type": "Point", "coordinates": [ -3.237635757776717, 51.124993457599118 ] } },
{ "type": "Feature", "properties": { "visible_points": 0, "total_points": 58, "visibility_pct": 0.0 }, "geometry": { "type": "Point", "coordinates": [ -3.237437804028571, 51.124995553021805 ] } },
{ "type": "Feature", "properties": { "visible_points": 0, "total_points": 55, "visibility_pct": 0.0 }, "geometry": { "type": "Point", "coordinates": [ -3.237737617816134, 51.125100290824314 ] } },
{ "type": "Feature", "properties": { "visible_points": 1, "total_points": 54, "visibility_pct": 1.8518518518518516 }, "geometry": { "type": "Point", "coordinates": [ -3.237539663614911, 51.125102386422263 ] } },
{ "type": "Feature", "properties": { "visible_points": 0, "total_points": 51, "visibility_pct": 0.0 }, "geometry": { "type": "Point", "coordinates": [ -3.237341709389796, 51.125104481685156 ] } },
{ "type": "Feature", "properties": { "visible_points": 1, "total_points": 49, "visibility_pct": 2.0408163265306123 }, "geometry": { "type": "Point", "coordinates": [ -3.237641523678213, 51.125209219729108 ] } },
{ "type": "Feature", "properties": { "visible_points": 0, "total_points": 47, "visibility_pct": 0.0 }, "geometry": { "type": "Point", "coordinates": [ -3.237443569000016, 51.125211315167235 ] } },
{ "type": "Feature", "properties": { "visible_points": 2, "total_points": 43, "visibility_pct": 4.6511627906976747 }, "geometry": { "type": "Point", "coordinates": [ -3.237545429087199, 51.125318148555742 ] } },
{ "type": "Feature", "properties": { "visible_points": 1, "total_points": 41, "visibility_pct": 2.4390243902439024 }, "geometry": { "type": "Point", "coordinates": [ -3.237347473932035, 51.125320243834082 ] } },
{ "type": "Feature", "properties": { "visible_points": 3, "total_points": 37, "visibility_pct": 8.1081081081081088 }, "geometry": { "type": "Point", "coordinates": [ -3.237449334043102, 51.125427077304238 ] } }
]
}
