{
"type": "FeatureCollection",
"name": "2b5e18078988_visibility",
"crs": { "type": "name", "properties": { "name": "urn:ogc:def:crs:OGC:1.3:CRS84" } },
"features": [
{ "type": "Feature", "properties": { "visible_points": 20, "total_points": 52, "visibility_pct": 38.461538461538467 }, "geometry": { "type": "Point", "coordinates": [ -3.184537443266736, 51.051899199726826 ] } },
{ "type": "Feature", "properties": { "visible_points": 29, "total_points": 52, "visibility_pct": 55.769230769230774 }, "geometry": { "type": "Point", "coordinates": [ -3.184339796483417, 51.051901203162288 ] } },
{ "type": "Feature", "properties": { "visible_points": 29, "total_points": 52, "visibility_pct": 55.769230769230774 }, "geometry": { "type": "Point", "coordinates": [ -3.184142149683724, 51.051903206266424 ] } },
{ "type": "Feature", "properties": { "visible_points": 22, "total_points": 48, "visibility_pct": 45.833333333333329 }, "geometry": { "type": "Point", "coordinates": [ -3.183944502861599, 51.051905209036306 ] } },
{ "type": "Feature", "properties": { "visible_points": 14, "total_points": 43, "visibility_pct": 32.558139534883722 }, "geometry": { "type": "Point", "coordinates": [ -3.183746856017041, 51.051907211471892 ] } },
{ "type": "Feature", "properties": { "visible_points": 17, "total_points": 44, "visibility_pct": 38.636363636363633 }, "geometry": { "type": "Point", "coordinates": [ -3.18483666727402, 51.052004078000941 ] } },
{ "type": "Feature", "properties": { "visible_points": 24, "total_points": 51, "visibility_pct": 47.058823529411761 }, "geometry": { "type": "Point", "coordinates": [ -3.184639020031016, 51.052006081897055 ] } },
{ "type": "Feature", "properties": { "visible_points": 27, "total_points": 52, "visibility_pct": 51.923076923076927 }, "geometry": { "type": "Point", "coordinates": [ -3.184441372792122, 51.052008085490797 ] } },
{ "type": "Feature", "properties": { "visible_points": 28, "total_points": 52, "visibility_pct": 53.846153846153847 }, "geometry": { "type": "Point", "coordinates": [ -3.184243725549591, 51.052010088766721 ] } },
{ "type": "Feature", "properties": { "visible_points": 22, "total_points": 52, "visibility_pct": 42.307692307692307 }, "geometry": { "type": "Point", "coordinates": [ -3.184046078284624, 51.052012091708399 ] } },
{ "type": "Feature", "properties": { "visible_points": 14, "total_points": 47, "visibility_pct": 29.787234042553191 }, "geometry": { "type": "Point", "coordinates": [ -3.183848430997219, 51.052014094315759 ] } },
{ "type": "Feature", "properties": { "visible_points": 16, "total_points": 40, "visibility_pct": 40.0 }, "geometry": { "type": "Point", "coordinates": [ -3.184938244955599, 51.052110959919531 ] } },
{ "type": "Feature", "properties": { "visible_points": 25, "total_points": 47, "visibility_pct": 53.191489361702125 }, "geometry": { "type": "Point", "coordinates": [ -3.184740597266891, 51.052112963986126 ] } },
{ "type": "Feature", "properties": { "visible_points": 30, "total_points": 51, "visibility_pct": 58.82352941176471 }, "geometry": { "type": "Point", "coordinates": [ -3.18454294957223, 51.05211496773223 ] } },
{ "type": "Feature", "properties": { "visible_points": 26, "total_points": 52, "visibility_pct": 50.0 }, "geometry": { "type": "Point", "coordinates": [ -3.184345301880732, 51.052116971176801 ] } },
{ "type": "Feature", "properties": { "visible_points": 13, "total_points": 52, "visibility_pct": 25.0 }, "geometry": { "type": "Point", "coordinates": [ -3.184147654172917, 51.052118974290238 ] } },
{ "type": "Feature", "properties": { "visible_points": 11, "total_points": 50, "visibility_pct": 22.0 }, "geometry": { "type": "Point", "coordinates": [ -3.183950006442662, 51.052120977069386 ] } },
{ "type": "Feature", "properties": { "visible_points": 2, "total_points": 44, "visibility_pct": 4.5454545454545459 }, "geometry": { "type": "Point", "coordinates": [ -3.183752358689981, 51.05212297951423 ] } },
{ "type": "Feature", "properties": { "visible_points": 11, "total_points": 51, "visibility_pct": 21.568627450980394 }, "geometry": { "type": "Point", "coordinates": [ -3.184051582353383, 51.052227859732788 ] } },
{ "type": "Feature", "properties": { "visible_points": 4, "total_points": 46, "visibility_pct": 8.695652173913043 }, "geometry": { "type": "Point", "coordinates": [ -3.18385393415785, 51.052229862349421 ] } }
]
}
