{
"type": "FeatureCollection",
"name": "5f51c7dc7106_visibility",
"crs": { "type": "name", "properties": { "name": "urn:ogc:def:crs:OGC:1.3:CRS84" } },
"features": [
{ "type": "Feature", "properties": { "visible_points": 1, "total_points": 56, "visibility_pct": 1.7857142857142856 }, "geometry": { "type": "Point", "coordinates": [ -3.03265739376261, 51.124880513706472 ] } },
{ "type": "Feature", "properties": { "visible_points": 0, "total_points": 53, "visibility_pct": 0.0 }, "geometry": { "type": "Point", "coordinates": [ -3.032459425819313, 51.124882259739429 ] } },
{ "type": "Feature", "properties": { "visible_points": 0, "total_points": 60, "visibility_pct": 0.0 }, "geometry": { "type": "Point", "coordinates": [ -3.032560818380504, 51.12498928567711 ] } },
{ "type": "Feature", "properties": { "visible_points": 0, "total_points": 56, "visibility_pct": 0.0 }, "geometry": { "type": "Point", "coordinates": [ -3.032362849966454, 51.124991031549136 ] } },
{ "type": "Feature", "properties": { "visible_points": 1, "total_points": 61, "visibility_pct": 1.639344262295082 }, "geometry": { "type": "Point", "coordinates": [ -3.032860180257651, 51.125094565140913 ] } },
{ "type": "Feature", "properties": { "visible_points": 1, "total_points": 61, "visibility_pct": 1.639344262295082 }, "geometry": { "type": "Point", "coordinates": [ -3.032662211412442, 51.125096311522292 ] } },
{ "type": "Feature", "properties": { "visible_points": 1, "total_points": 61, "visibility_pct": 1.639344262295082 }, "geometry": { "type": "Point", "coordinates": [ -3.032464242547425, 51.125098057568522 ] } },
{ "type": "Feature", "properties": { "visible_points": 1, "total_points": 57, "visibility_pct": 1.7543859649122806 }, "geometry": { "type": "Point", "coordinates": [ -3.03226627366262, 51.125099803279639 ] } },
{ "type": "Feature", "properties": { "visible_points": 2, "total_points": 61, "visibility_pct": 3.278688524590164 }, "geometry": { "type": "Point", "coordinates": [ -3.032961574211299, 51.125201590719378 ] } },
{ "type": "Feature", "properties": { "visible_points": 2, "total_points": 61, "visibility_pct": 3.278688524590164 }, "geometry": { "type": "Point", "coordinates": [ -3.032763604915129, 51.125203337274961 ] } },
{ "type": "Feature", "properties": { "visible_points": 0, "total_points": 61, "visibility_pct": 0.0 }, "geometry": { "type": "Point", "coordinates": [ -3.032565635599151, 51.125205083495416 ] } },
{ "type": "Feature", "properties": { "visible_points": 0, "total_points": 61, "visibility_pct": 0.0 }, "geometry": { "type": "Point", "coordinates": [ -3.032367666263376, 51.12520682938073 ] } },
{ "type": "Feature", "properties": { "visible_points": 0, "total_points": 56, "visibility_pct": 0.0 }, "geometry": { "type": "Point", "coordinates": [ -3.032169696907799, 51.125208574930916 ] } },
{ "type": "Feature", "properties": { "visible_points": 1, "total_points": 46, "visibility_pct": 2.1739130434782608 }, "geometry": { "type": "Point", "coordinates": [ -3.03326093836302, 51.125306869140395 ] } },
{ "type": "Feature", "properties": { "visible_points": 0, "total_points": 54, "visibility_pct": 0.0 }, "geometry": { "type": "Point", "coordinates": [ -3.033062968635702, 51.125308616205331 ] } },
{ "type": "Feature", "properties": { "visible_points": 4, "total_points": 60, "visibility_pct": 6.666666666666667 }, "geometry": { "type": "Point", "coordinates": [ -3.032864998888571, 51.12531036293511 ] } },
{ "type": "Feature", "properties": { "visible_points": 2, "total_points": 61, "visibility_pct": 3.278688524590164 }, "geometry": { "type": "Point", "coordinates": [ -3.03266702912163, 51.125312109329784 ] } },
{ "type": "Feature", "properties": { "visible_points": 0, "total_points": 61, "visibility_pct": 0.0 }, "geometry": { "type": "Point", "coordinates": [ -3.032469059334887, 51.125313855389336 ] } },
{ "type": "Feature", "properties": { "visible_points": 0, "total_points": 60, "visibility_pct": 0.0 }, "geometry": { "type": "Point", "coordinates": [ -3.032271089528342, 51.125315601113734 ] } },
{ "type": "Feature", "properties": { "visible_points": 0, "total_points": 53, "visibility_pct": 0.0 }, "geometry": { "type": "Point", "coordinates": [ -3.032966393332772, 51.12541738850279 ] } },
{ "type": "Feature", "properties": { "visible_points": 1, "total_points": 57, "visibility_pct": 1.7543859649122806 }, "geometry": { "type": "Point", "coordinates": [ -3.032768423114869, 51.125419135071674 ] } },
{ "type": "Feature", "properties": { "visible_points": 0, "total_points": 58, "visibility_pct": 0.0 }, "geometry": { "type": "Point", "coordinates": [ -3.032570452877154, 51.125420881305409 ] } },
{ "type": "Feature", "properties": { "visible_points": 0, "total_points": 50, "visibility_pct": 0.0 }, "geometry": { "type": "Point", "coordinates": [ -3.032869817370683, 51.125526158323169 ] } }
]
}
