{
"type": "FeatureCollection",
"name": "8a0cba40c5e6_visibility",
"crs": { "type": "name", "properties": { "name": "urn:ogc:def:crs:OGC:1.3:CRS84" } },
"features": [
{ "type": "Feature", "properties": { "visible_points": 7, "total_points": 50, "visibility_pct": 14.000000000000002 }, "geometry": { "type": "Point", "coordinates": [ -3.089427809613011, 51.08766804612786 ] } },
{ "type": "Feature", "properties": { "visible_points": 0, "total_points": 55, "visibility_pct": 0.0 }, "geometry": { "type": "Point", "coordinates": [ -3.089230004265024, 51.087669887261754 ] } },
{ "type": "Feature", "properties": { "visible_points": 0, "total_points": 57, "visibility_pct": 0.0 }, "geometry": { "type": "Point", "coordinates": [ -3.089032198896138, 51.087671728061089 ] } },
{ "type": "Feature", "properties": { "visible_points": 0, "total_points": 57, "visibility_pct": 0.0 }, "geometry": { "type": "Point", "coordinates": [ -3.088834393506351, 51.087673568525823 ] } },
{ "type": "Feature", "properties": { "visible_points": 0, "total_points": 55, "visibility_pct": 0.0 }, "geometry": { "type": "Point", "coordinates": [ -3.088636588095662, 51.087675408655976 ] } },
{ "type": "Feature", "properties": { "visible_points": 0, "total_points": 55, "visibility_pct": 0.0 }, "geometry": { "type": "Point", "coordinates": [ -3.089331442720857, 51.087776851912061 ] } },
{ "type": "Feature", "properties": { "visible_points": 0, "total_points": 57, "visibility_pct": 0.0 }, "geometry": { "type": "Point", "coordinates": [ -3.089133636900736, 51.087778692887042 ] } },
{ "type": "Feature", "properties": { "visible_points": 0, "total_points": 57, "visibility_pct": 0.0 }, "geometry": { "type": "Point", "coordinates": [ -3.088935831059711, 51.087780533527436 ] } },
{ "type": "Feature", "properties": { "visible_points": 0, "total_points": 57, "visibility_pct": 0.0 }, "geometry": { "type": "Point", "coordinates": [ -3.088738025197784, 51.087782373833228 ] } },
{ "type": "Feature", "properties": { "visible_points": 1, "total_points": 55, "visibility_pct": 1.8181818181818181 }, "geometry": { "type": "Point", "coordinates": [ -3.088540219314965, 51.087784213804454 ] } },
{ "type": "Feature", "properties": { "visible_points": 0, "total_points": 57, "visibility_pct": 0.0 }, "geometry": { "type": "Point", "coordinates": [ -3.089235075377462, 51.087885657618848 ] } },
{ "type": "Feature", "properties": { "visible_points": 0, "total_points": 57, "visibility_pct": 0.0 }, "geometry": { "type": "Point", "coordinates": [ -3.0890372690852, 51.087887498434903 ] } },
{ "type": "Feature", "properties": { "visible_points": 1, "total_points": 57, "visibility_pct": 1.7543859649122806 }, "geometry": { "type": "Point", "coordinates": [ -3.088839462772034, 51.087889338916369 ] } },
{ "type": "Feature", "properties": { "visible_points": 3, "total_points": 57, "visibility_pct": 5.2631578947368416 }, "geometry": { "type": "Point", "coordinates": [ -3.088641656437971, 51.087891179063256 ] } },
{ "type": "Feature", "properties": { "visible_points": 2, "total_points": 51, "visibility_pct": 3.9215686274509802 }, "geometry": { "type": "Point", "coordinates": [ -3.088443850083018, 51.087893018875548 ] } },
{ "type": "Feature", "properties": { "visible_points": 4, "total_points": 54, "visibility_pct": 7.4074074074074066 }, "geometry": { "type": "Point", "coordinates": [ -3.089336514326323, 51.087992622256536 ] } },
{ "type": "Feature", "properties": { "visible_points": 0, "total_points": 57, "visibility_pct": 0.0 }, "geometry": { "type": "Point", "coordinates": [ -3.08913870758282, 51.087994463248251 ] } },
{ "type": "Feature", "properties": { "visible_points": 0, "total_points": 57, "visibility_pct": 0.0 }, "geometry": { "type": "Point", "coordinates": [ -3.088940900818416, 51.087996303905378 ] } },
{ "type": "Feature", "properties": { "visible_points": 2, "total_points": 57, "visibility_pct": 3.5087719298245612 }, "geometry": { "type": "Point", "coordinates": [ -3.088743094033108, 51.087998144227925 ] } },
{ "type": "Feature", "properties": { "visible_points": 1, "total_points": 54, "visibility_pct": 1.8518518518518516 }, "geometry": { "type": "Point", "coordinates": [ -3.088545287226906, 51.087999984215855 ] } },
{ "type": "Feature", "properties": { "visible_points": 4, "total_points": 53, "visibility_pct": 7.5471698113207548 }, "geometry": { "type": "Point", "coordinates": [ -3.089240146552577, 51.088101427967437 ] } },
{ "type": "Feature", "properties": { "visible_points": 4, "total_points": 56, "visibility_pct": 7.1428571428571423 }, "geometry": { "type": "Point", "coordinates": [ -3.089042339336926, 51.088103268800246 ] } }
]
}
