{
"type": "FeatureCollection",
"name": "a85ade0e7e19_visibility",
"crs": { "type": "name", "properties": { "name": "urn:ogc:def:crs:OGC:1.3:CRS84" } },
"features": [
{ "type": "Feature", "properties": { "visible_points": 4, "total_points": 53, "visibility_pct": 7.5471698113207548 }, "geometry": { "type": "Point", "coordinates": [ -3.240479865873024, 50.986351287826437 ] } },
{ "type": "Feature", "properties": { "visible_points": 6, "total_points": 56, "visibility_pct": 10.714285714285714 }, "geometry": { "type": "Point", "coordinates": [ -3.240581423298222, 50.986458123694398 ] } },
{ "type": "Feature", "properties": { "visible_points": 7, "total_points": 60, "visibility_pct": 11.666666666666666 }, "geometry": { "type": "Point", "coordinates": [ -3.240384061260196, 50.986460220119802 ] } },
{ "type": "Feature", "properties": { "visible_points": 0, "total_points": 61, "visibility_pct": 0.0 }, "geometry": { "type": "Point", "coordinates": [ -3.240186699198601, 50.986462316211799 ] } },
{ "type": "Feature", "properties": { "visible_points": 3, "total_points": 56, "visibility_pct": 5.3571428571428568 }, "geometry": { "type": "Point", "coordinates": [ -3.240682981191407, 50.986564959469185 ] } },
{ "type": "Feature", "properties": { "visible_points": 5, "total_points": 61, "visibility_pct": 8.1967213114754092 }, "geometry": { "type": "Point", "coordinates": [ -3.240485618708959, 50.986567056069021 ] } },
{ "type": "Feature", "properties": { "visible_points": 8, "total_points": 61, "visibility_pct": 13.114754098360656 }, "geometry": { "type": "Point", "coordinates": [ -3.24028825620294, 50.986569152335434 ] } },
{ "type": "Feature", "properties": { "visible_points": 8, "total_points": 61, "visibility_pct": 13.114754098360656 }, "geometry": { "type": "Point", "coordinates": [ -3.240090893673349, 50.986571248268447 ] } },
{ "type": "Feature", "properties": { "visible_points": 0, "total_points": 59, "visibility_pct": 0.0 }, "geometry": { "type": "Point", "coordinates": [ -3.239893531120201, 50.986573343868059 ] } },
{ "type": "Feature", "properties": { "visible_points": 0, "total_points": 55, "visibility_pct": 0.0 }, "geometry": { "type": "Point", "coordinates": [ -3.240784539552581, 50.986671795150798 ] } },
{ "type": "Feature", "properties": { "visible_points": 0, "total_points": 61, "visibility_pct": 0.0 }, "geometry": { "type": "Point", "coordinates": [ -3.240587176625709, 50.986673891925044 ] } },
{ "type": "Feature", "properties": { "visible_points": 6, "total_points": 61, "visibility_pct": 9.8360655737704921 }, "geometry": { "type": "Point", "coordinates": [ -3.240389813675264, 50.986675988365896 ] } },
{ "type": "Feature", "properties": { "visible_points": 10, "total_points": 61, "visibility_pct": 16.393442622950818 }, "geometry": { "type": "Point", "coordinates": [ -3.240192450701248, 50.986678084473319 ] } },
{ "type": "Feature", "properties": { "visible_points": 4, "total_points": 61, "visibility_pct": 6.557377049180328 }, "geometry": { "type": "Point", "coordinates": [ -3.239995087703666, 50.986680180247355 ] } },
{ "type": "Feature", "properties": { "visible_points": 4, "total_points": 54, "visibility_pct": 7.4074074074074066 }, "geometry": { "type": "Point", "coordinates": [ -3.23979772468252, 50.986682275687983 ] } },
{ "type": "Feature", "properties": { "visible_points": 5, "total_points": 61, "visibility_pct": 8.1967213114754092 }, "geometry": { "type": "Point", "coordinates": [ -3.240491371615576, 50.98678282430317 ] } },
{ "type": "Feature", "properties": { "visible_points": 8, "total_points": 61, "visibility_pct": 13.114754098360656 }, "geometry": { "type": "Point", "coordinates": [ -3.240294008197135, 50.986784920585023 ] } },
{ "type": "Feature", "properties": { "visible_points": 5, "total_points": 60, "visibility_pct": 8.3333333333333321 }, "geometry": { "type": "Point", "coordinates": [ -3.240096644755115, 50.986787016533476 ] } },
{ "type": "Feature", "properties": { "visible_points": 7, "total_points": 54, "visibility_pct": 12.962962962962962 }, "geometry": { "type": "Point", "coordinates": [ -3.239899281289539, 50.986789112148521 ] } },
{ "type": "Feature", "properties": { "visible_points": 0, "total_points": 58, "visibility_pct": 0.0 }, "geometry": { "type": "Point", "coordinates": [ -3.240395566161009, 50.986891756603576 ] } },
{ "type": "Feature", "properties": { "visible_points": 0, "total_points": 57, "visibility_pct": 0.0 }, "geometry": { "type": "Point", "coordinates": [ -3.24019820227456, 50.986893852726425 ] } },
{ "type": "Feature", "properties": { "visible_points": 2, "total_points": 53, "visibility_pct": 3.7735849056603774 }, "geometry": { "type": "Point", "coordinates": [ -3.240000838364547, 50.986895948515894 ] } },
{ "type": "Feature", "properties": { "visible_points": 0, "total_points": 50, "visibility_pct": 0.0 }, "geometry": { "type": "Point", "coordinates": [ -3.240102395907543, 50.987002784790086 ] } }
]
}
