{
"type": "FeatureCollection",
"name": "f794947a1a14_visibility",
"crs": { "type": "name", "properties": { "name": "urn:ogc:def:crs:OGC:1.3:CRS84" } },
"features": [
{ "type": "Feature", "properties": { "visible_points": 0, "total_points": 41, "visibility_pct": 0.0 }, "geometry": { "type": "Point", "coordinates": [ -3.549938216733339, 51.209717577232752 ] } },
{ "type": "Feature", "properties": { "visible_points": 0, "total_points": 50, "visibility_pct": 0.0 }, "geometry": { "type": "Point", "coordinates": [ -3.549739931017057, 51.209720205299114 ] } },
{ "type": "Feature", "properties": { "visible_points": 0, "total_points": 54, "visibility_pct": 0.0 }, "geometry": { "type": "Point", "coordinates": [ -3.549541645270693, 51.209722833029474 ] } },
{ "type": "Feature", "properties": { "visible_points": 2, "total_points": 56, "visibility_pct": 3.5714285714285712 }, "geometry": { "type": "Point", "coordinates": [ -3.549343359494242, 51.209725460423805 ] } },
{ "type": "Feature", "properties": { "visible_points": 0, "total_points": 57, "visibility_pct": 0.0 }, "geometry": { "type": "Point", "coordinates": [ -3.549145073687712, 51.209728087482127 ] } },
{ "type": "Feature", "properties": { "visible_points": 0, "total_points": 56, "visibility_pct": 0.0 }, "geometry": { "type": "Point", "coordinates": [ -3.548946787851107, 51.20973071420444 ] } },
{ "type": "Feature", "properties": { "visible_points": 0, "total_points": 48, "visibility_pct": 0.0 }, "geometry": { "type": "Point", "coordinates": [ -3.54984269485007, 51.209826754331495 ] } },
{ "type": "Feature", "properties": { "visible_points": 0, "total_points": 55, "visibility_pct": 0.0 }, "geometry": { "type": "Point", "coordinates": [ -3.549644408650958, 51.209829382237821 ] } },
{ "type": "Feature", "properties": { "visible_points": 2, "total_points": 57, "visibility_pct": 3.5087719298245612 }, "geometry": { "type": "Point", "coordinates": [ -3.549446122421764, 51.209832009808139 ] } },
{ "type": "Feature", "properties": { "visible_points": 1, "total_points": 57, "visibility_pct": 1.7543859649122806 }, "geometry": { "type": "Point", "coordinates": [ -3.549247836162487, 51.209834637042441 ] } },
{ "type": "Feature", "properties": { "visible_points": 0, "total_points": 57, "visibility_pct": 0.0 }, "geometry": { "type": "Point", "coordinates": [ -3.549049549873131, 51.20983726394072 ] } },
{ "type": "Feature", "properties": { "visible_points": 0, "total_points": 53, "visibility_pct": 0.0 }, "geometry": { "type": "Point", "coordinates": [ -3.548851263553698, 51.209839890502991 ] } },
{ "type": "Feature", "properties": { "visible_points": 0, "total_points": 57, "visibility_pct": 0.0 }, "geometry": { "type": "Point", "coordinates": [ -3.549548885832108, 51.20993855909839 ] } },
{ "type": "Feature", "properties": { "visible_points": 0, "total_points": 57, "visibility_pct": 0.0 }, "geometry": { "type": "Point", "coordinates": [ -3.549350599120081, 51.209941186508658 ] } },
{ "type": "Feature", "properties": { "visible_points": 1, "total_points": 57, "visibility_pct": 1.7543859649122806 }, "geometry": { "type": "Point", "coordinates": [ -3.549152312377973, 51.20994381358291 ] } },
{ "type": "Feature", "properties": { "visible_points": 1, "total_points": 54, "visibility_pct": 1.8518518518518516 }, "geometry": { "type": "Point", "coordinates": [ -3.548954025605788, 51.209946440321161 ] } },
{ "type": "Feature", "properties": { "visible_points": 1, "total_points": 54, "visibility_pct": 1.8518518518518516 }, "geometry": { "type": "Point", "coordinates": [ -3.5490567881407, 51.210052990045284 ] } },
{ "type": "Feature", "properties": { "visible_points": 0, "total_points": 50, "visibility_pct": 0.0 }, "geometry": { "type": "Point", "coordinates": [ -3.548858500885689, 51.210055616623485 ] } },
{ "type": "Feature", "properties": { "visible_points": 0, "total_points": 53, "visibility_pct": 0.0 }, "geometry": { "type": "Point", "coordinates": [ -3.549159551158439, 51.21015953967531 ] } },
{ "type": "Feature", "properties": { "visible_points": 3, "total_points": 49, "visibility_pct": 6.1224489795918364 }, "geometry": { "type": "Point", "coordinates": [ -3.548961263450667, 51.210162166429498 ] } },
{ "type": "Feature", "properties": { "visible_points": 2, "total_points": 44, "visibility_pct": 4.5454545454545459 }, "geometry": { "type": "Point", "coordinates": [ -3.549064026498477, 51.210268716141442 ] } },
{ "type": "Feature", "properties": { "visible_points": 0, "total_points": 40, "visibility_pct": 0.0 }, "geometry": { "type": "Point", "coordinates": [ -3.548865738307864, 51.21027134273556 ] } }
]
}
