{
"type": "FeatureCollection",
"name": "fa999342947f_visibility",
"crs": { "type": "name", "properties": { "name": "urn:ogc:def:crs:OGC:1.3:CRS84" } },
"features": [
{ "type": "Feature", "properties": { "visible_points": 2, "total_points": 50, "visibility_pct": 4.0 }, "geometry": { "type": "Point", "coordinates": [ -3.26850531284604, 51.144840437590531 ] } },
{ "type": "Feature", "properties": { "visible_points": 0, "total_points": 54, "visibility_pct": 0.0 }, "geometry": { "type": "Point", "coordinates": [ -3.268307276711269, 51.1448425854257 ] } },
{ "type": "Feature", "properties": { "visible_points": 1, "total_points": 55, "visibility_pct": 1.8181818181818181 }, "geometry": { "type": "Point", "coordinates": [ -3.268109240551899, 51.144844732925833 ] } },
{ "type": "Feature", "properties": { "visible_points": 5, "total_points": 50, "visibility_pct": 10.0 }, "geometry": { "type": "Point", "coordinates": [ -3.268607288851709, 51.144947242680047 ] } },
{ "type": "Feature", "properties": { "visible_points": 0, "total_points": 55, "visibility_pct": 0.0 }, "geometry": { "type": "Point", "coordinates": [ -3.268409252261438, 51.144949390696212 ] } },
{ "type": "Feature", "properties": { "visible_points": 0, "total_points": 55, "visibility_pct": 0.0 }, "geometry": { "type": "Point", "coordinates": [ -3.268211215646564, 51.144951538377335 ] } },
{ "type": "Feature", "properties": { "visible_points": 0, "total_points": 55, "visibility_pct": 0.0 }, "geometry": { "type": "Point", "coordinates": [ -3.268013179007091, 51.144953685723422 ] } },
{ "type": "Feature", "properties": { "visible_points": 0, "total_points": 54, "visibility_pct": 0.0 }, "geometry": { "type": "Point", "coordinates": [ -3.267815142582298, 51.144955832549783 ] } },
{ "type": "Feature", "properties": { "visible_points": 1, "total_points": 55, "visibility_pct": 1.8181818181818181 }, "geometry": { "type": "Point", "coordinates": [ -3.268511228291703, 51.14505619586722 ] } },
{ "type": "Feature", "properties": { "visible_points": 0, "total_points": 55, "visibility_pct": 0.0 }, "geometry": { "type": "Point", "coordinates": [ -3.268313191221325, 51.145058343729353 ] } },
{ "type": "Feature", "properties": { "visible_points": 1, "total_points": 55, "visibility_pct": 1.8181818181818181 }, "geometry": { "type": "Point", "coordinates": [ -3.268115154126346, 51.145060491256409 ] } },
{ "type": "Feature", "properties": { "visible_points": 0, "total_points": 55, "visibility_pct": 0.0 }, "geometry": { "type": "Point", "coordinates": [ -3.267917117110363, 51.145062638408291 ] } },
{ "type": "Feature", "properties": { "visible_points": 0, "total_points": 53, "visibility_pct": 0.0 }, "geometry": { "type": "Point", "coordinates": [ -3.26771908033739, 51.1450647849381 ] } },
{ "type": "Feature", "properties": { "visible_points": 1, "total_points": 52, "visibility_pct": 1.9230769230769231 }, "geometry": { "type": "Point", "coordinates": [ -3.268613204802076, 51.14516300093873 ] } },
{ "type": "Feature", "properties": { "visible_points": 0, "total_points": 55, "visibility_pct": 0.0 }, "geometry": { "type": "Point", "coordinates": [ -3.268415167276191, 51.145165148981853 ] } },
{ "type": "Feature", "properties": { "visible_points": 0, "total_points": 55, "visibility_pct": 0.0 }, "geometry": { "type": "Point", "coordinates": [ -3.268217129725701, 51.14516729668992 ] } },
{ "type": "Feature", "properties": { "visible_points": 0, "total_points": 55, "visibility_pct": 0.0 }, "geometry": { "type": "Point", "coordinates": [ -3.268019092150607, 51.145169444062944 ] } },
{ "type": "Feature", "properties": { "visible_points": 0, "total_points": 55, "visibility_pct": 0.0 }, "geometry": { "type": "Point", "coordinates": [ -3.26782105478429, 51.145171590923532 ] } },
{ "type": "Feature", "properties": { "visible_points": 0, "total_points": 55, "visibility_pct": 0.0 }, "geometry": { "type": "Point", "coordinates": [ -3.26831910580516, 51.145274102023905 ] } },
{ "type": "Feature", "properties": { "visible_points": 0, "total_points": 55, "visibility_pct": 0.0 }, "geometry": { "type": "Point", "coordinates": [ -3.268121067774552, 51.145276249577911 ] } },
{ "type": "Feature", "properties": { "visible_points": 0, "total_points": 54, "visibility_pct": 0.0 }, "geometry": { "type": "Point", "coordinates": [ -3.267923029817292, 51.145278396758947 ] } },
{ "type": "Feature", "properties": { "visible_points": 0, "total_points": 52, "visibility_pct": 0.0 }, "geometry": { "type": "Point", "coordinates": [ -3.268025005367887, 51.145385202393349 ] } }
]
}
