{
"type": "FeatureCollection",
"name": "NORDE_42",
"crs": { "type": "name", "properties": { "name": "urn:ogc:def:crs:OGC:1.3:CRS84" } },
"features": [
{ "type": "Feature", "properties": { "osm_id": 913567493, "name": null, "amenity": "bench", "man_made": null, "leisure": null, "playground": null, "memorial": null }, "geometry": { "type": "Point", "coordinates": [ -4.0611931, 51.0848645 ] } },
{ "type": "Feature", "properties": { "osm_id": 913567492, "name": null, "amenity": "bench", "man_made": null, "leisure": null, "playground": null, "memorial": null }, "geometry": { "type": "Point", "coordinates": [ -4.0612615, 51.0848729 ] } }
]
}
