{
"type": "FeatureCollection",
"name": "NORDE_22",
"crs": { "type": "name", "properties": { "name": "urn:ogc:def:crs:OGC:1.3:CRS84" } },
"features": [
{ "type": "Feature", "properties": { "osm_id": 13537887310, "name": null, "amenity": "bench", "man_made": null, "leisure": null, "playground": null, "memorial": null }, "geometry": { "type": "Point", "coordinates": [ -4.0386926, 51.0754707 ] } },
{ "type": "Feature", "properties": { "osm_id": 13537887312, "name": null, "amenity": "bench", "man_made": null, "leisure": null, "playground": null, "memorial": null }, "geometry": { "type": "Point", "coordinates": [ -4.038979, 51.0755318 ] } },
{ "type": "Feature", "properties": { "osm_id": 13537887311, "name": null, "amenity": "bench", "man_made": null, "leisure": null, "playground": null, "memorial": null }, "geometry": { "type": "Point", "coordinates": [ -4.0385277, 51.0755752 ] } },
{ "type": "Feature", "properties": { "osm_id": 13537887313, "name": null, "amenity": "bench", "man_made": null, "leisure": null, "playground": null, "memorial": null }, "geometry": { "type": "Point", "coordinates": [ -4.03882, 51.0755882 ] } }
]
}
