{
"type": "FeatureCollection",
"name": "3fa76d88a8ad_visibility",
"crs": { "type": "name", "properties": { "name": "urn:ogc:def:crs:OGC:1.3:CRS84" } },
"features": [
{ "type": "Feature", "properties": { "visible_points": 7, "total_points": 55, "visibility_pct": 12.727272727272727 }, "geometry": { "type": "Point", "coordinates": [ -2.428201618651301, 51.543054143101614 ] } },
{ "type": "Feature", "properties": { "visible_points": 8, "total_points": 55, "visibility_pct": 14.545454545454545 }, "geometry": { "type": "Point", "coordinates": [ -2.428001813573806, 51.543054872503305 ] } },
{ "type": "Feature", "properties": { "visible_points": 6, "total_points": 52, "visibility_pct": 11.538461538461538 }, "geometry": { "type": "Point", "coordinates": [ -2.427802008487888, 51.543055601564767 ] } },
{ "type": "Feature", "properties": { "visible_points": 9, "total_points": 55, "visibility_pct": 16.363636363636363 }, "geometry": { "type": "Point", "coordinates": [ -2.428302536013945, 51.543161673819633 ] } },
{ "type": "Feature", "properties": { "visible_points": 8, "total_points": 55, "visibility_pct": 14.545454545454545 }, "geometry": { "type": "Point", "coordinates": [ -2.428102730465697, 51.543162403395051 ] } },
{ "type": "Feature", "properties": { "visible_points": 8, "total_points": 55, "visibility_pct": 14.545454545454545 }, "geometry": { "type": "Point", "coordinates": [ -2.427902924909023, 51.543163132630248 ] } },
{ "type": "Feature", "properties": { "visible_points": 0, "total_points": 53, "visibility_pct": 0.0 }, "geometry": { "type": "Point", "coordinates": [ -2.427703119343927, 51.543163861525215 ] } },
{ "type": "Feature", "properties": { "visible_points": 3, "total_points": 47, "visibility_pct": 6.3829787234042552 }, "geometry": { "type": "Point", "coordinates": [ -2.427503313770409, 51.54316459007994 ] } },
{ "type": "Feature", "properties": { "visible_points": 9, "total_points": 55, "visibility_pct": 16.363636363636363 }, "geometry": { "type": "Point", "coordinates": [ -2.428403453855762, 51.54326920444695 ] } },
{ "type": "Feature", "properties": { "visible_points": 8, "total_points": 55, "visibility_pct": 14.545454545454545 }, "geometry": { "type": "Point", "coordinates": [ -2.428203647836755, 51.543269934196111 ] } },
{ "type": "Feature", "properties": { "visible_points": 7, "total_points": 55, "visibility_pct": 12.727272727272727 }, "geometry": { "type": "Point", "coordinates": [ -2.428003841809324, 51.543270663605036 ] } },
{ "type": "Feature", "properties": { "visible_points": 0, "total_points": 55, "visibility_pct": 0.0 }, "geometry": { "type": "Point", "coordinates": [ -2.42780403577347, 51.543271392673745 ] } },
{ "type": "Feature", "properties": { "visible_points": 2, "total_points": 52, "visibility_pct": 3.8461538461538463 }, "geometry": { "type": "Point", "coordinates": [ -2.427604229729192, 51.543272121402197 ] } },
{ "type": "Feature", "properties": { "visible_points": 0, "total_points": 51, "visibility_pct": 0.0 }, "geometry": { "type": "Point", "coordinates": [ -2.42850437217675, 51.543376734983553 ] } },
{ "type": "Feature", "properties": { "visible_points": 7, "total_points": 55, "visibility_pct": 12.727272727272727 }, "geometry": { "type": "Point", "coordinates": [ -2.428304565686991, 51.543377464906456 ] } },
{ "type": "Feature", "properties": { "visible_points": 7, "total_points": 55, "visibility_pct": 12.727272727272727 }, "geometry": { "type": "Point", "coordinates": [ -2.428104759188799, 51.543378194489144 ] } },
{ "type": "Feature", "properties": { "visible_points": 5, "total_points": 55, "visibility_pct": 9.0909090909090917 }, "geometry": { "type": "Point", "coordinates": [ -2.427904952682185, 51.543378923731581 ] } },
{ "type": "Feature", "properties": { "visible_points": 5, "total_points": 52, "visibility_pct": 9.6153846153846168 }, "geometry": { "type": "Point", "coordinates": [ -2.4284054840164, 51.543484995526121 ] } },
{ "type": "Feature", "properties": { "visible_points": 5, "total_points": 55, "visibility_pct": 9.0909090909090917 }, "geometry": { "type": "Point", "coordinates": [ -2.428205677047452, 51.543485725282537 ] } },
{ "type": "Feature", "properties": { "visible_points": 5, "total_points": 55, "visibility_pct": 9.0909090909090917 }, "geometry": { "type": "Point", "coordinates": [ -2.428005870070072, 51.54348645469873 ] } },
{ "type": "Feature", "properties": { "visible_points": 7, "total_points": 48, "visibility_pct": 14.583333333333334 }, "geometry": { "type": "Point", "coordinates": [ -2.428306595385281, 51.54359325598525 ] } },
{ "type": "Feature", "properties": { "visible_points": 7, "total_points": 51, "visibility_pct": 13.725490196078432 }, "geometry": { "type": "Point", "coordinates": [ -2.428106787937138, 51.543593985575171 ] } }
]
}
