{
"type": "FeatureCollection",
"name": "b8a119294688_visibility",
"crs": { "type": "name", "properties": { "name": "urn:ogc:def:crs:OGC:1.3:CRS84" } },
"features": [
{ "type": "Feature", "properties": { "visible_points": 3, "total_points": 41, "visibility_pct": 7.3170731707317067 }, "geometry": { "type": "Point", "coordinates": [ -2.522626378676325, 51.61984888501221 ] } },
{ "type": "Feature", "properties": { "visible_points": 1, "total_points": 39, "visibility_pct": 2.5641025641025639 }, "geometry": { "type": "Point", "coordinates": [ -2.522426239208055, 51.619849776031089 ] } },
{ "type": "Feature", "properties": { "visible_points": 3, "total_points": 46, "visibility_pct": 6.5217391304347823 }, "geometry": { "type": "Point", "coordinates": [ -2.5227276882153, 51.619956333446446 ] } },
{ "type": "Feature", "properties": { "visible_points": 3, "total_points": 45, "visibility_pct": 6.666666666666667 }, "geometry": { "type": "Point", "coordinates": [ -2.522527548279116, 51.619957224641325 ] } },
{ "type": "Feature", "properties": { "visible_points": 0, "total_points": 51, "visibility_pct": 0.0 }, "geometry": { "type": "Point", "coordinates": [ -2.522828998232439, 51.620063781787884 ] } },
{ "type": "Feature", "properties": { "visible_points": 4, "total_points": 50, "visibility_pct": 8.0 }, "geometry": { "type": "Point", "coordinates": [ -2.522628857828339, 51.620064673158801 ] } },
{ "type": "Feature", "properties": { "visible_points": 0, "total_points": 56, "visibility_pct": 0.0 }, "geometry": { "type": "Point", "coordinates": [ -2.522930308727754, 51.620171230036561 ] } },
{ "type": "Feature", "properties": { "visible_points": 4, "total_points": 55, "visibility_pct": 7.2727272727272725 }, "geometry": { "type": "Point", "coordinates": [ -2.52273016785574, 51.620172121583501 ] } },
{ "type": "Feature", "properties": { "visible_points": 0, "total_points": 57, "visibility_pct": 0.0 }, "geometry": { "type": "Point", "coordinates": [ -2.523031619701241, 51.620278678192449 ] } },
{ "type": "Feature", "properties": { "visible_points": 5, "total_points": 58, "visibility_pct": 8.6206896551724146 }, "geometry": { "type": "Point", "coordinates": [ -2.52283147836131, 51.620279569915418 ] } },
{ "type": "Feature", "properties": { "visible_points": 4, "total_points": 58, "visibility_pct": 6.8965517241379306 }, "geometry": { "type": "Point", "coordinates": [ -2.522631337011108, 51.620280461297234 ] } },
{ "type": "Feature", "properties": { "visible_points": 5, "total_points": 54, "visibility_pct": 9.2592592592592595 }, "geometry": { "type": "Point", "coordinates": [ -2.522932789345059, 51.620387018154581 ] } },
{ "type": "Feature", "properties": { "visible_points": 3, "total_points": 55, "visibility_pct": 5.4545454545454541 }, "geometry": { "type": "Point", "coordinates": [ -2.522732647526938, 51.620387909712427 ] } },
{ "type": "Feature", "properties": { "visible_points": 0, "total_points": 49, "visibility_pct": 0.0 }, "geometry": { "type": "Point", "coordinates": [ -2.523034100806988, 51.62049446630094 ] } },
{ "type": "Feature", "properties": { "visible_points": 4, "total_points": 50, "visibility_pct": 8.0 }, "geometry": { "type": "Point", "coordinates": [ -2.522833958520942, 51.620495358034823 ] } },
{ "type": "Feature", "properties": { "visible_points": 4, "total_points": 43, "visibility_pct": 9.3023255813953494 }, "geometry": { "type": "Point", "coordinates": [ -2.523135412747104, 51.62060191435453 ] } },
{ "type": "Feature", "properties": { "visible_points": 4, "total_points": 45, "visibility_pct": 8.8888888888888893 }, "geometry": { "type": "Point", "coordinates": [ -2.522935269993133, 51.620602806264451 ] } },
{ "type": "Feature", "properties": { "visible_points": 4, "total_points": 37, "visibility_pct": 10.810810810810811 }, "geometry": { "type": "Point", "coordinates": [ -2.523236725165407, 51.620709362315353 ] } },
{ "type": "Feature", "properties": { "visible_points": 3, "total_points": 39, "visibility_pct": 7.6923076923076925 }, "geometry": { "type": "Point", "coordinates": [ -2.523036581943509, 51.620710254401288 ] } },
{ "type": "Feature", "properties": { "visible_points": 4, "total_points": 33, "visibility_pct": 12.121212121212121 }, "geometry": { "type": "Point", "coordinates": [ -2.523137894372076, 51.620817702445358 ] } }
]
}
