{
"type": "FeatureCollection",
"name": "bea63394e019_visibility",
"crs": { "type": "name", "properties": { "name": "urn:ogc:def:crs:OGC:1.3:CRS84" } },
"features": [
{ "type": "Feature", "properties": { "visible_points": 0, "total_points": 51, "visibility_pct": 0.0 }, "geometry": { "type": "Point", "coordinates": [ -2.384635057425422, 51.562701634375756 ] } },
{ "type": "Feature", "properties": { "visible_points": 0, "total_points": 55, "visibility_pct": 0.0 }, "geometry": { "type": "Point", "coordinates": [ -2.384435164968946, 51.562702289753574 ] } },
{ "type": "Feature", "properties": { "visible_points": 0, "total_points": 56, "visibility_pct": 0.0 }, "geometry": { "type": "Point", "coordinates": [ -2.384235272505315, 51.56270294478967 ] } },
{ "type": "Feature", "properties": { "visible_points": 0, "total_points": 56, "visibility_pct": 0.0 }, "geometry": { "type": "Point", "coordinates": [ -2.384035380034168, 51.562703599485246 ] } },
{ "type": "Feature", "properties": { "visible_points": 0, "total_points": 52, "visibility_pct": 0.0 }, "geometry": { "type": "Point", "coordinates": [ -2.383835487555516, 51.562704253840316 ] } },
{ "type": "Feature", "properties": { "visible_points": 0, "total_points": 45, "visibility_pct": 0.0 }, "geometry": { "type": "Point", "coordinates": [ -2.383635595069352, 51.562704907854879 ] } },
{ "type": "Feature", "properties": { "visible_points": 0, "total_points": 48, "visibility_pct": 0.0 }, "geometry": { "type": "Point", "coordinates": [ -2.384735914646782, 51.562809203594327 ] } },
{ "type": "Feature", "properties": { "visible_points": 0, "total_points": 55, "visibility_pct": 0.0 }, "geometry": { "type": "Point", "coordinates": [ -2.384536021723004, 51.562809859148182 ] } },
{ "type": "Feature", "properties": { "visible_points": 0, "total_points": 56, "visibility_pct": 0.0 }, "geometry": { "type": "Point", "coordinates": [ -2.384336128791998, 51.562810514355064 ] } },
{ "type": "Feature", "properties": { "visible_points": 0, "total_points": 56, "visibility_pct": 0.0 }, "geometry": { "type": "Point", "coordinates": [ -2.384136235853481, 51.56281116922144 ] } },
{ "type": "Feature", "properties": { "visible_points": 0, "total_points": 56, "visibility_pct": 0.0 }, "geometry": { "type": "Point", "coordinates": [ -2.383936342907454, 51.562811823747289 ] } },
{ "type": "Feature", "properties": { "visible_points": 0, "total_points": 49, "visibility_pct": 0.0 }, "geometry": { "type": "Point", "coordinates": [ -2.383736449953914, 51.562812477932624 ] } },
{ "type": "Feature", "properties": { "visible_points": 0, "total_points": 44, "visibility_pct": 0.0 }, "geometry": { "type": "Point", "coordinates": [ -2.384836772341698, 51.562916772721543 ] } },
{ "type": "Feature", "properties": { "visible_points": 0, "total_points": 51, "visibility_pct": 0.0 }, "geometry": { "type": "Point", "coordinates": [ -2.384636878951762, 51.562917428453908 ] } },
{ "type": "Feature", "properties": { "visible_points": 0, "total_points": 56, "visibility_pct": 0.0 }, "geometry": { "type": "Point", "coordinates": [ -2.384436985553561, 51.562918083832834 ] } },
{ "type": "Feature", "properties": { "visible_points": 1, "total_points": 56, "visibility_pct": 1.7857142857142856 }, "geometry": { "type": "Point", "coordinates": [ -2.38423709214767, 51.562918738869996 ] } },
{ "type": "Feature", "properties": { "visible_points": 0, "total_points": 56, "visibility_pct": 0.0 }, "geometry": { "type": "Point", "coordinates": [ -2.384037198734263, 51.562919393566631 ] } },
{ "type": "Feature", "properties": { "visible_points": 0, "total_points": 52, "visibility_pct": 0.0 }, "geometry": { "type": "Point", "coordinates": [ -2.383837305313348, 51.562920047922745 ] } },
{ "type": "Feature", "properties": { "visible_points": 1, "total_points": 45, "visibility_pct": 2.2222222222222223 }, "geometry": { "type": "Point", "coordinates": [ -2.383637411884928, 51.562920701938353 ] } },
{ "type": "Feature", "properties": { "visible_points": 0, "total_points": 53, "visibility_pct": 0.0 }, "geometry": { "type": "Point", "coordinates": [ -2.383938161147659, 51.56302761782522 ] } },
{ "type": "Feature", "properties": { "visible_points": 0, "total_points": 47, "visibility_pct": 0.0 }, "geometry": { "type": "Point", "coordinates": [ -2.383738267251858, 51.563028272011621 ] } }
]
}
