{
"type": "FeatureCollection",
"name": "c65fb9ae54ed_visibility",
"crs": { "type": "name", "properties": { "name": "urn:ogc:def:crs:OGC:1.3:CRS84" } },
"features": [
{ "type": "Feature", "properties": { "visible_points": 0, "total_points": 52, "visibility_pct": 0.0 }, "geometry": { "type": "Point", "coordinates": [ -2.413643574335409, 51.542383821238978 ] } },
{ "type": "Feature", "properties": { "visible_points": 5, "total_points": 49, "visibility_pct": 10.204081632653061 }, "geometry": { "type": "Point", "coordinates": [ -2.413443772611672, 51.542384525599196 ] } },
{ "type": "Feature", "properties": { "visible_points": 0, "total_points": 54, "visibility_pct": 0.0 }, "geometry": { "type": "Point", "coordinates": [ -2.413944257480563, 51.542490659878844 ] } },
{ "type": "Feature", "properties": { "visible_points": 0, "total_points": 54, "visibility_pct": 0.0 }, "geometry": { "type": "Point", "coordinates": [ -2.413744455289695, 51.542491364752912 ] } },
{ "type": "Feature", "properties": { "visible_points": 7, "total_points": 53, "visibility_pct": 13.20754716981132 }, "geometry": { "type": "Point", "coordinates": [ -2.413544653090626, 51.542492069286759 ] } },
{ "type": "Feature", "properties": { "visible_points": 0, "total_points": 54, "visibility_pct": 0.0 }, "geometry": { "type": "Point", "coordinates": [ -2.414045139393705, 51.542598203128534 ] } },
{ "type": "Feature", "properties": { "visible_points": 6, "total_points": 54, "visibility_pct": 11.111111111111111 }, "geometry": { "type": "Point", "coordinates": [ -2.413845336727503, 51.542598908176245 ] } },
{ "type": "Feature", "properties": { "visible_points": 5, "total_points": 54, "visibility_pct": 9.2592592592592595 }, "geometry": { "type": "Point", "coordinates": [ -2.413645534053099, 51.542599612883706 ] } },
{ "type": "Feature", "properties": { "visible_points": 5, "total_points": 53, "visibility_pct": 9.433962264150944 }, "geometry": { "type": "Point", "coordinates": [ -2.413445731370495, 51.542600317250994 ] } },
{ "type": "Feature", "properties": { "visible_points": 0, "total_points": 52, "visibility_pct": 0.0 }, "geometry": { "type": "Point", "coordinates": [ -2.414146021790375, 51.542705746287609 ] } },
{ "type": "Feature", "properties": { "visible_points": 6, "total_points": 54, "visibility_pct": 11.111111111111111 }, "geometry": { "type": "Point", "coordinates": [ -2.413946218648841, 51.54270645150897 ] } },
{ "type": "Feature", "properties": { "visible_points": 7, "total_points": 54, "visibility_pct": 12.962962962962962 }, "geometry": { "type": "Point", "coordinates": [ -2.413746415499098, 51.542707156390108 ] } },
{ "type": "Feature", "properties": { "visible_points": 4, "total_points": 54, "visibility_pct": 7.4074074074074066 }, "geometry": { "type": "Point", "coordinates": [ -2.413546612341156, 51.542707860931003 ] } },
{ "type": "Feature", "properties": { "visible_points": 0, "total_points": 53, "visibility_pct": 0.0 }, "geometry": { "type": "Point", "coordinates": [ -2.413346809175019, 51.542708565131676 ] } },
{ "type": "Feature", "properties": { "visible_points": 5, "total_points": 51, "visibility_pct": 9.8039215686274517 }, "geometry": { "type": "Point", "coordinates": [ -2.414047101053703, 51.5428139947511 ] } },
{ "type": "Feature", "properties": { "visible_points": 6, "total_points": 53, "visibility_pct": 11.320754716981133 }, "geometry": { "type": "Point", "coordinates": [ -2.413847297428626, 51.542814699805874 ] } },
{ "type": "Feature", "properties": { "visible_points": 0, "total_points": 54, "visibility_pct": 0.0 }, "geometry": { "type": "Point", "coordinates": [ -2.413647493795342, 51.542815404520425 ] } },
{ "type": "Feature", "properties": { "visible_points": 4, "total_points": 54, "visibility_pct": 7.4074074074074066 }, "geometry": { "type": "Point", "coordinates": [ -2.413447690153859, 51.542816108894733 ] } },
{ "type": "Feature", "properties": { "visible_points": 5, "total_points": 46, "visibility_pct": 10.869565217391305 }, "geometry": { "type": "Point", "coordinates": [ -2.414147983942107, 51.542921537902643 ] } },
{ "type": "Feature", "properties": { "visible_points": 0, "total_points": 49, "visibility_pct": 0.0 }, "geometry": { "type": "Point", "coordinates": [ -2.413948179841686, 51.542922243131066 ] } },
{ "type": "Feature", "properties": { "visible_points": 0, "total_points": 50, "visibility_pct": 0.0 }, "geometry": { "type": "Point", "coordinates": [ -2.413748375733062, 51.542922948019239 ] } }
]
}
