{
"type": "FeatureCollection",
"name": "CORNW_766",
"crs": { "type": "name", "properties": { "name": "urn:ogc:def:crs:OGC:1.3:CRS84" } },
"features": [
{ "type": "Feature", "properties": { "osm_id": 11920090410, "name": null, "amenity": "bench", "man_made": null, "leisure": null, "playground": null, "memorial": null }, "geometry": { "type": "Point", "coordinates": [ -4.7886142, 50.3387588 ] } },
{ "type": "Feature", "properties": { "osm_id": 12686564610, "name": null, "amenity": "bench", "man_made": null, "leisure": null, "playground": null, "memorial": null }, "geometry": { "type": "Point", "coordinates": [ -4.7881616, 50.3388967 ] } },
{ "type": "Feature", "properties": { "osm_id": 7824724123, "name": null, "amenity": "bench", "man_made": null, "leisure": null, "playground": null, "memorial": null }, "geometry": { "type": "Point", "coordinates": [ -4.7884715, 50.338902 ] } },
{ "type": "Feature", "properties": { "osm_id": 7824724125, "name": null, "amenity": "bench", "man_made": null, "leisure": null, "playground": null, "memorial": null }, "geometry": { "type": "Point", "coordinates": [ -4.7886439, 50.3389738 ] } },
{ "type": "Feature", "properties": { "osm_id": 7824724133, "name": null, "amenity": "bench", "man_made": null, "leisure": null, "playground": null, "memorial": null }, "geometry": { "type": "Point", "coordinates": [ -4.7878705, 50.3389994 ] } }
]
}
