{
"type": "FeatureCollection",
"name": "CORNW_1260",
"crs": { "type": "name", "properties": { "name": "urn:ogc:def:crs:OGC:1.3:CRS84" } },
"features": [
{ "type": "Feature", "properties": { "osm_id": 12449944643, "name": null, "amenity": "bench", "man_made": null, "leisure": null, "playground": null, "memorial": null }, "geometry": { "type": "Point", "coordinates": [ -5.4941981, 50.2049397 ] } },
{ "type": "Feature", "properties": { "osm_id": 12449944644, "name": null, "amenity": "bench", "man_made": null, "leisure": null, "playground": null, "memorial": null }, "geometry": { "type": "Point", "coordinates": [ -5.4954761, 50.205329 ] } },
{ "type": "Feature", "properties": { "osm_id": 12449944645, "name": null, "amenity": "bench", "man_made": null, "leisure": null, "playground": null, "memorial": null }, "geometry": { "type": "Point", "coordinates": [ -5.4941873, 50.2054006 ] } },
{ "type": "Feature", "properties": { "osm_id": 12449944646, "name": null, "amenity": "bench", "man_made": null, "leisure": null, "playground": null, "memorial": null }, "geometry": { "type": "Point", "coordinates": [ -5.4944113, 50.2054032 ] } },
{ "type": "Feature", "properties": { "osm_id": 12449944647, "name": null, "amenity": "bench", "man_made": null, "leisure": null, "playground": null, "memorial": null }, "geometry": { "type": "Point", "coordinates": [ -5.4948284, 50.2055603 ] } }
]
}
