{
"type": "FeatureCollection",
"name": "CORNW_112",
"crs": { "type": "name", "properties": { "name": "urn:ogc:def:crs:OGC:1.3:CRS84" } },
"features": [
{ "type": "Feature", "properties": { "osm_id": 6363204981, "name": null, "amenity": "bench", "man_made": null, "leisure": null, "playground": null, "memorial": null }, "geometry": { "type": "Point", "coordinates": [ -5.0690357, 50.1442607 ] } },
{ "type": "Feature", "properties": { "osm_id": 6363204982, "name": null, "amenity": "bench", "man_made": null, "leisure": null, "playground": null, "memorial": null }, "geometry": { "type": "Point", "coordinates": [ -5.068909, 50.1444244 ] } },
{ "type": "Feature", "properties": { "osm_id": 6363204983, "name": null, "amenity": "bench", "man_made": null, "leisure": null, "playground": null, "memorial": null }, "geometry": { "type": "Point", "coordinates": [ -5.0688487, 50.1444841 ] } },
{ "type": "Feature", "properties": { "osm_id": 6363204984, "name": null, "amenity": "bench", "man_made": null, "leisure": null, "playground": null, "memorial": null }, "geometry": { "type": "Point", "coordinates": [ -5.0687984, 50.1445323 ] } },
{ "type": "Feature", "properties": { "osm_id": 6363205085, "name": null, "amenity": "bench", "man_made": null, "leisure": null, "playground": null, "memorial": null }, "geometry": { "type": "Point", "coordinates": [ -5.068742, 50.1445899 ] } },
{ "type": "Feature", "properties": { "osm_id": 13256656078, "name": null, "amenity": "bench", "man_made": null, "leisure": null, "playground": null, "memorial": null }, "geometry": { "type": "Point", "coordinates": [ -5.0690928, 50.1450177 ] } },
{ "type": "Feature", "properties": { "osm_id": 13256656077, "name": null, "amenity": "bench", "man_made": null, "leisure": null, "playground": null, "memorial": null }, "geometry": { "type": "Point", "coordinates": [ -5.0690643, 50.1450297 ] } },
{ "type": "Feature", "properties": { "osm_id": 13256656076, "name": null, "amenity": "bench", "man_made": null, "leisure": null, "playground": null, "memorial": null }, "geometry": { "type": "Point", "coordinates": [ -5.0690225, 50.1450485 ] } }
]
}
