{
"type": "FeatureCollection",
"name": "CORNW_184",
"crs": { "type": "name", "properties": { "name": "urn:ogc:def:crs:OGC:1.3:CRS84" } },
"features": [
{ "type": "Feature", "properties": { "osm_id": 11267639129, "name": null, "amenity": "bench", "man_made": null, "leisure": null, "playground": null, "memorial": null }, "geometry": { "type": "Point", "coordinates": [ -4.4534735, 50.4530162 ] } },
{ "type": "Feature", "properties": { "osm_id": 11267639131, "name": null, "amenity": "bench", "man_made": null, "leisure": null, "playground": null, "memorial": null }, "geometry": { "type": "Point", "coordinates": [ -4.4538443, 50.4533663 ] } },
{ "type": "Feature", "properties": { "osm_id": 11267639130, "name": null, "amenity": "bench", "man_made": null, "leisure": null, "playground": null, "memorial": null }, "geometry": { "type": "Point", "coordinates": [ -4.4534862, 50.4533692 ] } }
]
}
