{
"type": "FeatureCollection",
"name": "CORNW_225",
"crs": { "type": "name", "properties": { "name": "urn:ogc:def:crs:OGC:1.3:CRS84" } },
"features": [
{ "type": "Feature", "properties": { "osm_id": 3733771964, "name": null, "amenity": null, "man_made": null, "leisure": "picnic_table", "playground": null, "memorial": null }, "geometry": { "type": "Point", "coordinates": [ -5.1846847, 50.2369978 ] } },
{ "type": "Feature", "properties": { "osm_id": 3733771966, "name": null, "amenity": null, "man_made": null, "leisure": "picnic_table", "playground": null, "memorial": null }, "geometry": { "type": "Point", "coordinates": [ -5.18469, 50.2370406 ] } }
]
}
