{
"type": "FeatureCollection",
"name": "CORNW_112",
"crs": { "type": "name", "properties": { "name": "urn:ogc:def:crs:OGC:1.3:CRS84" } },
"features": [
{ "type": "Feature", "properties": { "osm_id": 13256656078, "name": null, "amenity": "bench", "man_made": null, "leisure": null, "playground": null, "memorial": null }, "geometry": { "type": "Point", "coordinates": [ -5.0690928, 50.1450177 ] } },
{ "type": "Feature", "properties": { "osm_id": 13256656077, "name": null, "amenity": "bench", "man_made": null, "leisure": null, "playground": null, "memorial": null }, "geometry": { "type": "Point", "coordinates": [ -5.0690643, 50.1450297 ] } },
{ "type": "Feature", "properties": { "osm_id": 13256656076, "name": null, "amenity": "bench", "man_made": null, "leisure": null, "playground": null, "memorial": null }, "geometry": { "type": "Point", "coordinates": [ -5.0690225, 50.1450485 ] } }
]
}
