{
"type": "FeatureCollection",
"name": "CORNW_140",
"crs": { "type": "name", "properties": { "name": "urn:ogc:def:crs:OGC:1.3:CRS84" } },
"features": [
{ "type": "Feature", "properties": { "osm_id": 12369540232, "name": null, "amenity": "bench", "man_made": null, "leisure": null, "playground": null, "memorial": null }, "geometry": { "type": "Point", "coordinates": [ -4.3582533, 50.6313273 ] } },
{ "type": "Feature", "properties": { "osm_id": 12369455056, "name": null, "amenity": "bench", "man_made": null, "leisure": null, "playground": null, "memorial": null }, "geometry": { "type": "Point", "coordinates": [ -4.3578954, 50.6313415 ] } },
{ "type": "Feature", "properties": { "osm_id": 13326664053, "name": null, "amenity": "bench", "man_made": null, "leisure": null, "playground": null, "memorial": null }, "geometry": { "type": "Point", "coordinates": [ -4.3576608, 50.6313498 ] } },
{ "type": "Feature", "properties": { "osm_id": 12365328118, "name": null, "amenity": "bench", "man_made": null, "leisure": null, "playground": null, "memorial": null }, "geometry": { "type": "Point", "coordinates": [ -4.3573986, 50.6320672 ] } },
{ "type": "Feature", "properties": { "osm_id": 12365328119, "name": null, "amenity": "bench", "man_made": null, "leisure": null, "playground": null, "memorial": null }, "geometry": { "type": "Point", "coordinates": [ -4.3571485, 50.6320948 ] } },
{ "type": "Feature", "properties": { "osm_id": 12365328116, "name": null, "amenity": "bench", "man_made": null, "leisure": null, "playground": null, "memorial": null }, "geometry": { "type": "Point", "coordinates": [ -4.3585218, 50.6321858 ] } },
{ "type": "Feature", "properties": { "osm_id": 12365328117, "name": null, "amenity": "bench", "man_made": null, "leisure": null, "playground": null, "memorial": null }, "geometry": { "type": "Point", "coordinates": [ -4.3583272, 50.6322367 ] } },
{ "type": "Feature", "properties": { "osm_id": 12365328120, "name": null, "amenity": "bench", "man_made": null, "leisure": null, "playground": null, "memorial": null }, "geometry": { "type": "Point", "coordinates": [ -4.3575428, 50.6325182 ] } },
{ "type": "Feature", "properties": { "osm_id": 12365328121, "name": null, "amenity": "bench", "man_made": null, "leisure": null, "playground": null, "memorial": null }, "geometry": { "type": "Point", "coordinates": [ -4.3577408, 50.6325658 ] } },
{ "type": "Feature", "properties": { "osm_id": 12365328122, "name": null, "amenity": "bench", "man_made": null, "leisure": null, "playground": null, "memorial": null }, "geometry": { "type": "Point", "coordinates": [ -4.3579278, 50.6326156 ] } },
{ "type": "Feature", "properties": { "osm_id": 12365328115, "name": null, "amenity": "bench", "man_made": null, "leisure": null, "playground": null, "memorial": null }, "geometry": { "type": "Point", "coordinates": [ -4.3581346, 50.6332358 ] } }
]
}
