{
"type": "FeatureCollection",
"name": "CORNW_72",
"crs": { "type": "name", "properties": { "name": "urn:ogc:def:crs:OGC:1.3:CRS84" } },
"features": [
{ "type": "Feature", "properties": { "osm_id": 10935378917, "name": null, "amenity": "bench", "man_made": null, "leisure": null, "playground": null, "memorial": null }, "geometry": { "type": "Point", "coordinates": [ -5.3176516, 50.0851848 ] } },
{ "type": "Feature", "properties": { "osm_id": 8426554691, "name": null, "amenity": "bench", "man_made": null, "leisure": null, "playground": null, "memorial": null }, "geometry": { "type": "Point", "coordinates": [ -5.31746, 50.0853005 ] } },
{ "type": "Feature", "properties": { "osm_id": 8426554690, "name": null, "amenity": "bench", "man_made": null, "leisure": null, "playground": null, "memorial": null }, "geometry": { "type": "Point", "coordinates": [ -5.3173161, 50.0853029 ] } },
{ "type": "Feature", "properties": { "osm_id": 10935378920, "name": null, "amenity": "bench", "man_made": null, "leisure": null, "playground": null, "memorial": null }, "geometry": { "type": "Point", "coordinates": [ -5.31663, 50.085304 ] } },
{ "type": "Feature", "properties": { "osm_id": 8426554688, "name": null, "amenity": "bench", "man_made": null, "leisure": null, "playground": null, "memorial": null }, "geometry": { "type": "Point", "coordinates": [ -5.3170298, 50.0853062 ] } },
{ "type": "Feature", "properties": { "osm_id": 8426554689, "name": null, "amenity": "bench", "man_made": null, "leisure": null, "playground": null, "memorial": null }, "geometry": { "type": "Point", "coordinates": [ -5.3171764, 50.0853063 ] } },
{ "type": "Feature", "properties": { "osm_id": 888603341, "name": null, "amenity": "bench", "man_made": null, "leisure": null, "playground": null, "memorial": null }, "geometry": { "type": "Point", "coordinates": [ -5.3168923, 50.0853066 ] } },
{ "type": "Feature", "properties": { "osm_id": 8426554692, "name": null, "amenity": "bench", "man_made": null, "leisure": null, "playground": null, "memorial": null }, "geometry": { "type": "Point", "coordinates": [ -5.3168205, 50.0853066 ] } }
]
}
