{
"type": "FeatureCollection",
"name": "SOMER_1107",
"crs": { "type": "name", "properties": { "name": "urn:ogc:def:crs:OGC:1.3:CRS84" } },
"features": [
{ "type": "Feature", "properties": { "osm_id": 11916867599, "name": null, "amenity": "bench", "man_made": null, "leisure": null, "playground": null, "memorial": null }, "geometry": { "type": "Point", "coordinates": [ -2.9990912, 51.2409096 ] } },
{ "type": "Feature", "properties": { "osm_id": 11916867598, "name": null, "amenity": "bench", "man_made": null, "leisure": null, "playground": null, "memorial": null }, "geometry": { "type": "Point", "coordinates": [ -2.9991234, 51.2409253 ] } }
]
}
