{
"type": "FeatureCollection",
"name": "c8c894e27db2_visibility",
"crs": { "type": "name", "properties": { "name": "urn:ogc:def:crs:OGC:1.3:CRS84" } },
"features": [
{ "type": "Feature", "properties": { "visible_points": 2, "total_points": 50, "visibility_pct": 4.0 }, "geometry": { "type": "Point", "coordinates": [ -3.491533737755974, 50.696588521427202 ] } },
{ "type": "Feature", "properties": { "visible_points": 0, "total_points": 48, "visibility_pct": 0.0 }, "geometry": { "type": "Point", "coordinates": [ -3.491337612674032, 50.696591029144756 ] } },
{ "type": "Feature", "properties": { "visible_points": 5, "total_points": 44, "visibility_pct": 11.363636363636363 }, "geometry": { "type": "Point", "coordinates": [ -3.491141487563026, 50.696593536531147 ] } },
{ "type": "Feature", "properties": { "visible_points": 2, "total_points": 50, "visibility_pct": 4.0 }, "geometry": { "type": "Point", "coordinates": [ -3.491831349501086, 50.696692636878673 ] } },
{ "type": "Feature", "properties": { "visible_points": 0, "total_points": 50, "visibility_pct": 0.0 }, "geometry": { "type": "Point", "coordinates": [ -3.491635223989283, 50.696695145074941 ] } },
{ "type": "Feature", "properties": { "visible_points": 0, "total_points": 50, "visibility_pct": 0.0 }, "geometry": { "type": "Point", "coordinates": [ -3.491439098448408, 50.696697652940031 ] } },
{ "type": "Feature", "properties": { "visible_points": 0, "total_points": 48, "visibility_pct": 0.0 }, "geometry": { "type": "Point", "coordinates": [ -3.491242972878468, 50.696700160473945 ] } },
{ "type": "Feature", "properties": { "visible_points": 5, "total_points": 43, "visibility_pct": 11.627906976744185 }, "geometry": { "type": "Point", "coordinates": [ -3.491046847279466, 50.696702667676675 ] } },
{ "type": "Feature", "properties": { "visible_points": 2, "total_points": 44, "visibility_pct": 4.5454545454545459 }, "geometry": { "type": "Point", "coordinates": [ -3.492128962622977, 50.696796751637976 ] } },
{ "type": "Feature", "properties": { "visible_points": 1, "total_points": 50, "visibility_pct": 2.0 }, "geometry": { "type": "Point", "coordinates": [ -3.491932836681319, 50.696799260312943 ] } },
{ "type": "Feature", "properties": { "visible_points": 2, "total_points": 50, "visibility_pct": 4.0 }, "geometry": { "type": "Point", "coordinates": [ -3.49173671071058, 50.696801768656712 ] } },
{ "type": "Feature", "properties": { "visible_points": 0, "total_points": 50, "visibility_pct": 0.0 }, "geometry": { "type": "Point", "coordinates": [ -3.491540584710773, 50.696804276669333 ] } },
{ "type": "Feature", "properties": { "visible_points": 2, "total_points": 50, "visibility_pct": 4.0 }, "geometry": { "type": "Point", "coordinates": [ -3.491344458681896, 50.696806784350791 ] } },
{ "type": "Feature", "properties": { "visible_points": 3, "total_points": 47, "visibility_pct": 6.3829787234042552 }, "geometry": { "type": "Point", "coordinates": [ -3.491148332623958, 50.696809291701072 ] } },
{ "type": "Feature", "properties": { "visible_points": 4, "total_points": 45, "visibility_pct": 8.8888888888888893 }, "geometry": { "type": "Point", "coordinates": [ -3.492034324349548, 50.696905883681247 ] } },
{ "type": "Feature", "properties": { "visible_points": 0, "total_points": 50, "visibility_pct": 0.0 }, "geometry": { "type": "Point", "coordinates": [ -3.491838197919875, 50.696908392172567 ] } },
{ "type": "Feature", "properties": { "visible_points": 2, "total_points": 50, "visibility_pct": 4.0 }, "geometry": { "type": "Point", "coordinates": [ -3.491642071461131, 50.696910900332718 ] } },
{ "type": "Feature", "properties": { "visible_points": 3, "total_points": 50, "visibility_pct": 6.0 }, "geometry": { "type": "Point", "coordinates": [ -3.491445944973322, 50.696913408161706 ] } },
{ "type": "Feature", "properties": { "visible_points": 4, "total_points": 45, "visibility_pct": 8.8888888888888893 }, "geometry": { "type": "Point", "coordinates": [ -3.491939685617169, 50.69701501562249 ] } },
{ "type": "Feature", "properties": { "visible_points": 5, "total_points": 49, "visibility_pct": 10.204081632653061 }, "geometry": { "type": "Point", "coordinates": [ -3.49174355869949, 50.697017523930171 ] } }
]
}
