{
"type": "FeatureCollection",
"name": "cd827ef5fbde_visibility",
"crs": { "type": "name", "properties": { "name": "urn:ogc:def:crs:OGC:1.3:CRS84" } },
"features": [
{ "type": "Feature", "properties": { "visible_points": 0, "total_points": 45, "visibility_pct": 0.0 }, "geometry": { "type": "Point", "coordinates": [ -3.529761446043852, 50.740053237108668 ] } },
{ "type": "Feature", "properties": { "visible_points": 0, "total_points": 44, "visibility_pct": 0.0 }, "geometry": { "type": "Point", "coordinates": [ -3.529565144418558, 50.740055812656223 ] } },
{ "type": "Feature", "properties": { "visible_points": 1, "total_points": 51, "visibility_pct": 1.9607843137254901 }, "geometry": { "type": "Point", "coordinates": [ -3.52986311277757, 50.740159825455912 ] } },
{ "type": "Feature", "properties": { "visible_points": 2, "total_points": 50, "visibility_pct": 4.0 }, "geometry": { "type": "Point", "coordinates": [ -3.529666810716473, 50.740162401179248 ] } },
{ "type": "Feature", "properties": { "visible_points": 0, "total_points": 48, "visibility_pct": 0.0 }, "geometry": { "type": "Point", "coordinates": [ -3.529470508626662, 50.740164976572238 ] } },
{ "type": "Feature", "properties": { "visible_points": 3, "total_points": 55, "visibility_pct": 5.4545454545454541 }, "geometry": { "type": "Point", "coordinates": [ -3.529768477478893, 50.740268989606889 ] } },
{ "type": "Feature", "properties": { "visible_points": 0, "total_points": 54, "visibility_pct": 0.0 }, "geometry": { "type": "Point", "coordinates": [ -3.529572174953279, 50.74027156517564 ] } },
{ "type": "Feature", "properties": { "visible_points": 3, "total_points": 60, "visibility_pct": 5.0 }, "geometry": { "type": "Point", "coordinates": [ -3.529870144705829, 50.740375577939119 ] } },
{ "type": "Feature", "properties": { "visible_points": 3, "total_points": 59, "visibility_pct": 5.0847457627118651 }, "geometry": { "type": "Point", "coordinates": [ -3.529673841744401, 50.740378153683643 ] } },
{ "type": "Feature", "properties": { "visible_points": 4, "total_points": 57, "visibility_pct": 7.0175438596491224 }, "geometry": { "type": "Point", "coordinates": [ -3.529477538754265, 50.740380729097808 ] } },
{ "type": "Feature", "properties": { "visible_points": 2, "total_points": 62, "visibility_pct": 3.225806451612903 }, "geometry": { "type": "Point", "coordinates": [ -3.529971812397279, 50.740482166175994 ] } },
{ "type": "Feature", "properties": { "visible_points": 1, "total_points": 63, "visibility_pct": 1.5873015873015872 }, "geometry": { "type": "Point", "coordinates": [ -3.529775509000043, 50.740484742096278 ] } },
{ "type": "Feature", "properties": { "visible_points": 1, "total_points": 62, "visibility_pct": 1.6129032258064515 }, "geometry": { "type": "Point", "coordinates": [ -3.529579205574093, 50.74048731768621 ] } },
{ "type": "Feature", "properties": { "visible_points": 2, "total_points": 57, "visibility_pct": 3.5087719298245612 }, "geometry": { "type": "Point", "coordinates": [ -3.530073480553257, 50.740588754317457 ] } },
{ "type": "Feature", "properties": { "visible_points": 0, "total_points": 58, "visibility_pct": 0.0 }, "geometry": { "type": "Point", "coordinates": [ -3.529877176720202, 50.740591330413515 ] } },
{ "type": "Feature", "properties": { "visible_points": 0, "total_points": 59, "visibility_pct": 0.0 }, "geometry": { "type": "Point", "coordinates": [ -3.529680872858437, 50.740593906179214 ] } },
{ "type": "Feature", "properties": { "visible_points": 2, "total_points": 53, "visibility_pct": 3.7735849056603774 }, "geometry": { "type": "Point", "coordinates": [ -3.529978844904884, 50.740697918635391 ] } },
{ "type": "Feature", "properties": { "visible_points": 0, "total_points": 54, "visibility_pct": 0.0 }, "geometry": { "type": "Point", "coordinates": [ -3.529782540607302, 50.740700494576842 ] } },
{ "type": "Feature", "properties": { "visible_points": 2, "total_points": 47, "visibility_pct": 4.2553191489361701 }, "geometry": { "type": "Point", "coordinates": [ -3.530080513554096, 50.740804506761862 ] } },
{ "type": "Feature", "properties": { "visible_points": 0, "total_points": 48, "visibility_pct": 0.0 }, "geometry": { "type": "Point", "coordinates": [ -3.529884208820692, 50.74080708287908 ] } },
{ "type": "Feature", "properties": { "visible_points": 0, "total_points": 41, "visibility_pct": 0.0 }, "geometry": { "type": "Point", "coordinates": [ -3.530182182667839, 50.740911094792935 ] } },
{ "type": "Feature", "properties": { "visible_points": 0, "total_points": 43, "visibility_pct": 0.0 }, "geometry": { "type": "Point", "coordinates": [ -3.529985877498615, 50.740913671085941 ] } },
{ "type": "Feature", "properties": { "visible_points": 0, "total_points": 37, "visibility_pct": 0.0 }, "geometry": { "type": "Point", "coordinates": [ -3.530087546641068, 50.741020259197406 ] } }
]
}
