{
"type": "FeatureCollection",
"name": "BOUCH_2",
"crs": { "type": "name", "properties": { "name": "urn:ogc:def:crs:OGC:1.3:CRS84" } },
"features": [
{ "type": "Feature", "properties": { "osm_id": 10103490082, "name": null, "amenity": "bench", "man_made": null, "leisure": null, "playground": null, "memorial": null }, "geometry": { "type": "Point", "coordinates": [ -1.8988259, 50.7131195 ] } },
{ "type": "Feature", "properties": { "osm_id": 10103490081, "name": null, "amenity": "bench", "man_made": null, "leisure": null, "playground": null, "memorial": null }, "geometry": { "type": "Point", "coordinates": [ -1.8999189, 50.7138527 ] } },
{ "type": "Feature", "properties": { "osm_id": 10103490084, "name": null, "amenity": "bench", "man_made": null, "leisure": null, "playground": null, "memorial": null }, "geometry": { "type": "Point", "coordinates": [ -1.8975214, 50.7123538 ] } },
{ "type": "Feature", "properties": { "osm_id": 10103490083, "name": null, "amenity": "bench", "man_made": null, "leisure": null, "playground": null, "memorial": null }, "geometry": { "type": "Point", "coordinates": [ -1.8976602, 50.7123984 ] } },
{ "type": "Feature", "properties": { "osm_id": 10103490080, "name": null, "amenity": "bench", "man_made": null, "leisure": null, "playground": null, "memorial": null }, "geometry": { "type": "Point", "coordinates": [ -1.9006165, 50.7145652 ] } },
{ "type": "Feature", "properties": { "osm_id": 10103490079, "name": null, "amenity": "bench", "man_made": null, "leisure": null, "playground": null, "memorial": null }, "geometry": { "type": "Point", "coordinates": [ -1.9017456, 50.716407 ] } },
{ "type": "Feature", "properties": { "osm_id": 10103490078, "name": null, "amenity": "bench", "man_made": null, "leisure": null, "playground": null, "memorial": null }, "geometry": { "type": "Point", "coordinates": [ -1.9020097, 50.7171377 ] } }
]
}
