{
"type": "FeatureCollection",
"name": "BOUCH_38",
"crs": { "type": "name", "properties": { "name": "urn:ogc:def:crs:OGC:1.3:CRS84" } },
"features": [
{ "type": "Feature", "properties": { "osm_id": 13806206568, "name": null, "amenity": "bench", "man_made": null, "leisure": null, "playground": null, "memorial": null }, "geometry": { "type": "Point", "coordinates": [ -1.8784118, 50.7464908 ] } },
{ "type": "Feature", "properties": { "osm_id": 13367058981, "name": null, "amenity": "bench", "man_made": null, "leisure": null, "playground": null, "memorial": null }, "geometry": { "type": "Point", "coordinates": [ -1.8781838, 50.7464972 ] } },
{ "type": "Feature", "properties": { "osm_id": 13806210008, "name": null, "amenity": "bench", "man_made": null, "leisure": null, "playground": null, "memorial": null }, "geometry": { "type": "Point", "coordinates": [ -1.8785266, 50.7465036 ] } },
{ "type": "Feature", "properties": { "osm_id": 13806212112, "name": null, "amenity": "bench", "man_made": null, "leisure": null, "playground": null, "memorial": null }, "geometry": { "type": "Point", "coordinates": [ -1.8782541, 50.7465753 ] } },
{ "type": "Feature", "properties": { "osm_id": 13806225370, "name": null, "amenity": "bench", "man_made": null, "leisure": null, "playground": null, "memorial": null }, "geometry": { "type": "Point", "coordinates": [ -1.8784004, 50.7465759 ] } },
{ "type": "Feature", "properties": { "osm_id": 13806210010, "name": null, "amenity": "bench", "man_made": null, "leisure": null, "playground": null, "memorial": null }, "geometry": { "type": "Point", "coordinates": [ -1.8785002, 50.7465893 ] } }
]
}
